Workbook

Sheet Instructions
A1: INSTRUCTIONS
A3: Why we use Excel
A14: Exporting from ARGUS to Excel
A15: 1 | B15: Select "PROPERTY REPORTS" > "CASH FLOW" from reports tab
A20: 2 | B20: Select "REPORT" > "REPORT OPTIONS"
A29: 3 | B29: Scroll down midway and select "YES" for "PRINT OCCUPANCY SUMMARY"
A58: 4 | B58: Select "EXPORT" > "MICROSOFT EXCEL"

Sheet Property Summary
A2: PROPERTY INFORMATION | F2: REVERSION CALCULATION | K2: RETURN SUMMARY
A3: Property | B3: The Empire State Building | C3: Address | D3: 350 Fifth Avenue | F3: Sale Year | G3: =D6 -> 10 | I3: =INDEX(Proforma!$E$4:$P$4,MATCH(G3,Proforma!$E$3:$P$3,0)) -> 48944 | K3: Deal Unleveraged Profit | L3: =M3/$B$4 -> 688.226 | M3: =SUMIF($B$33:$M$33,">0",$B$33:$M$33)+SUMIF($B$33:$M$33,"<0",$B$33:$M$33) -> 1.9329288e+09
A4: RBA | B4: 2808567 | C4: City, State | D4: New York, NY | H4: PSF | I4: $ | K4: Deal Unleveraged IRR | M4: =XIRR(B33:M33,B18:M18) -> 0.08357549
A5: Purchase Price | B5: ='Observatory Analysis'!B5+'Building Analysis'!B5 -> 2.1392098e+09 | F5: Gross Sales Price | H5: =I5/$B$4 -> 892.57906 | I5: =SUM('Observatory Analysis'!$D$5+'Building Analysis'!$I$9) -> 2.5068681e+09 | K5: Deal Unleveraged Multiple | M5: =SUMIF(B33:M33,">"&0,B33:M33)/-SUMIF(B33:M33,"<"&0,B33:M33) -> 1.9035714
A6: Purchase Price (PSF) | B6: =B5/B4 -> 761.67307 | C6: Hold Period | D6: 10 | F6: Selling Expense | G6: 0.02 | H6: =I6/$B$4 -> -17.851581 | I6: =-I5*G6 -> -50137362 | K6: Deal Leveraged Profit | L6: =M6/$B$4 -> 429.13215 | M6: =SUMIF($B$41:$M$41,">0",$B$41:$M$41)+SUMIF($B$41:$M$41,"<0",$B$41:$M$41) -> 1.2052464e+09
A7: Going-In Cap Rate | B7: =B9/B5 -> 0.083974999 | C7: Analysis Start Date | D7: 45292 | F7: Net Sales Price | H7: =I7/$B$4 -> 874.72748 | I7: =SUM(I5:I6) -> 2.4567307e+09 | K7: Deal Leveraged IRR | M7: =XIRR(B41:M41,B18:M18) -> 0.095341793
A8: In Place Occupancy | B8: =C19 -> 0.88421604 | C8: Analysis End Date | D8: =EOMONTH(D7-1,D6*12) -> 48944 | F8: ="PV of Net Sales Price @ "&TEXT(M4,"0.00%")&" Discount Rate" -> PV of Net Sales Price @ 8.36% Discount Rate | H8: =I8/$B$4 -> 391.99546 | I8: =I7/(1+M4)^G3 -> 1.1009455e+09 | K8: Deal Leveraged Multiple | M8: =SUMIF(B41:M41,">"&0,B41:M41)/-SUMIF(B41:M41,"<"&0,B41:M41) -> 2.1268146
A9: YR1 NOI | B9: =C22 -> 179640144 | C9: ="Exit Forward NOI - YR"&D6&"" -> Exit Forward NOI - YR10 | D9: =INDEX($B$22:$M$22,MATCH($D$6+1,$B$17:$M$17,0)) -> 1.981071e+08 | F9: Less: Loan Balance | H9: =I9/$B$4 -> -347.12265 | I9: =SUM(B37:M37) -> -9.7491723e+08 | K9: ='Property Summary'!$A$60&" Profit" -> Capital Partner Profit | L9: =M9/$B$4 -> 407.67554 | M9: ='Waterfall Model'!R4 -> 1.1449841e+09
F10: Proceeds from Sale | H10: =I10/$B$4 -> 527.60482 | I10: =I7+I9 -> 1.4818135e+09 | K10: ='Property Summary'!$A$60&" IRR" -> Capital Partner IRR | M10: ='Waterfall Model'!P4 -> 0.095341793
A11: DEBT | F11: ="PV of Net Sales Price @ "&TEXT(M4,"0.00%")&" Discount Rate" -> PV of Net Sales Price @ 8.36% Discount Rate | H11: =I11/$B$4 -> 236.43786 | I11: =I10/(1+M4)^G3 -> 6.6405158e+08 | K11: ='Property Summary'!$A$60&" Multiple" -> Capital Partner Multiple | M11: ='Waterfall Model'!Q4 -> 2.1268146
A12: LTC | B12: 0.5 | C12: Loan Proceeds | D12: =B12*B5 -> 1.0696049e+09 | K12: ='Property Summary'!$A$59&" Profit" -> Sponsor Profit | L12: =M12/$B$4 -> 21.456608 | M12: ='Waterfall Model'!N4 -> 60262320
A13: 10YR UST | B13: 0.035 | C13: Term of Loan (Years) | D13: 10 | K13: ='Property Summary'!$A$59&" IRR" -> Sponsor IRR | M13: ='Waterfall Model'!L4 -> 0.095341793
A14: Spread | B14: 0.035 | C14: Interest Only (Years) | D14: 3 | K14: ='Property Summary'!$A$59&" Multiple" -> Sponsor Multiple | M14: ='Waterfall Model'!M4 -> 2.1268146
A15: Rate (Annual) | B15: =SUM(B13:B14) -> 0.07 | C15: Amortization (Years) | D15: 30
A17: CASH FLOW SUMMARY | B17: =Proforma!E3 -> 0 | C17: =Proforma!F3 -> 1 | D17: =Proforma!G3 -> 2 | E17: =Proforma!H3 -> 3 | F17: =Proforma!I3 -> 4 | G17: =Proforma!J3 -> 5 | H17: =Proforma!K3 -> 6 | I17: =Proforma!L3 -> 7 | ... M17: =Proforma!P3 -> 11
A18: Year Ending | B18: =Proforma!E4 -> 45292 | C18: =Proforma!F4 -> 45657 | D18: =Proforma!G4 -> 46022 | E18: =Proforma!H4 -> 46387 | F18: =Proforma!I4 -> 46752 | G18: =Proforma!J4 -> 47118 | H18: =Proforma!K4 -> 47483 | I18: =Proforma!L4 -> 47848 | ... M18: =Proforma!P4 -> 49309
A19: Average Occupancy | B19: - | C19: =Proforma!F6 -> 0.88421604 | D19: =Proforma!G6 -> 0.91714992 | E19: =Proforma!H6 -> 0.97081074 | F19: =Proforma!I6 -> 0.97584097 | G19: =Proforma!J6 -> 0.96203111 | H19: =Proforma!K6 -> 0.90869332 | I19: =Proforma!L6 -> 0.99193005 | J19: =Proforma!M6 -> 0.99292729 | ... M19: =Proforma!P6 -> 0.96345829
A20: Building NOI | B20: =Proforma!E37 -> 0 | C20: =Proforma!F37 -> 87248544 | D20: =Proforma!G37 -> 91652523 | E20: =Proforma!H37 -> 95756622 | F20: =Proforma!I37 -> 98326799 | G20: =Proforma!J37 -> 96446550 | H20: =Proforma!K37 -> 71090813 | I20: =Proforma!L37 -> 80711654 | ... M20: =Proforma!P37 -> 85482252
A21: Observatory NOI | B21: ='Observatory Analysis'!B13 -> 0 | C21: ='Observatory Analysis'!C13 -> 92391600 | D21: ='Observatory Analysis'!D13 -> 94239432 | E21: ='Observatory Analysis'!E13 -> 96124221 | F21: ='Observatory Analysis'!F13 -> 98046705 | G21: ='Observatory Analysis'!G13 -> 1.0000764e+08 | H21: ='Observatory Analysis'!H13 -> 1.0200779e+08 | I21: ='Observatory Analysis'!I13 -> 1.0404795e+08 | ... M21: ='Observatory Analysis'!M13 -> 1.1262484e+08
A22: PROPERTY LEVEL NOI | B22: 0 | C22: =C20+C21 -> 179640144 | D22: =D20+D21 -> 185891955 | E22: =E20+E21 -> 1.9188084e+08 | F22: =F20+F21 -> 1.963735e+08 | G22: =G20+G21 -> 1.9645419e+08 | H22: =H20+H21 -> 1.730986e+08 | I22: =I20+I21 -> 1.847596e+08 | J22: =J20+J21 -> 1.8835507e+08 | ... M22: =M20+M21 -> 1.981071e+08
A23: NOI Growth | B23: - | C23: 0 | D23: =(D22-C22)/C22 -> 0.034801859 | E23: =(E22-D22)/D22 -> 0.032217035 | F23: =(F22-E22)/E22 -> 0.023413809 | G23: =(G22-F22)/F22 -> 0.0004108757 | H23: =(H22-G22)/G22 -> -0.11888565 | I23: =(I22-H22)/H22 -> 0.067366209 | J23: =(J22-I22)/I22 -> 0.019460266 | K23: =(K22-J22)/J22 -> 0.015309257 | ... M23: =(M22-L22)/L22 -> 0.011380824
A25: Leasing Costs | B25: =-Proforma!E42 -> 0 | C25: =-Proforma!F42 -> -52346631 | D25: =-Proforma!G42 -> -34717449 | E25: =-Proforma!H42 -> -21201215 | F25: =-Proforma!I42 -> -15202057 | G25: =-Proforma!J42 -> -12932417 | H25: =-Proforma!K42 -> -75397937 | I25: =-Proforma!L42 -> -4731266 | ... M25: =-Proforma!P42 -> -18345095
A26: Building Capital Expenditures | B26: =-Proforma!E43 -> 0 | C26: =-Proforma!F43 -> -10608333 | D26: =-Proforma!G43 -> -10608833 | E26: =-Proforma!H43 -> -10609343 | F26: =-Proforma!I43 -> -4976530 | G26: =-Proforma!J43 -> -2227061 | H26: =-Proforma!K43 -> -27602 | I26: =-Proforma!L43 -> -28154 | ... M26: =-Proforma!P43 -> -30475
A27: Total Capital Improvements | B27: =SUM(B25:B26) -> 0 | C27: =SUM(C25:C26) -> -62954964 | D27: =SUM(D25:D26) -> -45326282 | E27: =SUM(E25:E26) -> -31810558 | F27: =SUM(F25:F26) -> -20178587 | G27: =SUM(G25:G26) -> -15159478 | H27: =SUM(H25:H26) -> -75425539 | I27: =SUM(I25:I26) -> -4759420 | ... M27: =SUM(M25:M26) -> -18375570
A29: Cash Flow Before Debt Service | C29: =C22+C27 -> 116685180 | D29: =D22+D27 -> 140565673 | E29: =E22+E27 -> 1.6007028e+08 | F29: =F22+F27 -> 1.7619492e+08 | G29: =G22+G27 -> 1.8129471e+08 | H29: =H22+H27 -> 97673066 | I29: =I22+I27 -> 1.8000018e+08 | J29: =J22+J27 -> 1.8308825e+08 | ... M29: =M22+M27 -> 1.7973153e+08
A31: ="Building Net Reversion " -> Building Net Reversion | C31: =IF(C17=$D$6,$I$7,0) -> 0 | D31: =IF(D17=$D$6,$I$7,0) -> 0 | E31: =IF(E17=$D$6,$I$7,0) -> 0 | F31: =IF(F17=$D$6,$I$7,0) -> 0 | G31: =IF(G17=$D$6,$I$7,0) -> 0 | H31: =IF(H17=$D$6,$I$7,0) -> 0 | I31: =IF(I17=$D$6,$I$7,0) -> 0 | J31: =IF(J17=$D$6,$I$7,0) -> 0 | ... M31: =IF(M17=$D$6,$I$7,0) -> 0
A33: Unleveraged Cash Flow | B33: =-B5*(B17<=$G$3) -> -2.1392098e+09 | C33: =SUM(C29,C31)*(C17<=$G$3) -> 116685180 | D33: =SUM(D29,D31)*(D17<=$G$3) -> 140565673 | E33: =SUM(E29,E31)*(E17<=$G$3) -> 1.6007028e+08 | F33: =SUM(F29,F31)*(F17<=$G$3) -> 1.7619492e+08 | G33: =SUM(G29,G31)*(G17<=$G$3) -> 1.8129471e+08 | H33: =SUM(H29,H31)*(H17<=$G$3) -> 97673066 | I33: =SUM(I29,I31)*(I17<=$G$3) -> 1.8000018e+08 | J33: =SUM(J29,J31)*(J17<=$G$3) -> 1.8308825e+08 | ... M33: =SUM(M29,M31)*(M17<=$G$3) -> 0
A35: Loan Proceeds | B35: =D12 -> 1.0696049e+09 | C35: 0 | D35: 0 | E35: 0 | F35: 0 | G35: 0 | H35: 0 | I35: 0 | J35: 0 | K35: 0 | L35: 0 | M35: 0
A36: Debt Service | B36: =SUM(Proforma!E53:E54) -> 0 | C36: =SUM(Proforma!F53:F54) -> -74872345 | D36: =SUM(Proforma!G53:G54) -> -74872345 | E36: =SUM(Proforma!H53:H54) -> -74872345 | F36: =SUM(Proforma!I53:I54) -> -85393299 | G36: =SUM(Proforma!J53:J54) -> -85393299 | H36: =SUM(Proforma!K53:K54) -> -85393299 | I36: =SUM(Proforma!L53:L54) -> -85393299 | ... M36: =SUM(Proforma!P53:P54) -> 0
A37: Principal Payoff | B37: =Proforma!E55 -> 0 | C37: =Proforma!F55 -> 0 | D37: =Proforma!G55 -> 0 | E37: =Proforma!H55 -> 0 | F37: =Proforma!I55 -> 0 | G37: =Proforma!J55 -> 0 | H37: =Proforma!K55 -> 0 | I37: =Proforma!L55 -> 0 | ... M37: =Proforma!P55 -> 0
A38: Total Financing | B38: =SUM(B35:B37) -> 1.0696049e+09 | C38: =SUM(C35:C37) -> -74872345 | D38: =SUM(D35:D37) -> -74872345 | E38: =SUM(E35:E37) -> -74872345 | F38: =SUM(F35:F37) -> -85393299 | G38: =SUM(G35:G37) -> -85393299 | H38: =SUM(H35:H37) -> -85393299 | I38: =SUM(I35:I37) -> -85393299 | ... M38: =SUM(M35:M37) -> 0
A39: DSCR | B39: - | C39: =IFERROR(-C22/C36,"") -> 2.3992857 | D39: =IFERROR(-D22/D36,"") -> 2.4827853 | E39: =IFERROR(-E22/E36,"") -> 2.5627733 | F39: =IFERROR(-F22/F36,"") -> 2.299636 | G39: =IFERROR(-G22/G36,"") -> 2.3005809 | H39: =IFERROR(-H22/H36,"") -> 2.0270748 | I39: =IFERROR(-I22/I36,"") -> 2.1636312 | J39: =IFERROR(-J22/J36,"") -> 2.205736 | ... M39: =IFERROR(-M22/M36,"")
A40: Debt Yield | B40: - | C40: =C22/$B$35 -> 0.16795 | D40: =D22/$B$35 -> 0.17379497 | E40: =E22/$B$35 -> 0.17939413 | F40: =F22/$B$35 -> 0.18359443 | G40: =G22/$B$35 -> 0.18366986 | H40: =H22/$B$35 -> 0.16183415 | I40: =I22/$B$35 -> 0.1727363 | J40: =J22/$B$35 -> 0.1760978 | ... M40: =M22/$B$35 -> 0.18521521
A41: Leveraged Cash Flow | B41: =B33+B38*(B17<=$D$6) -> -1.0696049e+09 | C41: =C33+C38*(C17<=$D$6) -> 41812835 | D41: =D33+D38*(D17<=$D$6) -> 65693328 | E41: =E33+E38*(E17<=$D$6) -> 85197940 | F41: =F33+F38*(F17<=$D$6) -> 90801618 | G41: =G33+G38*(G17<=$D$6) -> 95901412 | H41: =H33+H38*(H17<=$D$6) -> 12279767 | I41: =I33+I38*(I17<=$D$6) -> 94606883 | ... M41: =M33+M38*(M17<=$D$6) -> 0
A42: Cash on Cash | C42: =((C36+C29)/-$B$41)*(C17<=$D$13) -> 0.03909185 | D42: =((D36+D29)/-$B$41)*(D17<=$D$13) -> 0.061418312 | E42: =((E36+E29)/-$B$41)*(E17<=$D$13) -> 0.079653654 | F42: =((F36+F29)/-$B$41)*(F17<=$D$13) -> 0.084892671 | G42: =((G36+G29)/-$B$41)*(G17<=$D$13) -> 0.089660594 | H42: =((H36+H29)/-$B$41)*(H17<=$D$13) -> 0.011480657 | I42: =((I36+I29)/-$B$41)*(I17<=$D$13) -> 0.088450306 | J42: =((J36+J29)/-$B$41)*(J17<=$D$13) -> 0.091337418 | ... M42: =((M36+M29)/-$B$41)*(M17<=$D$13) -> 0
A44: SOURCES AND USES | E44: SENSITIVITIES
A45: Sources | B45: % | C45: Amount | E45: PURCHASE PRICE | F45: ="Unlevered IRR & Equity Multiple " -> Unlevered IRR & Equity Multiple | J45: ="Levered IRR & Equity Multiple " -> Levered IRR & Equity Multiple | S45: UL Hold Period Sensitivity | Y45: L Hold Period Sensitivity
A46: Debt | B46: =C46/$C$49 -> 0.44430391 | C46: =D12 -> 1.0696049e+09 | F46: =T46 -> 3 | G46: =U46 -> 5 | H46: =V46 -> 7 | I46: =W46 -> 10 | J46: =Z46 -> 3 | K46: =AA46 -> 5 | L46: =AB46 -> 7 | M46: =AC46 -> 10 | S46: =TEXT(M4,"0.00%")&" - "&TEXT(M5,"0.00x") -> 8.36% - 1.90x | T46: =W46-7 -> 3 | U46: =W46-5 -> 5 | V46: =W46-3 -> 7 | W46: 10 | Y46: =TEXT(M7,"0.00%")&" - "&TEXT(M8,"0.00x") -> 9.53% - 2.13x | Z46: =AC46-7 -> 3 | AA46: =AC46-5 -> 5 | AB46: =AC46-3 -> 7 | AC46: 10
A47: Equity | B47: =C47/$C$49 -> 0.44430391 | C47: =B5-C46 -> 1.0696049e+09 | E47: =TEXT(S47/1000000,"$#,000")&"B - "&TEXT(R47,"0.00%")&" Going-In Cap" -> $2,339B - 7.68% Going-In Cap | F47: =T47 -> 7.24% - 1.22x | G47: =U47 -> 5.05% - 1.25x | H47: =V47 -> 6.36% - 1.45x | I47: =W47 -> 7.11% - 1.74x | J47: =Z47 -> 10.05% - 1.32x | K47: =AA47 -> 4.34% - 1.22x | L47: =AB47 -> 6.26% - 1.46x | M47: =AC47 -> 7.23% - 1.80x | R47: =$B$9/S47 -> 0.076795224 | S47: =S48+$F$52 -> 2339209844 | T47: 7.24% - 1.22x | U47: 5.05% - 1.25x | V47: 6.36% - 1.45x | W47: 7.11% - 1.74x | Y47: =Y48+$F$52 -> 2339209844 | Z47: 10.05% - 1.32x | AA47: 4.34% - 1.22x | AB47: 6.26% - 1.46x | AC47: 7.23% - 1.80x
A48: Cash Flow | B48: =C48/$C$49 -> 0.11139218 | C48: =C54-SUM(C46:C47) -> 268162461 | E48: =TEXT(S48/1000000,"$#,000")&"B - "&TEXT(R48,"0.00%")&" Going-In Cap" -> $2,239B - 8.02% Going-In Cap | F48: =T48 -> 8.90% - 1.28x | G48: =U48 -> 6.09% - 1.30x | H48: =V48 -> 7.15% - 1.51x | I48: =W48 -> 7.72% - 1.82x | J48: =Z48 -> 13.12% - 1.43x | K48: =AA48 -> 6.38% - 1.33x | L48: =AB48 -> 7.78% - 1.59x | M48: =AC48 -> 8.36% - 1.96x | R48: =$B$9/S48 -> 0.080224792 | S48: =S49+$F$52 -> 2239209844 | T48: 8.90% - 1.28x | U48: 6.09% - 1.30x | V48: 7.15% - 1.51x | W48: 7.72% - 1.82x | Y48: =Y49+$F$52 -> 2239209844 | Z48: 13.12% - 1.43x | AA48: 6.38% - 1.33x | AB48: 7.78% - 1.59x | AC48: 8.36% - 1.96x
A49: Total Sources | B49: =SUM(B46:B48) -> 1 | C49: =SUM(C46:C48) -> 2.4073723e+09 | E49: =TEXT(S49/1000000,"$#,000")&"B - "&TEXT(R49,"0.00%")&" Going-In Cap" -> $2,139B - 8.40% Going-In Cap | F49: =T49 -> 10.66% - 1.34x | G49: =U49 -> 7.18% - 1.37x | H49: =V49 -> 7.99% - 1.58x | I49: =W49 -> 8.36% - 1.90x | J49: =Z49 -> 16.32% - 1.55x | K49: =AA49 -> 8.48% - 1.45x | L49: =AB49 -> 9.34% - 1.73x | M49: =AC49 -> 9.53% - 2.13x | R49: =$B$9/S49 -> 0.083974999 | S49: 2139209844 | T49: 10.66% - 1.34x | U49: 7.18% - 1.37x | V49: 7.99% - 1.58x | W49: 8.36% - 1.90x | Y49: 2139209844 | Z49: 16.32% - 1.55x | AA49: 8.48% - 1.45x | AB49: 9.34% - 1.73x | AC49: 9.53% - 2.13x
A50: Uses | B50: % | C50: Amount | E50: =TEXT(S50/1000000,"$#,000")&"B - "&TEXT(R50,"0.00%")&" Going-In Cap" -> $2,039B - 8.81% Going-In Cap | F50: =T50 -> 12.53% - 1.40x | G50: =U50 -> 8.35% - 1.43x | H50: =V50 -> 8.88% - 1.66x | I50: =W50 -> 9.04% - 2.00x | J50: =Z50 -> 19.66% - 1.68x | K50: =AA50 -> 10.64% - 1.58x | L50: =AB50 -> 10.95% - 1.88x | M50: =AC50 -> 10.75% - 2.31x | R50: =$B$9/S50 -> 0.088093015 | S50: =S49-$F$52 -> 2039209844 | T50: 12.53% - 1.40x | U50: 8.35% - 1.43x | V50: 8.88% - 1.66x | W50: 9.04% - 2.00x | Y50: =Y49-$F$52 -> 2039209844 | Z50: 19.66% - 1.68x | AA50: 10.64% - 1.58x | AB50: 10.95% - 1.88x | AC50: 10.75% - 2.31x
A51: Purchase Price | B51: =C51/$C$54 -> 0.88860782 | C51: =-B33 -> 2.1392098e+09 | E51: =TEXT(S51/1000000,"$#,000")&"B - "&TEXT(R51,"0.00%")&" Going-In Cap" -> $1,939B - 9.26% Going-In Cap | F51: =T51 -> 14.54% - 1.47x | G51: =U51 -> 9.58% - 1.51x | H51: =V51 -> 9.82% - 1.75x | I51: =W51 -> 9.77% - 2.10x | J51: =Z51 -> 23.17% - 1.83x | K51: =AA51 -> 12.89% - 1.73x | L51: =AB51 -> 12.64% - 2.05x | M51: =AC51 -> 12.02% - 2.52x | R51: =$B$9/S51 -> 0.092635743 | S51: =S50-$F$52 -> 1939209844 | T51: 14.54% - 1.47x | U51: 9.58% - 1.51x | V51: 9.82% - 1.75x | W51: 9.77% - 2.10x | Y51: =Y50-$F$52 -> 1939209844 | Z51: 23.17% - 1.83x | AA51: 12.89% - 1.73x | AB51: 12.64% - 2.05x | AC51: 12.02% - 2.52x
A52: Capital Improvements | B52: =C52/$C$54 -> 0.11139218 | C52: =-SUMIF($C$17:$M$17,"<="&G3,C27:M27) -> 268162461 | E52: Pricing Sensitivity: | F52: 100000000
A54: Total Uses | B54: =SUM(B51:B53) -> 1 | C54: =SUM(C51:C53) -> 2.4073723e+09
A56: PARTNERSHIP ASSUMPTIONS | J56: RETURN METRICS
C57: Initial Contribution | D57: Preferred Return | E57: Promote up to Hurdle | F57: Hurdle Rate | G57: Promote over Hurdle | J57: Cap Rate | K57: Hold Period Avg. Cash on Cash | L57: Unlevered IRR | M57: Levered IRR
J58: =C22/-B33 -> 0.083974999 | K58: =AVERAGEIF($C$17:$M$17,"<="&D6,C42:M42) -> 0.07414306 | L58: =IRR(B33:M33) -> 0.083618202 | M58: =IRR(B41:M41) -> 0.095391292
A59: Sponsor | B59: 0.05 | C59: =-'Waterfall Model'!$G$11*B59 -> 53480246 | D59: 0.1 | E59: 0.325 | F59: 0.15 | G59: 0.46 | J59: Equity Multiple | K59: LTV | L59: DSCR | M59: Debt Yield
A60: Capital Partner | B60: =1-B59 -> 0.95 | C60: =-'Waterfall Model'!$G$11*B60 -> 1.0161247e+09 | D60: =D59 -> 0.1 | E60: =1-E59 -> 0.675 | F60: =D59 -> 0.1 | G60: =1-G59 -> 0.54 | J60: =SUMIF(B41:M41,">"&0,B41:M41)/-SUMIF(B41:M41,"<"&0,B41:M41) -> 2.1268146 | K60: =B35/-B33 -> 0.5 | L60: =C22/-C38 -> 2.3992857 | M60: =C22/B35 -> 0.16795

Sheet Observatory Analysis
A1: OBSERVATION DECK ANALYSIS INPUTS
A2: Revenue Est. Ending 2023 | B2: 129400000 | C2: Hold Period | D2: ='Building Analysis'!D6 -> 10
A3: Avg Growth Rate | B3: =AVERAGEIF($C$8:$M$8,"<="&$D$2,$C$10:$M$10) -> 0.02 | C3: Operating Expenses | D3: 0.3
A4: Discount Rate | B4: 0.09 | C4: Exit Cap Rate | D4: 0.08
A5: Observatory PV | B5: =SUM(C18:M18) -> 1.2349265e+09 | C5: Exit Value | D5: =INDEX($B$13:$M$13,MATCH($D$2+1,$B$8:$M$8,0))/D4 -> 1.4078106e+09
A6: Going-In Cap Rate | B6: =C13/B5 -> 0.074815464
B8: =Proforma!E3 -> 0 | C8: =Proforma!F3 -> 1 | D8: =Proforma!G3 -> 2 | E8: =Proforma!H3 -> 3 | F8: =Proforma!I3 -> 4 | G8: =Proforma!J3 -> 5 | H8: =Proforma!K3 -> 6 | I8: =Proforma!L3 -> 7 | ... M8: =Proforma!P3 -> 11
A9: YEAR ENDING | B9: =EOMONTH(C9,-12) -> 45291 | C9: =Proforma!F4 -> 45657 | D9: =Proforma!G4 -> 46022 | E9: =Proforma!H4 -> 46387 | F9: =Proforma!I4 -> 46752 | G9: =Proforma!J4 -> 47118 | H9: =Proforma!K4 -> 47483 | I9: =Proforma!L4 -> 47848 | J9: =Proforma!M4 -> 48213 | ... M9: =Proforma!P4 -> 49309
A10: Growth Rate | C10: 0.02 | D10: 0.02 | E10: 0.02 | F10: 0.02 | G10: 0.02 | H10: 0.02 | I10: 0.02 | J10: 0.02 | K10: 0.02 | L10: 0.02 | M10: 0.02
A11: OBSERVATORY REVENUE | C11: =$B$2*(1+C10) -> 131988000 | D11: =C11*(1+D10) -> 134627760 | E11: =D11*(1+E10) -> 1.3732032e+08 | F11: =E11*(1+F10) -> 1.4006672e+08 | G11: =F11*(1+G10) -> 1.4286806e+08 | H11: =G11*(1+H10) -> 1.4572542e+08 | I11: =H11*(1+I10) -> 1.4863993e+08 | J11: =I11*(1+J10) -> 1.5161272e+08 | K11: =J11*(1+K10) -> 1.5464498e+08 | ... M11: =L11*(1+M10) -> 1.6089264e+08
A12: OPERATING EXPENSES | C12: =C11*$D$3 -> 39596400 | D12: =D11*$D$3 -> 40388328 | E12: =E11*$D$3 -> 41196095 | F12: =F11*$D$3 -> 42020016 | G12: =G11*$D$3 -> 42860417 | H12: =H11*$D$3 -> 43717625 | I12: =I11*$D$3 -> 44591978 | J12: =J11*$D$3 -> 45483817 | ... M12: =M11*$D$3 -> 48267791
A13: NOI | C13: =C11-C12 -> 92391600 | D13: =D11-D12 -> 94239432 | E13: =E11-E12 -> 96124221 | F13: =F11-F12 -> 98046705 | G13: =G11-G12 -> 1.0000764e+08 | H13: =H11-H12 -> 1.0200779e+08 | I13: =I11-I12 -> 1.0404795e+08 | J13: =J11-J12 -> 1.0612891e+08 | ... M13: =M11-M12 -> 1.1262484e+08
A14: Reversion | B14: =$D$5*(B8=$D$2) -> 0 | C14: =$D$5*(C8=$D$2) -> 0 | D14: =$D$5*(D8=$D$2) -> 0 | E14: =$D$5*(E8=$D$2) -> 0 | F14: =$D$5*(F8=$D$2) -> 0 | G14: =$D$5*(G8=$D$2) -> 0 | H14: =$D$5*(H8=$D$2) -> 0 | I14: =$D$5*(I8=$D$2) -> 0 | ... M14: =$D$5*(M8=$D$2) -> 0
A16: NOI PRESENT VALUE | C16: =(C13/(1+$B$4)^C$8)*(C8<=$D$2) -> 84762936 | D16: =(D13/(1+$B$4)^D$8)*(D8<=$D$2) -> 79319444 | E16: =(E13/(1+$B$4)^E$8)*(E8<=$D$2) -> 74225535 | F16: =(F13/(1+$B$4)^F$8)*(F8<=$D$2) -> 69458758 | G16: =(G13/(1+$B$4)^G$8)*(G8<=$D$2) -> 64998104 | H16: =(H13/(1+$B$4)^H$8)*(H8<=$D$2) -> 60823913 | I16: =(I13/(1+$B$4)^I$8)*(I8<=$D$2) -> 56917791 | J16: =(J13/(1+$B$4)^J$8)*(J8<=$D$2) -> 53262520 | ... M16: =(M13/(1+$B$4)^M$8)*(M8<=$D$2) -> 0
A17: REVERSION PRESENT VALUE | C17: =C14/(1+$B$4)^C$8 -> 0 | D17: =D14/(1+$B$4)^D$8 -> 0 | E17: =E14/(1+$B$4)^E$8 -> 0 | F17: =F14/(1+$B$4)^F$8 -> 0 | G17: =G14/(1+$B$4)^G$8 -> 0 | H17: =H14/(1+$B$4)^H$8 -> 0 | I17: =I14/(1+$B$4)^I$8 -> 0 | J17: =J14/(1+$B$4)^J$8 -> 0 | ... M17: =M14/(1+$B$4)^M$8 -> 0
A18: TOTAL PRESENT VALUE | C18: =SUM(C16:C17) -> 84762936 | D18: =SUM(D16:D17) -> 79319444 | E18: =SUM(E16:E17) -> 74225535 | F18: =SUM(F16:F17) -> 69458758 | G18: =SUM(G16:G17) -> 64998104 | H18: =SUM(H16:H17) -> 60823913 | I18: =SUM(I16:I17) -> 56917791 | J18: =SUM(J16:J17) -> 53262520 | ... M18: =SUM(M16:M17) -> 0
A46: FOR CHART
A47: YR | B47: Historic Revenue | C47: Projected Revenue
A48: 2001 | B48: 25
A49: =A48+1 -> 2002 | B49: 29.6
A50: =A49+1 -> 2003 | B50: 33.4
A51: =A50+1 -> 2004 | B51: 40
A52: =A51+1 -> 2005 | B52: 50.1
A53: =A52+1 -> 2006 | B53: 56.3
A54: =A53+1 -> 2007 | B54: 62.9
A55: =A54+1 -> 2008 | B55: 72.2
A56: =A55+1 -> 2009 | B56: 71.6
A57: =A56+1 -> 2010 | B57: 78.9
A58: =A57+1 -> 2011 | B58: 80.6
A59: =A58+1 -> 2012 | B59: 91.9
A60: =A59+1 -> 2013 | B60: 101.8
... A69: =A68+1 -> 2022 | B69: 61.8
A70: =A69+1 -> 2023 | C70: =B2/1000000 -> 129.4
A71: =A70+1 -> 2024 | C71: =C11/1000000 -> 131.988
A72: =A71+1 -> 2025 | C72: =D11/1000000 -> 134.62776
A73: =A72+1 -> 2026 | C73: =E11/1000000 -> 137.32032
A74: =A73+1 -> 2027 | C74: =F11/1000000 -> 140.06672
A75: =A74+1 -> 2028 | C75: =G11/1000000 -> 142.86806
A76: =A75+1 -> 2029 | C76: =H11/1000000 -> 145.72542
A77: =A76+1 -> 2030 | C77: =I11/1000000 -> 148.63993
A78: =A77+1 -> 2031 | C78: =J11/1000000 -> 151.61272
A79: =A78+1 -> 2032 | C79: =K11/1000000 -> 154.64498
A80: =A79+1 -> 2033 | C80: =L11/1000000 -> 157.73788
A81: =A80+1 -> 2034 | C81: =M11/1000000 -> 160.89264

Sheet Building Analysis
A2: PROPERTY INFORMATION | F2: REVERSION CALCULATION | K2: SOURCES AND USES
A3: Property | B3: ='Property Summary'!B3 -> The Empire State Building | C3: Address | D3: ='Property Summary'!D3 -> 350 Fifth Avenue | F3: Sale Year | G3: =D6 -> 10 | I3: =INDEX(Proforma!$E$4:$P$4,MATCH(G3,Proforma!$E$3:$P$3,0)) -> 48944 | K3: Sources | L3: % | M3: Amount
A4: RBA | B4: ='Property Summary'!B4 -> 2808567 | C4: City, State | D4: ='Property Summary'!D4 -> New York, NY | H4: PSF | I4: $
A5: Purchase Price | B5: 904283329 | C5: Exit Cap Rate | D5: 0.07 | F5: Forward NOI | H5: =I5/$B$4 -> 30.436252 | I5: =INDEX(Proforma!$E$37:$P$37,MATCH($G$3+1,Proforma!$E$3:$P$3,0)) -> 85482252 | K5: Equity | L5: =M5/$M$7 -> 0.77127944 | M5: =B5-M4 -> 904283329
A6: Purchase Price (PSF) | B6: =B5/B4 -> 321.97321 | C6: Hold Period | D6: ='Property Summary'!D6 -> 10 | F6: Reversion Vacancy | G6: 0.1 | H6: =I6/$B$4 -> -3.0436252 | I6: =-I5*G6 -> -8548225.2 | K6: Cash Flow | L6: =M6/$M$7 -> 0.22872056 | M6: =M12-SUM(M4:M5) -> 268162461
A7: Going-In Cap Rate | B7: =B9/B5 -> 0.096483636 | C7: Analysis Start Date | D7: ='Property Summary'!D7 -> 45292 | F7: NOI to Capitalize | H7: =I7/$B$4 -> 27.392626 | I7: =SUM(I5:I6) -> 76934027 | K7: Total Sources | L7: =SUM(L4:L6) -> 1 | M7: =SUM(M4:M6) -> 1172445790
A8: In Place Occupancy | B8: =Proforma!F6 -> 0.88421604 | C8: Analysis End Date | D8: =EOMONTH(D7-1,D6*12) -> 48944 | F8: Divide by Exit Cap Rate | I8: =D5 -> 0.07 | K8: Uses | L8: % | M8: Amount
A9: YR1 NOI | B9: =Proforma!F37 -> 87248544 | C9: ="Exit Forward NOI - YR"&D6&"" -> Exit Forward NOI - YR10 | D9: =INDEX(Proforma!$E$37:$P$37,MATCH(D6,Proforma!$E$3:$P$3,0)) -> 85461331 | F9: Gross Sales Price | H9: =I9/$B$4 -> 391.32324 | I9: =I7/I8 -> 1.0990575e+09 | K9: Purchase Price | L9: =M9/$M$12 -> 0.77127944 | M9: =-B33 -> 904283329
F10: Selling Expense | G10: ='Property Summary'!$G$6 -> 0.02 | H10: =I10/$B$4 -> -7.8264647 | I10: =-I9*G10 -> -21981151 | K10: Capital Improvements | L10: =M10/$M$12 -> 0.22872056 | M10: =-SUMIF($C$17:$M$17,"<="&G3,C27:M27) -> 268162461
F11: Net Sales Price | H11: =I11/$B$4 -> 383.49677 | I11: =SUM(I9:I10) -> 1.0770764e+09
A12: RETURN SUMMARY | F12: ="PV of Net Sales Price @ "&TEXT(C14,"0.00%")&" Discount Rate" -> PV of Net Sales Price @ 7.72% Discount Rate | H12: =I12/$B$4 -> 182.36476 | I12: =I11/(1+C14)^G3 -> 5.1218363e+08 | K12: Total Uses | L12: =SUM(L9:L11) -> 1 | M12: =SUM(M9:M11) -> 1172445790
A13: Deal Unleveraged Profit | B13: =C13/$B$4 -> 276.48931 | C13: =Proforma!C62 -> 7.7653875e+08
A14: Deal Unleveraged IRR | C14: =Proforma!C63 -> 0.07716462
A15: Deal Unleveraged Multiple | C15: =Proforma!C64 -> 1.8546372
A17: CASH FLOW SUMMARY | B17: =Proforma!E3 -> 0 | C17: =Proforma!F3 -> 1 | D17: =Proforma!G3 -> 2 | E17: =Proforma!H3 -> 3 | F17: =Proforma!I3 -> 4 | G17: =Proforma!J3 -> 5 | H17: =Proforma!K3 -> 6 | I17: =Proforma!L3 -> 7 | ... M17: =Proforma!P3 -> 11
A18: Year Ending | B18: =Proforma!E4 -> 45292 | C18: =Proforma!F4 -> 45657 | D18: =Proforma!G4 -> 46022 | E18: =Proforma!H4 -> 46387 | F18: =Proforma!I4 -> 46752 | G18: =Proforma!J4 -> 47118 | H18: =Proforma!K4 -> 47483 | I18: =Proforma!L4 -> 47848 | ... M18: =Proforma!P4 -> 49309
A19: Average Occupancy | B19: - | C19: =Proforma!F6 -> 0.88421604 | D19: =Proforma!G6 -> 0.91714992 | E19: =Proforma!H6 -> 0.97081074 | F19: =Proforma!I6 -> 0.97584097 | G19: =Proforma!J6 -> 0.96203111 | H19: =Proforma!K6 -> 0.90869332 | I19: =Proforma!L6 -> 0.99193005 | J19: =Proforma!M6 -> 0.99292729 | ... M19: =Proforma!P6 -> 0.96345829
A20: Effective Gross Income | B20: 0 | C20: =Proforma!F27 -> 174227252 | D20: =Proforma!G27 -> 180905314 | E20: =Proforma!H27 -> 187616360 | F20: =Proforma!I27 -> 192115860 | G20: =Proforma!J27 -> 191791166 | H20: =Proforma!K27 -> 166705609 | I20: =Proforma!L27 -> 179754367 | J20: =Proforma!M27 -> 183262071 | ... M20: =Proforma!P27 -> 192163767
A21: Operating Expenses | B21: =Proforma!E35 -> 0 | C21: =Proforma!F35 -> 86978708 | D21: =Proforma!G35 -> 89252791 | E21: =Proforma!H35 -> 91859738 | F21: =Proforma!I35 -> 93789061 | G21: =Proforma!J35 -> 95344616 | H21: =Proforma!K35 -> 95614796 | I21: =Proforma!L35 -> 99042713 | ... M21: =Proforma!P35 -> 106681515
A22: Net Operating Income | B22: 0 | C22: =C20-C21 -> 87248544 | D22: =D20-D21 -> 91652523 | E22: =E20-E21 -> 95756622 | F22: =F20-F21 -> 98326799 | G22: =G20-G21 -> 96446550 | H22: =H20-H21 -> 71090813 | I22: =I20-I21 -> 80711654 | J22: =J20-J21 -> 82226166 | ... M22: =M20-M21 -> 85482252
A23: NOI Growth | B23: - | C23: 0 | D23: =(D22-C22)/C22 -> 0.050476246 | E23: =(E22-D22)/D22 -> 0.044778898 | F23: =(F22-E22)/E22 -> 0.026840723 | G23: =(G22-F22)/F22 -> -0.019122447 | H23: =(H22-G22)/G22 -> -0.26289937 | I23: =(I22-H22)/H22 -> 0.13533171 | J23: =(J22-I22)/I22 -> 0.018764477 | K23: =(K22-J22)/J22 -> 0.0092549372 | ... M23: =(M22-L22)/L22 -> 0.00024480077
A25: Leasing Costs | B25: =-Proforma!E42 -> 0 | C25: =-Proforma!F42 -> -52346631 | D25: =-Proforma!G42 -> -34717449 | E25: =-Proforma!H42 -> -21201215 | F25: =-Proforma!I42 -> -15202057 | G25: =-Proforma!J42 -> -12932417 | H25: =-Proforma!K42 -> -75397937 | I25: =-Proforma!L42 -> -4731266 | ... M25: =-Proforma!P42 -> -18345095
A26: Building Capital Expenditures | B26: =-Proforma!E43 -> 0 | C26: =-Proforma!F43 -> -10608333 | D26: =-Proforma!G43 -> -10608833 | E26: =-Proforma!H43 -> -10609343 | F26: =-Proforma!I43 -> -4976530 | G26: =-Proforma!J43 -> -2227061 | H26: =-Proforma!K43 -> -27602 | I26: =-Proforma!L43 -> -28154 | ... M26: =-Proforma!P43 -> -30475
A27: Total Capital Improvements | B27: =SUM(B25:B26) -> 0 | C27: =SUM(C25:C26) -> -62954964 | D27: =SUM(D25:D26) -> -45326282 | E27: =SUM(E25:E26) -> -31810558 | F27: =SUM(F25:F26) -> -20178587 | G27: =SUM(G25:G26) -> -15159478 | H27: =SUM(H25:H26) -> -75425539 | I27: =SUM(I25:I26) -> -4759420 | ... M27: =SUM(M25:M26) -> -18375570
A29: Cash Flow Before Debt Service | C29: =(C22+C27)*(C17<=$D$6) -> 24293580 | D29: =(D22+D27)*(D17<=$D$6) -> 46326241 | E29: =(E22+E27)*(E17<=$D$6) -> 63946064 | F29: =(F22+F27)*(F17<=$D$6) -> 78148212 | G29: =(G22+G27)*(G17<=$D$6) -> 81287072 | H29: =(H22+H27)*(H17<=$D$6) -> -4334726 | I29: =(I22+I27)*(I17<=$D$6) -> 75952234 | J29: =(J22+J27)*(J17<=$D$6) -> 76959344 | ... M29: =(M22+M27)*(M17<=$D$6) -> 0
A31: ="Net Reversion @ "&TEXT($D$5,"0.00%")&" Exit Cap" -> Net Reversion @ 7.00% Exit Cap | C31: =Proforma!F47 -> 0 | D31: =Proforma!G47 -> 0 | E31: =Proforma!H47 -> 0 | F31: =Proforma!I47 -> 0 | G31: =Proforma!J47 -> 0 | H31: =Proforma!K47 -> 0 | I31: =Proforma!L47 -> 0 | J31: =Proforma!M47 -> 0 | ... M31: =Proforma!P47 -> 0
A33: Unleveraged Cash Flow | B33: =-B5 -> -904283329 | C33: =SUM(C29,C31)*(C17<=$D$6) -> 24293580 | D33: =SUM(D29,D31)*(D17<=$D$6) -> 46326241 | E33: =SUM(E29,E31)*(E17<=$D$6) -> 63946064 | F33: =SUM(F29,F31)*(F17<=$D$6) -> 78148212 | G33: =SUM(G29,G31)*(G17<=$D$6) -> 81287072 | H33: =SUM(H29,H31)*(H17<=$D$6) -> -4334726 | I33: =SUM(I29,I31)*(I17<=$D$6) -> 75952234 | J33: =SUM(J29,J31)*(J17<=$D$6) -> 76959344 | ... M33: =SUM(M29,M31)*(M17<=$D$6) -> 0
A35: SENSITIVITIES | G35: RETURN METRICS
A36: PURCHASE PRICE | B36: ="Unlevered IRR & Equity Multiple - @ "&TEXT($D$5,"0.00%")&" Exit Cap" -> Unlevered IRR & Equity Multiple - @ 7.00% Exit Cap | G36: Cap Rate | H36: Unlevered IRR | S36: UL Hold Period Sensitivity
B37: =T37 -> 3 | C37: =U37 -> 5 | D37: =V37 -> 7 | E37: =W37 -> 10 | G37: =C22/-B33 -> 0.096483636 | H37: =IRR(B33:M33) -> 0.07716462 | S37: =TEXT(C14,"0.00%")&" - "&TEXT(C15,"0.00x") -> 7.72% - 1.85x | T37: =W37-7 -> 3 | U37: =W37-5 -> 5 | V37: =W37-3 -> 7 | W37: 10
A38: =TEXT(S38/1000000,"$#,000")&"B - "&TEXT(R38,"0.00%")&" Going-In Cap" -> $906B - 9.63% Going-In Cap | B38: =T38 -> 15.31% - 1.52x | C38: =U38 -> 6.11% - 1.31x | D38: =V38 -> 7.32% - 1.55x | E38: =W38 -> 7.70% - 1.85x | R38: =$B$9/S38 -> 0.096333861 | S38: =S39+$B$43 -> 905689265 | T38: 15.31% - 1.52x | U38: 6.11% - 1.31x | V38: 7.32% - 1.55x | W38: 7.70% - 1.85x
A39: =TEXT(S39/1000000,"$#,000")&"B - "&TEXT(R39,"0.00%")&" Going-In Cap" -> $806B - 10.83% Going-In Cap | B39: =T39 -> 20.04% - 1.70x | C39: =U39 -> 8.86% - 1.48x | D39: =V39 -> 9.42% - 1.74x | E39: =W39 -> 9.28% - 2.08x | R39: =$B$9/S39 -> 0.10829056 | S39: =S40+$B$43 -> 805689265 | T39: 20.04% - 1.70x | U39: 8.86% - 1.48x | V39: 9.42% - 1.74x | W39: 9.28% - 2.08x
A40: =TEXT(S40/1000000,"$#,000")&"B - "&TEXT(R40,"0.00%")&" Going-In Cap" -> $706B - 12.36% Going-In Cap | B40: =T40 -> 25.63% - 1.95x | C40: =U40 -> 12.09% - 1.69x | D40: =V40 -> 11.87% - 1.98x | E40: =W40 -> 11.14% - 2.37x | R40: =$B$9/S40 -> 0.12363592 | S40: 705689265 | T40: 25.63% - 1.95x | U40: 12.09% - 1.69x | V40: 11.87% - 1.98x | W40: 11.14% - 2.37x
A41: =TEXT(S41/1000000,"$#,000")&"B - "&TEXT(R41,"0.00%")&" Going-In Cap" -> $606B - 14.40% Going-In Cap | B41: =T41 -> 32.43% - 2.27x | C41: =U41 -> 15.96% - 1.96x | D41: =V41 -> 14.80% - 2.30x | E41: =W41 -> 13.37% - 2.76x | R41: =$B$9/S41 -> 0.14404836 | S41: =S40-$B$43 -> 605689265 | T41: 32.43% - 2.27x | U41: 15.96% - 1.96x | V41: 14.80% - 2.30x | W41: 13.37% - 2.76x
A42: =TEXT(S42/1000000,"$#,000")&"B - "&TEXT(R42,"0.00%")&" Going-In Cap" -> $506B - 17.25% Going-In Cap | B42: =T42 -> 40.96% - 2.72x | C42: =U42 -> 20.74% - 2.35x | D42: =V42 -> 18.42% - 2.76x | E42: =W42 -> 16.14% - 3.30x | R42: =$B$9/S42 -> 0.17253391 | S42: =S41-$B$43 -> 505689265 | T42: 40.96% - 2.72x | U42: 20.74% - 2.35x | V42: 18.42% - 2.76x | W42: 16.14% - 3.30x
A43: Pricing Sensitivity: | B43: 100000000

Sheet ARGUS MLAs
A1: ARGUS INPUT UNDERWRITING ASSUMPTIONS
A3: Property Assumptions | K3: MARKET LEASING PROFILE ASSUMPTIONS | M3: MLA 1 | N3: MLA 2 | O3: MLA 3 | P3: MLA 4 | Q3: MLA 5
A4: Rentable Building Area | I4: 2808567 | K4: Market Inflation | M4: High Rise Office | N4: Mid Rise Office | O4: Low Rise Office | P4: Retail | Q4: Antenna
A5: Vacant Square Feet | I5: 455384 | K5: 45657 | L5: 0 | M5: 70 | N5: 65 | O5: 60 | P5: 70 | Q5: 550
A6: Current Occupancy | I6: =I4-I5 -> 2353183 | K6: =EOMONTH(K5,12) -> 46022 | L6: 0 | M6: =M5*(1+$L6) -> 70 | N6: =N5*(1+$L6) -> 65 | O6: =O5*(1+$L6) -> 60 | P6: =P5*(1+$L6) -> 70 | Q6: =Q5*(1+$L6) -> 550
K7: =EOMONTH(K6,12) -> 46387 | L7: 0 | M7: =M6*(1+$L7) -> 70 | N7: =N6*(1+$L7) -> 65 | O7: =O6*(1+$L7) -> 60 | P7: =P6*(1+$L7) -> 70 | Q7: =Q6*(1+$L7) -> 550
A8: Global Assumptions | K8: =EOMONTH(K7,12) -> 46752 | L8: 0.01 | M8: =M7*(1+$L8) -> 70.7 | N8: =N7*(1+$L8) -> 65.65 | O8: =O7*(1+$L8) -> 60.6 | P8: =P7*(1+$L8) -> 70.7 | Q8: =Q7*(1+$L8) -> 555.5
A9: Analysis Begin Date | I9: 45292 | K9: =EOMONTH(K8,12) -> 47118 | L9: 0.01 | M9: =M8*(1+$L9) -> 71.407 | N9: =N8*(1+$L9) -> 66.3065 | O9: =O8*(1+$L9) -> 61.206 | P9: =P8*(1+$L9) -> 71.407 | Q9: =Q8*(1+$L9) -> 561.055
A10: Analysis End Date | I10: =EOMONTH(I9,120) -> 48975 | K10: =EOMONTH(K9,12) -> 47483 | L10: 0.015 | M10: =M9*(1+$L10) -> 72.478105 | N10: =N9*(1+$L10) -> 67.301097 | O10: =O9*(1+$L10) -> 62.12409 | P10: =P9*(1+$L10) -> 72.478105 | Q10: =Q9*(1+$L10) -> 569.47082
A11: Term of Analysis | I11: 10 | K11: =EOMONTH(K10,12) -> 47848 | L11: 0.02 | M11: =M10*(1+$L11) -> 73.927667 | N11: =N10*(1+$L11) -> 68.647119 | O11: =O10*(1+$L11) -> 63.366572 | P11: =P10*(1+$L11) -> 73.927667 | Q11: =Q10*(1+$L11) -> 580.86024
A12: General Inflation Rate | I12: 0.03 | K12: =EOMONTH(K11,12) -> 48213 | L12: 0.025 | M12: =M11*(1+$L12) -> 75.775859 | N12: =N11*(1+$L12) -> 70.363297 | O12: =O11*(1+$L12) -> 64.950736 | P12: =P11*(1+$L12) -> 75.775859 | Q12: =Q11*(1+$L12) -> 595.38175
A13: Market Inflation Rate | I13: 0.015 | K13: =EOMONTH(K12,12) -> 48579 | L13: 0.025 | M13: =M12*(1+$L13) -> 77.670255 | N13: =N12*(1+$L13) -> 72.12238 | O13: =O12*(1+$L13) -> 66.574504 | P13: =P12*(1+$L13) -> 77.670255 | Q13: =Q12*(1+$L13) -> 610.26629
A14: Expense Inflation Rate | I14: 0.02 | K14: =EOMONTH(K13,12) -> 48944 | L14: 0.03 | M14: =M13*(1+$L14) -> 80.000363 | N14: =N13*(1+$L14) -> 74.286051 | O14: =O13*(1+$L14) -> 68.57174 | P14: =P13*(1+$L14) -> 80.000363 | Q14: =Q13*(1+$L14) -> 628.57428
A15: General Vacancy | I15: 0.1 | K15: Term
A16: Credit Loss | I16: 0.01 | K16: Lease Term | M16: 10 | N16: 10 | O16: 10 | P16: 7 | Q16: 5
A17: Management Fees - YR1 | I17: 0.03 | K17: Renewal Probability | M17: 0.6 | N17: 0.6 | O17: 0.6 | P17: 0.6 | Q17: 0.7
A18: Capital Reserve | K18: Downtime
K19: Months Vacant | M19: 12 | N19: 12 | O19: 12 | P19: 6 | Q19: 6
A20: Year 1 Operating Expenses | K20: Weighted Average | M20: =(M19*M$17)+(0*(1-M$17)) -> 7.2 | N20: =(N19*N$17)+(0*(1-N$17)) -> 7.2 | O20: =(O19*O$17)+(0*(1-O$17)) -> 7.2 | P20: =(P19*P$17)+(0*(1-P$17)) -> 3.6 | Q20: =(Q19*Q$17)+(0*(1-Q$17)) -> 4.2
A21: Real estate taxes | H21: =I21/$I$6 -> 18.281621 | I21: 43020000 | K21: Rent
A22: Insurance | H22: =I22/$I$6 -> 1.4441571 | I22: 3398366 | K22: Market Rent | M22: 70 | N22: 65 | O22: 60 | P22: 70 | Q22: 550
A23: Utilities | H23: =I23/$I$6 -> 2.3322751 | I23: 5488270 | K23: Rent Steps | M23: 0.01 | N23: 0.01 | O23: 0.01 | P23: 0.01
A24: Repairs and maint. | H24: =I24/$I$6 -> 3.9670094 | I24: 9335099 | K24: Free Rent
A25: Management fees | H25: =I25/$I$6 -> 2.2211694 | I25: 5226818 | K25: New | M25: 2 | N25: 4 | O25: 4 | P25: 2 | Q25: 0
A26: Payroll and benefits | H26: =I26/$I$6 -> 3.2821752 | I26: 7723559 | K26: Renew | M26: 2 | N26: 2 | O26: 2 | P26: 2 | Q26: 0
A27: Adv. and marketing | H27: =I27/$I$6 -> 0.60768754 | I27: 1430000 | K27: Weighted Average | M27: =(M26*M$17)+(M25*(1-M$17)) -> 2 | N27: =(N26*N$17)+(N25*(1-N$17)) -> 2.8 | O27: =(O26*O$17)+(O25*(1-O$17)) -> 2.8 | P27: =(P26*P$17)+(P25*(1-P$17)) -> 2 | Q27: =(Q26*Q$17)+(Q25*(1-Q$17)) -> 0
A28: Security | H28: =I28/$I$6 -> 2.259993 | I28: 5318177 | K28: Tenant Improvements
A29: Janitorial and cleaning | H29: =I29/$I$6 -> 2.5660643 | I29: 6038419 | K29: New | M29: 100 | N29: 75 | O29: 60 | P29: 45 | Q29: 0
H30: =I30/$I$6 -> 0 | K30: Renew | M30: 50 | N30: 40 | O30: 30 | P30: 25 | Q30: 0
A31: Total Year 1 Expenses | H31: =SUM(H21:H30) -> 36.962152 | I31: =SUM(I21:I30) -> 86978708 | K31: Weighted Average | M31: =(M30*M$17)+(M29*(1-M$17)) -> 70 | N31: =(N30*N$17)+(N29*(1-N$17)) -> 54 | O31: =(O30*O$17)+(O29*(1-O$17)) -> 42 | P31: =(P30*P$17)+(P29*(1-P$17)) -> 33 | Q31: =(Q30*Q$17)+(Q29*(1-Q$17)) -> 0
K32: Leasing Commissions
A33: Vacant Suite Lease-Up Assumptions | K33: New | M33: 0.06 | N33: 0.06 | O33: 0.06 | P33: 0.06
A34: Type | C34: Floor | F34: Square Feet | I34: Category | K34: Renew | M34: 0.03 | N34: 0.03 | O34: 0.03 | P34: 0.03
A35: Retail | C35: Ground | F35: 15389 | I35: Retail | K35: Weighted Average | M35: =(M34*M$17)+(M33*(1-M$17)) -> 0.042 | N35: =(N34*N$17)+(N33*(1-N$17)) -> 0.042 | O35: =(O34*O$17)+(O33*(1-O$17)) -> 0.042 | P35: =(P34*P$17)+(P33*(1-P$17)) -> 0.042 | Q35: =(Q34*Q$17)+(Q33*(1-Q$17)) -> 0
A36: Retail | C36: Ground | F36: 2758 | I36: Retail | K36: Expense Recovery
A37: Retail | C37: Ground | F37: 5561 | I37: Retail | K37: Recovery Type | M37: BASE YR STOP | N37: BASE YR STOP | O37: BASE YR STOP | P37: NET | Q37: -
A38: Office - Low | C38: 5th | F38: 35110 | I38: Big Block | K38: Assigned Tenants1
A39: Office - Low | C39: 7th | F39: 52116 | I39: Big Block | K39: Tenants | M39: FDIC | N39: LinkedIn | O39: Revolution LLC | P39: Starbucks | Q39: Broadcast 1
A40: Office - Low | C40: 8th | F40: 51703 | I40: Big Block | M40: COTY, Inc. | N40: Human Rights Watch, Inc. | O40: Phillips Engineering | P40: ABC Global | Q40: Broadcast 2
A41: Office - Low | C41: 9th | F41: 51988 | I41: Big Block | M41: Shutterstock | N41: Global Brands Group | O41: Chattaway Partners | P41: Pacific Century Cyberworks | Q41: Broadcast 3
A42: Office - Low | C42: 10th | F42: 51971 | I42: Big Block | M42: Centric Brands | N42: JCDecaux North America | O42: Oasis | P42: Elj Marketing Service Inc | Q42: Broadcast 4
A43: Office - Low | C43: 11th | F43: 35087 | I43: Big Block | M43: HNTB | N43: Kaltex North America | O43: Midtown Eye | P43: Walgreens | Q43: Broadcast 5
A44: Office - Mid | C44: 37th | F44: 25349 | I44: Full Floor | N44: USI | O44: Showtime Pictures | P44: AT&T Wireless | Q44: Broadcast 6
A45: Office - Mid | C45: 59th | F45: 26018 | I45: Full Floor | N45: Impact | O45: Global Brands Group | P45: Smartbox | Q45: Broadcast 7
A46: Office - Mid | C46: 68th | F46: 26620 | I46: Full Floor | N46: Skanska | O46: Algonquin Legal Associates | P46: Isde | Q46: Broadcast 8
A47: Office - High | C47: 78th | F47: 23186 | I47: Full Floor | N47: ZS Associates, Inc. | O47: Langley Stanton | P47: Citizen Watch Company Of America | Q47: Broadcast 9
A48: Office - Low | C48: 21st | F48: 37181 | I48: Spec | N48: Funaro & Co., P.C. | O48: Pantheon Capital | P48: Retail Concepts LLC | Q48: Broadcast 10
A49: Office - Mid | C49: 47th | F49: 3112 | I49: Spec | N49: Workday | O49: Signature Partners | P49: Rocket Pharma
A50: Office - Mid | C50: 47th | F50: 7668 | I50: Spec | N50: Dufry | O50: Stanley, Stanley and Drunkenmiller | P50: Chipotle
A51: Office - Mid | C51: 76th | F51: 4567 | I51: Spec | N51: Others1 | O51: Others1 | P51: Others1
A52: Total | F52: =SUM(F35:F51) -> 455384 | K52: 1 If more than 10 tenants - see the rent roll for all tenants and their assigned MLAs

Sheet Proforma
A1: ='Building Analysis'!B3 -> The Empire State Building
A2: ='Building Analysis'!B4 -> 2808567
E3: 0 | F3: 1 | G3: =F3+1 -> 2 | H3: =G3+1 -> 3 | I3: =H3+1 -> 4 | J3: =I3+1 -> 5 | K3: =J3+1 -> 6 | L3: =K3+1 -> 7 | M3: =L3+1 -> 8 | N3: =M3+1 -> 9 | ... P3: =O3+1 -> 11
E4: ='Building Analysis'!$D$7 -> 45292 | F4: =EOMONTH(E4,11) -> 45657 | G4: =EOMONTH(F4,12) -> 46022 | H4: =EOMONTH(G4,12) -> 46387 | I4: =EOMONTH(H4,12) -> 46752 | J4: =EOMONTH(I4,12) -> 47118 | K4: =EOMONTH(J4,12) -> 47483 | L4: =EOMONTH(K4,12) -> 47848 | M4: =EOMONTH(L4,12) -> 48213 | N4: =EOMONTH(M4,12) -> 48579 | ... P4: =EOMONTH(O4,12) -> 49309
A6: Average Occupancy Percentage | F6: =SUMIFS(INDEX('Argus Cash Flow Drop'!$B$1:$Z$98,0,MATCH(Proforma!F$3,'Argus Cash Flow Drop'!$B$1:$Z$1,0)),'Argus Cash Flow Drop'!$B$1:$B$98,Proforma!$A6) -> 0.88421604 | G6: =SUMIFS(INDEX('Argus Cash Flow Drop'!$B$1:$Z$98,0,MATCH(Proforma!G$3,'Argus Cash Flow Drop'!$B$1:$Z$1,0)),'Argus Cash Flow Drop'!$B$1:$B$98,Proforma!$A6) -> 0.91714992 | H6: =SUMIFS(INDEX('Argus Cash Flow Drop'!$B$1:$Z$98,0,MATCH(Proforma!H$3,'Argus Cash Flow Drop'!$B$1:$Z$1,0)),'Argus Cash Flow Drop'!$B$1:$B$98,Proforma!$A6) -> 0.97081074 | I6: =SUMIFS(INDEX('Argus Cash Flow Drop'!$B$1:$Z$98,0,MATCH(Proforma!I$3,'Argus Cash Flow Drop'!$B$1:$Z$1,0)),'Argus Cash Flow Drop'!$B$1:$B$98,Proforma!$A6) -> 0.97584097 | J6: =SUMIFS(INDEX('Argus Cash Flow Drop'!$B$1:$Z$98,0,MATCH(Proforma!J$3,'Argus Cash Flow Drop'!$B$1:$Z$1,0)),'Argus Cash Flow Drop'!$B$1:$B$98,Proforma!$A6) -> 0.96203111 | K6: =SUMIFS(INDEX('Argus Cash Flow Drop'!$B$1:$Z$98,0,MATCH(Proforma!K$3,'Argus Cash Flow Drop'!$B$1:$Z$1,0)),'Argus Cash Flow Drop'!$B$1:$B$98,Proforma!$A6) -> 0.90869332 | L6: =SUMIFS(INDEX('Argus Cash Flow Drop'!$B$1:$Z$98,0,MATCH(Proforma!L$3,'Argus Cash Flow Drop'!$B$1:$Z$1,0)),'Argus Cash Flow Drop'!$B$1:$B$98,Proforma!$A6) -> 0.99193005 | M6: =SUMIFS(INDEX('Argus Cash Flow Drop'!$B$1:$Z$98,0,MATCH(Proforma!M$3,'Argus Cash Flow Drop'!$B$1:$Z$1,0)),'Argus Cash Flow Drop'!$B$1:$B$98,Proforma!$A6) -> 0.99292729 | ... P6: =SUMIFS(INDEX('Argus Cash Flow Drop'!$B$1:$Z$98,0,MATCH(Proforma!P$3,'Argus Cash Flow Drop'!$B$1:$Z$1,0)),'Argus Cash Flow Drop'!$B$1:$B$98,Proforma!$A6) -> 0.96345829
A7: Vacant Area | F7: =SUMIFS(INDEX('Argus Cash Flow Drop'!$B$1:$Z$98,0,MATCH(Proforma!F$3,'Argus Cash Flow Drop'!$B$1:$Z$1,0)),'Argus Cash Flow Drop'!$B$1:$B$98,Proforma!$A7) -> 325187 | G7: =SUMIFS(INDEX('Argus Cash Flow Drop'!$B$1:$Z$98,0,MATCH(Proforma!G$3,'Argus Cash Flow Drop'!$B$1:$Z$1,0)),'Argus Cash Flow Drop'!$B$1:$B$98,Proforma!$A7) -> 232690 | H7: =SUMIFS(INDEX('Argus Cash Flow Drop'!$B$1:$Z$98,0,MATCH(Proforma!H$3,'Argus Cash Flow Drop'!$B$1:$Z$1,0)),'Argus Cash Flow Drop'!$B$1:$B$98,Proforma!$A7) -> 81980 | I7: =SUMIFS(INDEX('Argus Cash Flow Drop'!$B$1:$Z$98,0,MATCH(Proforma!I$3,'Argus Cash Flow Drop'!$B$1:$Z$1,0)),'Argus Cash Flow Drop'!$B$1:$B$98,Proforma!$A7) -> 67852 | J7: =SUMIFS(INDEX('Argus Cash Flow Drop'!$B$1:$Z$98,0,MATCH(Proforma!J$3,'Argus Cash Flow Drop'!$B$1:$Z$1,0)),'Argus Cash Flow Drop'!$B$1:$B$98,Proforma!$A7) -> 106638 | K7: =SUMIFS(INDEX('Argus Cash Flow Drop'!$B$1:$Z$98,0,MATCH(Proforma!K$3,'Argus Cash Flow Drop'!$B$1:$Z$1,0)),'Argus Cash Flow Drop'!$B$1:$B$98,Proforma!$A7) -> 256441 | L7: =SUMIFS(INDEX('Argus Cash Flow Drop'!$B$1:$Z$98,0,MATCH(Proforma!L$3,'Argus Cash Flow Drop'!$B$1:$Z$1,0)),'Argus Cash Flow Drop'!$B$1:$B$98,Proforma!$A7) -> 22665 | M7: =SUMIFS(INDEX('Argus Cash Flow Drop'!$B$1:$Z$98,0,MATCH(Proforma!M$3,'Argus Cash Flow Drop'!$B$1:$Z$1,0)),'Argus Cash Flow Drop'!$B$1:$B$98,Proforma!$A7) -> 19864 | ... P7: =SUMIFS(INDEX('Argus Cash Flow Drop'!$B$1:$Z$98,0,MATCH(Proforma!P$3,'Argus Cash Flow Drop'!$B$1:$Z$1,0)),'Argus Cash Flow Drop'!$B$1:$B$98,Proforma!$A7) -> 102630
A9: POTENTIAL GROSS REVENUE | C9: YR1 / SF
A10: Potential Base Rent | C10: =F10/$A$2/12 -> 5.7185232 | E10: 0 | F10: =SUMIFS(INDEX('Argus Cash Flow Drop'!$B$1:$Z$98,0,MATCH(Proforma!F$3,'Argus Cash Flow Drop'!$B$1:$Z$1,0)),'Argus Cash Flow Drop'!$B$1:$B$98,Proforma!$A10) -> 192730265 | G10: =SUMIFS(INDEX('Argus Cash Flow Drop'!$B$1:$Z$98,0,MATCH(Proforma!G$3,'Argus Cash Flow Drop'!$B$1:$Z$1,0)),'Argus Cash Flow Drop'!$B$1:$B$98,Proforma!$A10) -> 196665836 | H10: =SUMIFS(INDEX('Argus Cash Flow Drop'!$B$1:$Z$98,0,MATCH(Proforma!H$3,'Argus Cash Flow Drop'!$B$1:$Z$1,0)),'Argus Cash Flow Drop'!$B$1:$B$98,Proforma!$A10) -> 201172086 | I10: =SUMIFS(INDEX('Argus Cash Flow Drop'!$B$1:$Z$98,0,MATCH(Proforma!I$3,'Argus Cash Flow Drop'!$B$1:$Z$1,0)),'Argus Cash Flow Drop'!$B$1:$B$98,Proforma!$A10) -> 203672189 | J10: =SUMIFS(INDEX('Argus Cash Flow Drop'!$B$1:$Z$98,0,MATCH(Proforma!J$3,'Argus Cash Flow Drop'!$B$1:$Z$1,0)),'Argus Cash Flow Drop'!$B$1:$B$98,Proforma!$A10) -> 201866506 | K10: =SUMIFS(INDEX('Argus Cash Flow Drop'!$B$1:$Z$98,0,MATCH(Proforma!K$3,'Argus Cash Flow Drop'!$B$1:$Z$1,0)),'Argus Cash Flow Drop'!$B$1:$B$98,Proforma!$A10) -> 189739704 | L10: =SUMIFS(INDEX('Argus Cash Flow Drop'!$B$1:$Z$98,0,MATCH(Proforma!L$3,'Argus Cash Flow Drop'!$B$1:$Z$1,0)),'Argus Cash Flow Drop'!$B$1:$B$98,Proforma!$A10) -> 188872887 | M10: =SUMIFS(INDEX('Argus Cash Flow Drop'!$B$1:$Z$98,0,MATCH(Proforma!M$3,'Argus Cash Flow Drop'!$B$1:$Z$1,0)),'Argus Cash Flow Drop'!$B$1:$B$98,Proforma!$A10) -> 191192600 | ... P10: =SUMIFS(INDEX('Argus Cash Flow Drop'!$B$1:$Z$98,0,MATCH(Proforma!P$3,'Argus Cash Flow Drop'!$B$1:$Z$1,0)),'Argus Cash Flow Drop'!$B$1:$B$98,Proforma!$A10) -> 197724472
A11: Absorption & Turnover Vacancy | C11: =F11/$A$2/12 -> -0.59065035 | E11: 0 | F11: =SUMIFS(INDEX('Argus Cash Flow Drop'!$B$1:$Z$98,0,MATCH(Proforma!F$3,'Argus Cash Flow Drop'!$B$1:$Z$1,0)),'Argus Cash Flow Drop'!$B$1:$B$98,Proforma!$A11) -> -19906573 | G11: =SUMIFS(INDEX('Argus Cash Flow Drop'!$B$1:$Z$98,0,MATCH(Proforma!G$3,'Argus Cash Flow Drop'!$B$1:$Z$1,0)),'Argus Cash Flow Drop'!$B$1:$B$98,Proforma!$A11) -> -14667121 | H11: =SUMIFS(INDEX('Argus Cash Flow Drop'!$B$1:$Z$98,0,MATCH(Proforma!H$3,'Argus Cash Flow Drop'!$B$1:$Z$1,0)),'Argus Cash Flow Drop'!$B$1:$B$98,Proforma!$A11) -> -5159640 | I11: =SUMIFS(INDEX('Argus Cash Flow Drop'!$B$1:$Z$98,0,MATCH(Proforma!I$3,'Argus Cash Flow Drop'!$B$1:$Z$1,0)),'Argus Cash Flow Drop'!$B$1:$B$98,Proforma!$A11) -> -4447950 | J11: =SUMIFS(INDEX('Argus Cash Flow Drop'!$B$1:$Z$98,0,MATCH(Proforma!J$3,'Argus Cash Flow Drop'!$B$1:$Z$1,0)),'Argus Cash Flow Drop'!$B$1:$B$98,Proforma!$A11) -> -7092471 | K11: =SUMIFS(INDEX('Argus Cash Flow Drop'!$B$1:$Z$98,0,MATCH(Proforma!K$3,'Argus Cash Flow Drop'!$B$1:$Z$1,0)),'Argus Cash Flow Drop'!$B$1:$B$98,Proforma!$A11) -> -17970691 | L11: =SUMIFS(INDEX('Argus Cash Flow Drop'!$B$1:$Z$98,0,MATCH(Proforma!L$3,'Argus Cash Flow Drop'!$B$1:$Z$1,0)),'Argus Cash Flow Drop'!$B$1:$B$98,Proforma!$A11) -> -1492850 | M11: =SUMIFS(INDEX('Argus Cash Flow Drop'!$B$1:$Z$98,0,MATCH(Proforma!M$3,'Argus Cash Flow Drop'!$B$1:$Z$1,0)),'Argus Cash Flow Drop'!$B$1:$B$98,Proforma!$A11) -> -1401642 | ... P11: =SUMIFS(INDEX('Argus Cash Flow Drop'!$B$1:$Z$98,0,MATCH(Proforma!P$3,'Argus Cash Flow Drop'!$B$1:$Z$1,0)),'Argus Cash Flow Drop'!$B$1:$B$98,Proforma!$A11) -> -7352362
A12: Free Rent | C12: =F12/$A$2/12 -> -0.17943406 | E12: 0 | F12: =SUMIFS(INDEX('Argus Cash Flow Drop'!$B$1:$Z$98,0,MATCH(Proforma!F$3,'Argus Cash Flow Drop'!$B$1:$Z$1,0)),'Argus Cash Flow Drop'!$B$1:$B$98,Proforma!$A12) -> -6047431 | G12: =SUMIFS(INDEX('Argus Cash Flow Drop'!$B$1:$Z$98,0,MATCH(Proforma!G$3,'Argus Cash Flow Drop'!$B$1:$Z$1,0)),'Argus Cash Flow Drop'!$B$1:$B$98,Proforma!$A12) -> -5519907 | H12: =SUMIFS(INDEX('Argus Cash Flow Drop'!$B$1:$Z$98,0,MATCH(Proforma!H$3,'Argus Cash Flow Drop'!$B$1:$Z$1,0)),'Argus Cash Flow Drop'!$B$1:$B$98,Proforma!$A12) -> -4347120 | I12: =SUMIFS(INDEX('Argus Cash Flow Drop'!$B$1:$Z$98,0,MATCH(Proforma!I$3,'Argus Cash Flow Drop'!$B$1:$Z$1,0)),'Argus Cash Flow Drop'!$B$1:$B$98,Proforma!$A12) -> -2773989 | J12: =SUMIFS(INDEX('Argus Cash Flow Drop'!$B$1:$Z$98,0,MATCH(Proforma!J$3,'Argus Cash Flow Drop'!$B$1:$Z$1,0)),'Argus Cash Flow Drop'!$B$1:$B$98,Proforma!$A12) -> -2060532 | K12: =SUMIFS(INDEX('Argus Cash Flow Drop'!$B$1:$Z$98,0,MATCH(Proforma!K$3,'Argus Cash Flow Drop'!$B$1:$Z$1,0)),'Argus Cash Flow Drop'!$B$1:$B$98,Proforma!$A12) -> -9599230 | L12: =SUMIFS(INDEX('Argus Cash Flow Drop'!$B$1:$Z$98,0,MATCH(Proforma!L$3,'Argus Cash Flow Drop'!$B$1:$Z$1,0)),'Argus Cash Flow Drop'!$B$1:$B$98,Proforma!$A12) -> -859887 | M12: =SUMIFS(INDEX('Argus Cash Flow Drop'!$B$1:$Z$98,0,MATCH(Proforma!M$3,'Argus Cash Flow Drop'!$B$1:$Z$1,0)),'Argus Cash Flow Drop'!$B$1:$B$98,Proforma!$A12) -> -928928 | ... P12: =SUMIFS(INDEX('Argus Cash Flow Drop'!$B$1:$Z$98,0,MATCH(Proforma!P$3,'Argus Cash Flow Drop'!$B$1:$Z$1,0)),'Argus Cash Flow Drop'!$B$1:$B$98,Proforma!$A12) -> -2382661
A13: Scheduled Base Rent | C13: =SUM(C10:C12) -> 4.9484387 | E13: 0 | F13: =SUM(F10:F12) -> 166776261 | G13: =SUM(G10:G12) -> 176478808 | H13: =SUM(H10:H12) -> 191665326 | I13: =SUM(I10:I12) -> 196450250 | J13: =SUM(J10:J12) -> 192713503 | K13: =SUM(K10:K12) -> 162169783 | L13: =SUM(L10:L12) -> 186520150 | M13: =SUM(M10:M12) -> 188862030 | ... P13: =SUM(P10:P12) -> 187989449
A15: Other Income
A16: Total Expense Recoveries | C16: =F16/$A$2/12 -> 0.31643373 | E16: 0 | F16: =SUMIFS(INDEX('Argus Cash Flow Drop'!$B$1:$Z$98,0,MATCH(Proforma!F$3,'Argus Cash Flow Drop'!$B$1:$Z$1,0)),'Argus Cash Flow Drop'!$B$1:$B$98,Proforma!$A16) -> 10664704 | G16: =SUMIFS(INDEX('Argus Cash Flow Drop'!$B$1:$Z$98,0,MATCH(Proforma!G$3,'Argus Cash Flow Drop'!$B$1:$Z$1,0)),'Argus Cash Flow Drop'!$B$1:$B$98,Proforma!$A16) -> 12357653 | H16: =SUMIFS(INDEX('Argus Cash Flow Drop'!$B$1:$Z$98,0,MATCH(Proforma!H$3,'Argus Cash Flow Drop'!$B$1:$Z$1,0)),'Argus Cash Flow Drop'!$B$1:$B$98,Proforma!$A16) -> 13921960 | I16: =SUMIFS(INDEX('Argus Cash Flow Drop'!$B$1:$Z$98,0,MATCH(Proforma!I$3,'Argus Cash Flow Drop'!$B$1:$Z$1,0)),'Argus Cash Flow Drop'!$B$1:$B$98,Proforma!$A16) -> 14912340 | J16: =SUMIFS(INDEX('Argus Cash Flow Drop'!$B$1:$Z$98,0,MATCH(Proforma!J$3,'Argus Cash Flow Drop'!$B$1:$Z$1,0)),'Argus Cash Flow Drop'!$B$1:$B$98,Proforma!$A16) -> 15685452 | K16: =SUMIFS(INDEX('Argus Cash Flow Drop'!$B$1:$Z$98,0,MATCH(Proforma!K$3,'Argus Cash Flow Drop'!$B$1:$Z$1,0)),'Argus Cash Flow Drop'!$B$1:$B$98,Proforma!$A16) -> 11651807 | L16: =SUMIFS(INDEX('Argus Cash Flow Drop'!$B$1:$Z$98,0,MATCH(Proforma!L$3,'Argus Cash Flow Drop'!$B$1:$Z$1,0)),'Argus Cash Flow Drop'!$B$1:$B$98,Proforma!$A16) -> 13941425 | M16: =SUMIFS(INDEX('Argus Cash Flow Drop'!$B$1:$Z$98,0,MATCH(Proforma!M$3,'Argus Cash Flow Drop'!$B$1:$Z$1,0)),'Argus Cash Flow Drop'!$B$1:$B$98,Proforma!$A16) -> 15633018 | ... P16: =SUMIFS(INDEX('Argus Cash Flow Drop'!$B$1:$Z$98,0,MATCH(Proforma!P$3,'Argus Cash Flow Drop'!$B$1:$Z$1,0)),'Argus Cash Flow Drop'!$B$1:$B$98,Proforma!$A16) -> 20489924
A17: Total Tenant Revenue | C17: =SUM(C16:C16) -> 0.31643373 | E17: =SUM(E16:E16) -> 0 | F17: =SUM(F16:F16) -> 10664704 | G17: =SUM(G16:G16) -> 12357653 | H17: =SUM(H16:H16) -> 13921960 | I17: =SUM(I16:I16) -> 14912340 | J17: =SUM(J16:J16) -> 15685452 | K17: =SUM(K16:K16) -> 11651807 | L17: =SUM(L16:L16) -> 13941425 | ... P17: =SUM(P16:P16) -> 20489924
A21: Potential Gross Revenue | C21: =F21/$A$2/12 -> 5.2648725 | E21: =E13+E17+E19 -> 0 | F21: =F13+F17 -> 177440965 | G21: =G13+G17 -> 188836461 | H21: =H13+H17 -> 205587286 | I21: =I13+I17 -> 211362590 | J21: =J13+J17 -> 208398955 | K21: =K13+K17 -> 173821590 | L21: =L13+L17 -> 200461575 | M21: =M13+M17 -> 204495048 | ... P21: =P13+P17 -> 208479373
A23: Vacancy Allowance | C23: =F23/$A$2/12 -> -0.042705735 | E23: 0 | F23: =SUMIFS(INDEX('Argus Cash Flow Drop'!$B$1:$Z$98,0,MATCH(Proforma!F$3,'Argus Cash Flow Drop'!$B$1:$Z$1,0)),'Argus Cash Flow Drop'!$B$1:$B$98,Proforma!$A23) -> -1439303 | G23: =SUMIFS(INDEX('Argus Cash Flow Drop'!$B$1:$Z$98,0,MATCH(Proforma!G$3,'Argus Cash Flow Drop'!$B$1:$Z$1,0)),'Argus Cash Flow Drop'!$B$1:$B$98,Proforma!$A23) -> -6042782 | H23: =SUMIFS(INDEX('Argus Cash Flow Drop'!$B$1:$Z$98,0,MATCH(Proforma!H$3,'Argus Cash Flow Drop'!$B$1:$Z$1,0)),'Argus Cash Flow Drop'!$B$1:$B$98,Proforma!$A23) -> -15915053 | I23: =SUMIFS(INDEX('Argus Cash Flow Drop'!$B$1:$Z$98,0,MATCH(Proforma!I$3,'Argus Cash Flow Drop'!$B$1:$Z$1,0)),'Argus Cash Flow Drop'!$B$1:$B$98,Proforma!$A23) -> -17133104 | J23: =SUMIFS(INDEX('Argus Cash Flow Drop'!$B$1:$Z$98,0,MATCH(Proforma!J$3,'Argus Cash Flow Drop'!$B$1:$Z$1,0)),'Argus Cash Flow Drop'!$B$1:$B$98,Proforma!$A23) -> -14523799 | K23: =SUMIFS(INDEX('Argus Cash Flow Drop'!$B$1:$Z$98,0,MATCH(Proforma!K$3,'Argus Cash Flow Drop'!$B$1:$Z$1,0)),'Argus Cash Flow Drop'!$B$1:$B$98,Proforma!$A23) -> -5377765 | L23: =SUMIFS(INDEX('Argus Cash Flow Drop'!$B$1:$Z$98,0,MATCH(Proforma!L$3,'Argus Cash Flow Drop'!$B$1:$Z$1,0)),'Argus Cash Flow Drop'!$B$1:$B$98,Proforma!$A23) -> -18702592 | M23: =SUMIFS(INDEX('Argus Cash Flow Drop'!$B$1:$Z$98,0,MATCH(Proforma!M$3,'Argus Cash Flow Drop'!$B$1:$Z$1,0)),'Argus Cash Flow Drop'!$B$1:$B$98,Proforma!$A23) -> -19188027 | ... P23: =SUMIFS(INDEX('Argus Cash Flow Drop'!$B$1:$Z$98,0,MATCH(Proforma!P$3,'Argus Cash Flow Drop'!$B$1:$Z$1,0)),'Argus Cash Flow Drop'!$B$1:$B$98,Proforma!$A23) -> -14230812
A24: Credit Loss | C24: =F24/$A$2/12 -> -0.052648735 | E24: 0 | F24: =SUMIFS(INDEX('Argus Cash Flow Drop'!$B$1:$Z$98,0,MATCH(Proforma!F$3,'Argus Cash Flow Drop'!$B$1:$Z$1,0)),'Argus Cash Flow Drop'!$B$1:$B$98,Proforma!$A24) -> -1774410 | G24: =SUMIFS(INDEX('Argus Cash Flow Drop'!$B$1:$Z$98,0,MATCH(Proforma!G$3,'Argus Cash Flow Drop'!$B$1:$Z$1,0)),'Argus Cash Flow Drop'!$B$1:$B$98,Proforma!$A24) -> -1888365 | H24: =SUMIFS(INDEX('Argus Cash Flow Drop'!$B$1:$Z$98,0,MATCH(Proforma!H$3,'Argus Cash Flow Drop'!$B$1:$Z$1,0)),'Argus Cash Flow Drop'!$B$1:$B$98,Proforma!$A24) -> -2055873 | I24: =SUMIFS(INDEX('Argus Cash Flow Drop'!$B$1:$Z$98,0,MATCH(Proforma!I$3,'Argus Cash Flow Drop'!$B$1:$Z$1,0)),'Argus Cash Flow Drop'!$B$1:$B$98,Proforma!$A24) -> -2113626 | J24: =SUMIFS(INDEX('Argus Cash Flow Drop'!$B$1:$Z$98,0,MATCH(Proforma!J$3,'Argus Cash Flow Drop'!$B$1:$Z$1,0)),'Argus Cash Flow Drop'!$B$1:$B$98,Proforma!$A24) -> -2083990 | K24: =SUMIFS(INDEX('Argus Cash Flow Drop'!$B$1:$Z$98,0,MATCH(Proforma!K$3,'Argus Cash Flow Drop'!$B$1:$Z$1,0)),'Argus Cash Flow Drop'!$B$1:$B$98,Proforma!$A24) -> -1738216 | L24: =SUMIFS(INDEX('Argus Cash Flow Drop'!$B$1:$Z$98,0,MATCH(Proforma!L$3,'Argus Cash Flow Drop'!$B$1:$Z$1,0)),'Argus Cash Flow Drop'!$B$1:$B$98,Proforma!$A24) -> -2004616 | M24: =SUMIFS(INDEX('Argus Cash Flow Drop'!$B$1:$Z$98,0,MATCH(Proforma!M$3,'Argus Cash Flow Drop'!$B$1:$Z$1,0)),'Argus Cash Flow Drop'!$B$1:$B$98,Proforma!$A24) -> -2044950 | ... P24: =SUMIFS(INDEX('Argus Cash Flow Drop'!$B$1:$Z$98,0,MATCH(Proforma!P$3,'Argus Cash Flow Drop'!$B$1:$Z$1,0)),'Argus Cash Flow Drop'!$B$1:$B$98,Proforma!$A24) -> -2084794
A25: Total Vacancy & Credit Loss | C25: =SUM(C23:C24) -> -0.09535447 | E25: =SUM(E23:E24) -> 0 | F25: =SUM(F23:F24) -> -3213713 | G25: =SUM(G23:G24) -> -7931147 | H25: =SUM(H23:H24) -> -17970926 | I25: =SUM(I23:I24) -> -19246730 | J25: =SUM(J23:J24) -> -16607789 | K25: =SUM(K23:K24) -> -7115981 | L25: =SUM(L23:L24) -> -20707208 | ... P25: =SUM(P23:P24) -> -16315606
A27: Effective Gross Revenue | C27: =C21+C25 -> 5.169518 | E27: =E21+E25 -> 0 | F27: =F21+F25 -> 174227252 | G27: =G21+G25 -> 180905314 | H27: =H21+H25 -> 187616360 | I27: =I21+I25 -> 192115860 | J27: =J21+J25 -> 191791166 | K27: =K21+K25 -> 166705609 | L27: =L21+L25 -> 179754367 | ... P27: =P21+P25 -> 192163767
A29: OPERATING EXPENSES
A30: CAM | C30: =F30/$A$2/12 -> 0.88554216 | E30: 0 | F30: =SUMIFS(INDEX('Argus Cash Flow Drop'!$A$1:$Z$200,0,MATCH(Proforma!F$3,'Argus Cash Flow Drop'!$A$1:$Z$1,0)),'Argus Cash Flow Drop'!$A$1:$A$200,Proforma!$A30) -> 29845254 | G30: =SUMIFS(INDEX('Argus Cash Flow Drop'!$A$1:$Z$200,0,MATCH(Proforma!G$3,'Argus Cash Flow Drop'!$A$1:$Z$1,0)),'Argus Cash Flow Drop'!$A$1:$A$200,Proforma!$A30) -> 30672357 | H30: =SUMIFS(INDEX('Argus Cash Flow Drop'!$A$1:$Z$200,0,MATCH(Proforma!H$3,'Argus Cash Flow Drop'!$A$1:$Z$1,0)),'Argus Cash Flow Drop'!$A$1:$A$200,Proforma!$A30) -> 31668381 | I30: =SUMIFS(INDEX('Argus Cash Flow Drop'!$A$1:$Z$200,0,MATCH(Proforma!I$3,'Argus Cash Flow Drop'!$A$1:$Z$1,0)),'Argus Cash Flow Drop'!$A$1:$A$200,Proforma!$A30) -> 32338329 | J30: =SUMIFS(INDEX('Argus Cash Flow Drop'!$A$1:$Z$200,0,MATCH(Proforma!J$3,'Argus Cash Flow Drop'!$A$1:$Z$1,0)),'Argus Cash Flow Drop'!$A$1:$A$200,Proforma!$A30) -> 32882661 | K30: =SUMIFS(INDEX('Argus Cash Flow Drop'!$A$1:$Z$200,0,MATCH(Proforma!K$3,'Argus Cash Flow Drop'!$A$1:$Z$1,0)),'Argus Cash Flow Drop'!$A$1:$A$200,Proforma!$A30) -> 33136766 | L30: =SUMIFS(INDEX('Argus Cash Flow Drop'!$A$1:$Z$200,0,MATCH(Proforma!L$3,'Argus Cash Flow Drop'!$A$1:$Z$1,0)),'Argus Cash Flow Drop'!$A$1:$A$200,Proforma!$A30) -> 34441857 | M30: =SUMIFS(INDEX('Argus Cash Flow Drop'!$A$1:$Z$200,0,MATCH(Proforma!M$3,'Argus Cash Flow Drop'!$A$1:$Z$1,0)),'Argus Cash Flow Drop'!$A$1:$A$200,Proforma!$A30) -> 35138544 | ... P30: =SUMIFS(INDEX('Argus Cash Flow Drop'!$A$1:$Z$200,0,MATCH(Proforma!P$3,'Argus Cash Flow Drop'!$A$1:$Z$1,0)),'Argus Cash Flow Drop'!$A$1:$A$200,Proforma!$A30) -> 37043139
A31: REAL ESTATE TAXES | C31: =F31/$A$2/12 -> 1.2764517 | E31: 0 | F31: =SUMIFS(INDEX('Argus Cash Flow Drop'!$A$1:$Z$200,0,MATCH(Proforma!F$3,'Argus Cash Flow Drop'!$A$1:$Z$1,0)),'Argus Cash Flow Drop'!$A$1:$A$200,Proforma!$A31) -> 43020000 | G31: =SUMIFS(INDEX('Argus Cash Flow Drop'!$A$1:$Z$200,0,MATCH(Proforma!G$3,'Argus Cash Flow Drop'!$A$1:$Z$1,0)),'Argus Cash Flow Drop'!$A$1:$A$200,Proforma!$A31) -> 43880400 | H31: =SUMIFS(INDEX('Argus Cash Flow Drop'!$A$1:$Z$200,0,MATCH(Proforma!H$3,'Argus Cash Flow Drop'!$A$1:$Z$1,0)),'Argus Cash Flow Drop'!$A$1:$A$200,Proforma!$A31) -> 44758008 | I31: =SUMIFS(INDEX('Argus Cash Flow Drop'!$A$1:$Z$200,0,MATCH(Proforma!I$3,'Argus Cash Flow Drop'!$A$1:$Z$1,0)),'Argus Cash Flow Drop'!$A$1:$A$200,Proforma!$A31) -> 45653168 | J31: =SUMIFS(INDEX('Argus Cash Flow Drop'!$A$1:$Z$200,0,MATCH(Proforma!J$3,'Argus Cash Flow Drop'!$A$1:$Z$1,0)),'Argus Cash Flow Drop'!$A$1:$A$200,Proforma!$A31) -> 46566232 | K31: =SUMIFS(INDEX('Argus Cash Flow Drop'!$A$1:$Z$200,0,MATCH(Proforma!K$3,'Argus Cash Flow Drop'!$A$1:$Z$1,0)),'Argus Cash Flow Drop'!$A$1:$A$200,Proforma!$A31) -> 47497556 | L31: =SUMIFS(INDEX('Argus Cash Flow Drop'!$A$1:$Z$200,0,MATCH(Proforma!L$3,'Argus Cash Flow Drop'!$A$1:$Z$1,0)),'Argus Cash Flow Drop'!$A$1:$A$200,Proforma!$A31) -> 48447507 | M31: =SUMIFS(INDEX('Argus Cash Flow Drop'!$A$1:$Z$200,0,MATCH(Proforma!M$3,'Argus Cash Flow Drop'!$A$1:$Z$1,0)),'Argus Cash Flow Drop'!$A$1:$A$200,Proforma!$A31) -> 49416457 | ... P31: =SUMIFS(INDEX('Argus Cash Flow Drop'!$A$1:$Z$200,0,MATCH(Proforma!P$3,'Argus Cash Flow Drop'!$A$1:$Z$1,0)),'Argus Cash Flow Drop'!$A$1:$A$200,Proforma!$A31) -> 52441140
A32: UTILITES | C32: =F32/$A$2/12 -> 0.16284313 | E32: 0 | F32: =SUMIFS(INDEX('Argus Cash Flow Drop'!$A$1:$Z$200,0,MATCH(Proforma!F$3,'Argus Cash Flow Drop'!$A$1:$Z$1,0)),'Argus Cash Flow Drop'!$A$1:$A$200,Proforma!$A32) -> 5488270 | G32: =SUMIFS(INDEX('Argus Cash Flow Drop'!$A$1:$Z$200,0,MATCH(Proforma!G$3,'Argus Cash Flow Drop'!$A$1:$Z$1,0)),'Argus Cash Flow Drop'!$A$1:$A$200,Proforma!$A32) -> 5806542 | H32: =SUMIFS(INDEX('Argus Cash Flow Drop'!$A$1:$Z$200,0,MATCH(Proforma!H$3,'Argus Cash Flow Drop'!$A$1:$Z$1,0)),'Argus Cash Flow Drop'!$A$1:$A$200,Proforma!$A32) -> 6269198 | I32: =SUMIFS(INDEX('Argus Cash Flow Drop'!$A$1:$Z$200,0,MATCH(Proforma!I$3,'Argus Cash Flow Drop'!$A$1:$Z$1,0)),'Argus Cash Flow Drop'!$A$1:$A$200,Proforma!$A32) -> 6427715 | J32: =SUMIFS(INDEX('Argus Cash Flow Drop'!$A$1:$Z$200,0,MATCH(Proforma!J$3,'Argus Cash Flow Drop'!$A$1:$Z$1,0)),'Argus Cash Flow Drop'!$A$1:$A$200,Proforma!$A32) -> 6463487 | K32: =SUMIFS(INDEX('Argus Cash Flow Drop'!$A$1:$Z$200,0,MATCH(Proforma!K$3,'Argus Cash Flow Drop'!$A$1:$Z$1,0)),'Argus Cash Flow Drop'!$A$1:$A$200,Proforma!$A32) -> 6227235 | L32: =SUMIFS(INDEX('Argus Cash Flow Drop'!$A$1:$Z$200,0,MATCH(Proforma!L$3,'Argus Cash Flow Drop'!$A$1:$Z$1,0)),'Argus Cash Flow Drop'!$A$1:$A$200,Proforma!$A32) -> 6933606 | M32: =SUMIFS(INDEX('Argus Cash Flow Drop'!$A$1:$Z$200,0,MATCH(Proforma!M$3,'Argus Cash Flow Drop'!$A$1:$Z$1,0)),'Argus Cash Flow Drop'!$A$1:$A$200,Proforma!$A32) -> 7079388 | ... P32: =SUMIFS(INDEX('Argus Cash Flow Drop'!$A$1:$Z$200,0,MATCH(Proforma!P$3,'Argus Cash Flow Drop'!$A$1:$Z$1,0)),'Argus Cash Flow Drop'!$A$1:$A$200,Proforma!$A32) -> 7289734
A33: INSURANCE | C33: =F33/$A$2/12 -> 0.10083333 | E33: 0 | F33: =SUMIFS(INDEX('Argus Cash Flow Drop'!$A$1:$Z$200,0,MATCH(Proforma!F$3,'Argus Cash Flow Drop'!$A$1:$Z$1,0)),'Argus Cash Flow Drop'!$A$1:$A$200,Proforma!$A33) -> 3398366 | G33: =SUMIFS(INDEX('Argus Cash Flow Drop'!$A$1:$Z$200,0,MATCH(Proforma!G$3,'Argus Cash Flow Drop'!$A$1:$Z$1,0)),'Argus Cash Flow Drop'!$A$1:$A$200,Proforma!$A33) -> 3466333 | H33: =SUMIFS(INDEX('Argus Cash Flow Drop'!$A$1:$Z$200,0,MATCH(Proforma!H$3,'Argus Cash Flow Drop'!$A$1:$Z$1,0)),'Argus Cash Flow Drop'!$A$1:$A$200,Proforma!$A33) -> 3535660 | I33: =SUMIFS(INDEX('Argus Cash Flow Drop'!$A$1:$Z$200,0,MATCH(Proforma!I$3,'Argus Cash Flow Drop'!$A$1:$Z$1,0)),'Argus Cash Flow Drop'!$A$1:$A$200,Proforma!$A33) -> 3606373 | J33: =SUMIFS(INDEX('Argus Cash Flow Drop'!$A$1:$Z$200,0,MATCH(Proforma!J$3,'Argus Cash Flow Drop'!$A$1:$Z$1,0)),'Argus Cash Flow Drop'!$A$1:$A$200,Proforma!$A33) -> 3678501 | K33: =SUMIFS(INDEX('Argus Cash Flow Drop'!$A$1:$Z$200,0,MATCH(Proforma!K$3,'Argus Cash Flow Drop'!$A$1:$Z$1,0)),'Argus Cash Flow Drop'!$A$1:$A$200,Proforma!$A33) -> 3752071 | L33: =SUMIFS(INDEX('Argus Cash Flow Drop'!$A$1:$Z$200,0,MATCH(Proforma!L$3,'Argus Cash Flow Drop'!$A$1:$Z$1,0)),'Argus Cash Flow Drop'!$A$1:$A$200,Proforma!$A33) -> 3827112 | M33: =SUMIFS(INDEX('Argus Cash Flow Drop'!$A$1:$Z$200,0,MATCH(Proforma!M$3,'Argus Cash Flow Drop'!$A$1:$Z$1,0)),'Argus Cash Flow Drop'!$A$1:$A$200,Proforma!$A33) -> 3903654 | ... P33: =SUMIFS(INDEX('Argus Cash Flow Drop'!$A$1:$Z$200,0,MATCH(Proforma!P$3,'Argus Cash Flow Drop'!$A$1:$Z$1,0)),'Argus Cash Flow Drop'!$A$1:$A$200,Proforma!$A33) -> 4142589
A34: MGMT FEE | C34: =F34/$A$2/12 -> 0.15508555 | E34: 0 | F34: =SUMIFS(INDEX('Argus Cash Flow Drop'!$A$1:$Z$200,0,MATCH(Proforma!F$3,'Argus Cash Flow Drop'!$A$1:$Z$1,0)),'Argus Cash Flow Drop'!$A$1:$A$200,Proforma!$A34) -> 5226818 | G34: =SUMIFS(INDEX('Argus Cash Flow Drop'!$A$1:$Z$200,0,MATCH(Proforma!G$3,'Argus Cash Flow Drop'!$A$1:$Z$1,0)),'Argus Cash Flow Drop'!$A$1:$A$200,Proforma!$A34) -> 5427159 | H34: =SUMIFS(INDEX('Argus Cash Flow Drop'!$A$1:$Z$200,0,MATCH(Proforma!H$3,'Argus Cash Flow Drop'!$A$1:$Z$1,0)),'Argus Cash Flow Drop'!$A$1:$A$200,Proforma!$A34) -> 5628491 | I34: =SUMIFS(INDEX('Argus Cash Flow Drop'!$A$1:$Z$200,0,MATCH(Proforma!I$3,'Argus Cash Flow Drop'!$A$1:$Z$1,0)),'Argus Cash Flow Drop'!$A$1:$A$200,Proforma!$A34) -> 5763476 | J34: =SUMIFS(INDEX('Argus Cash Flow Drop'!$A$1:$Z$200,0,MATCH(Proforma!J$3,'Argus Cash Flow Drop'!$A$1:$Z$1,0)),'Argus Cash Flow Drop'!$A$1:$A$200,Proforma!$A34) -> 5753735 | K34: =SUMIFS(INDEX('Argus Cash Flow Drop'!$A$1:$Z$200,0,MATCH(Proforma!K$3,'Argus Cash Flow Drop'!$A$1:$Z$1,0)),'Argus Cash Flow Drop'!$A$1:$A$200,Proforma!$A34) -> 5001168 | L34: =SUMIFS(INDEX('Argus Cash Flow Drop'!$A$1:$Z$200,0,MATCH(Proforma!L$3,'Argus Cash Flow Drop'!$A$1:$Z$1,0)),'Argus Cash Flow Drop'!$A$1:$A$200,Proforma!$A34) -> 5392631 | M34: =SUMIFS(INDEX('Argus Cash Flow Drop'!$A$1:$Z$200,0,MATCH(Proforma!M$3,'Argus Cash Flow Drop'!$A$1:$Z$1,0)),'Argus Cash Flow Drop'!$A$1:$A$200,Proforma!$A34) -> 5497862 | ... P34: =SUMIFS(INDEX('Argus Cash Flow Drop'!$A$1:$Z$200,0,MATCH(Proforma!P$3,'Argus Cash Flow Drop'!$A$1:$Z$1,0)),'Argus Cash Flow Drop'!$A$1:$A$200,Proforma!$A34) -> 5764913
A35: Total Operating Expenses | C35: =SUM(C30:C34) -> 2.5807558 | E35: =SUM(E30:E34) -> 0 | F35: =SUM(F30:F34) -> 86978708 | G35: =SUM(G30:G34) -> 89252791 | H35: =SUM(H30:H34) -> 91859738 | I35: =SUM(I30:I34) -> 93789061 | J35: =SUM(J30:J34) -> 95344616 | K35: =SUM(K30:K34) -> 95614796 | L35: =SUM(L30:L34) -> 99042713 | ... P35: =SUM(P30:P34) -> 106681515
A37: Net Operating Income | C37: =C27-C35 -> 2.5887622 | E37: =E27-E35 -> 0 | F37: =F27-F35 -> 87248544 | G37: =G27-G35 -> 91652523 | H37: =H27-H35 -> 95756622 | I37: =I27-I35 -> 98326799 | J37: =J27-J35 -> 96446550 | K37: =K27-K35 -> 71090813 | L37: =L27-L35 -> 80711654 | ... P37: =P27-P35 -> 85482252
A39: LEASING AND CAPITAL COSTS
A40: Tenant Improvements | C40: =F40/$A$2/12 -> 1.0370019 | E40: 0 | F40: =SUMIFS(INDEX('Argus Cash Flow Drop'!$B$1:$Z$98,0,MATCH(Proforma!F$3,'Argus Cash Flow Drop'!$B$1:$Z$1,0)),'Argus Cash Flow Drop'!$B$1:$B$98,Proforma!$A40) -> 34949871 | G40: =SUMIFS(INDEX('Argus Cash Flow Drop'!$B$1:$Z$98,0,MATCH(Proforma!G$3,'Argus Cash Flow Drop'!$B$1:$Z$1,0)),'Argus Cash Flow Drop'!$B$1:$B$98,Proforma!$A40) -> 22950092 | H40: =SUMIFS(INDEX('Argus Cash Flow Drop'!$B$1:$Z$98,0,MATCH(Proforma!H$3,'Argus Cash Flow Drop'!$B$1:$Z$1,0)),'Argus Cash Flow Drop'!$B$1:$B$98,Proforma!$A40) -> 13696597 | I40: =SUMIFS(INDEX('Argus Cash Flow Drop'!$B$1:$Z$98,0,MATCH(Proforma!I$3,'Argus Cash Flow Drop'!$B$1:$Z$1,0)),'Argus Cash Flow Drop'!$B$1:$B$98,Proforma!$A40) -> 10184088 | J40: =SUMIFS(INDEX('Argus Cash Flow Drop'!$B$1:$Z$98,0,MATCH(Proforma!J$3,'Argus Cash Flow Drop'!$B$1:$Z$1,0)),'Argus Cash Flow Drop'!$B$1:$B$98,Proforma!$A40) -> 8652727 | K40: =SUMIFS(INDEX('Argus Cash Flow Drop'!$B$1:$Z$98,0,MATCH(Proforma!K$3,'Argus Cash Flow Drop'!$B$1:$Z$1,0)),'Argus Cash Flow Drop'!$B$1:$B$98,Proforma!$A40) -> 53012645 | L40: =SUMIFS(INDEX('Argus Cash Flow Drop'!$B$1:$Z$98,0,MATCH(Proforma!L$3,'Argus Cash Flow Drop'!$B$1:$Z$1,0)),'Argus Cash Flow Drop'!$B$1:$B$98,Proforma!$A40) -> 3063045 | M40: =SUMIFS(INDEX('Argus Cash Flow Drop'!$B$1:$Z$98,0,MATCH(Proforma!M$3,'Argus Cash Flow Drop'!$B$1:$Z$1,0)),'Argus Cash Flow Drop'!$B$1:$B$98,Proforma!$A40) -> 3405628 | ... P40: =SUMIFS(INDEX('Argus Cash Flow Drop'!$B$1:$Z$98,0,MATCH(Proforma!P$3,'Argus Cash Flow Drop'!$B$1:$Z$1,0)),'Argus Cash Flow Drop'!$B$1:$B$98,Proforma!$A40) -> 11960829
A41: Leasing Commissions | C41: =F41/$A$2/12 -> 0.51618138 | E41: 0 | F41: =SUMIFS(INDEX('Argus Cash Flow Drop'!$B$1:$Z$98,0,MATCH(Proforma!F$3,'Argus Cash Flow Drop'!$B$1:$Z$1,0)),'Argus Cash Flow Drop'!$B$1:$B$98,Proforma!$A41) -> 17396760 | G41: =SUMIFS(INDEX('Argus Cash Flow Drop'!$B$1:$Z$98,0,MATCH(Proforma!G$3,'Argus Cash Flow Drop'!$B$1:$Z$1,0)),'Argus Cash Flow Drop'!$B$1:$B$98,Proforma!$A41) -> 11767357 | H41: =SUMIFS(INDEX('Argus Cash Flow Drop'!$B$1:$Z$98,0,MATCH(Proforma!H$3,'Argus Cash Flow Drop'!$B$1:$Z$1,0)),'Argus Cash Flow Drop'!$B$1:$B$98,Proforma!$A41) -> 7504618 | I41: =SUMIFS(INDEX('Argus Cash Flow Drop'!$B$1:$Z$98,0,MATCH(Proforma!I$3,'Argus Cash Flow Drop'!$B$1:$Z$1,0)),'Argus Cash Flow Drop'!$B$1:$B$98,Proforma!$A41) -> 5017969 | J41: =SUMIFS(INDEX('Argus Cash Flow Drop'!$B$1:$Z$98,0,MATCH(Proforma!J$3,'Argus Cash Flow Drop'!$B$1:$Z$1,0)),'Argus Cash Flow Drop'!$B$1:$B$98,Proforma!$A41) -> 4279690 | K41: =SUMIFS(INDEX('Argus Cash Flow Drop'!$B$1:$Z$98,0,MATCH(Proforma!K$3,'Argus Cash Flow Drop'!$B$1:$Z$1,0)),'Argus Cash Flow Drop'!$B$1:$B$98,Proforma!$A41) -> 22385292 | L41: =SUMIFS(INDEX('Argus Cash Flow Drop'!$B$1:$Z$98,0,MATCH(Proforma!L$3,'Argus Cash Flow Drop'!$B$1:$Z$1,0)),'Argus Cash Flow Drop'!$B$1:$B$98,Proforma!$A41) -> 1668221 | M41: =SUMIFS(INDEX('Argus Cash Flow Drop'!$B$1:$Z$98,0,MATCH(Proforma!M$3,'Argus Cash Flow Drop'!$B$1:$Z$1,0)),'Argus Cash Flow Drop'!$B$1:$B$98,Proforma!$A41) -> 1832477 | ... P41: =SUMIFS(INDEX('Argus Cash Flow Drop'!$B$1:$Z$98,0,MATCH(Proforma!P$3,'Argus Cash Flow Drop'!$B$1:$Z$1,0)),'Argus Cash Flow Drop'!$B$1:$B$98,Proforma!$A41) -> 6384266
A42: Total Leasing Costs | C42: =SUM(C40:C41) -> 1.5531833 | E42: =SUM(E40:E41) -> 0 | F42: =SUM(F40:F41) -> 52346631 | G42: =SUM(G40:G41) -> 34717449 | H42: =SUM(H40:H41) -> 21201215 | I42: =SUM(I40:I41) -> 15202057 | J42: =SUM(J40:J41) -> 12932417 | K42: =SUM(K40:K41) -> 75397937 | L42: =SUM(L40:L41) -> 4731266 | ... P42: =SUM(P40:P41) -> 18345095
A43: Total Capital Expenditures | E43: 0 | F43: =SUMIFS(INDEX('Argus Cash Flow Drop'!$B$1:$Z$98,0,MATCH(Proforma!F$3,'Argus Cash Flow Drop'!$B$1:$Z$1,0)),'Argus Cash Flow Drop'!$B$1:$B$98,Proforma!$A43) -> 10608333 | G43: =SUMIFS(INDEX('Argus Cash Flow Drop'!$B$1:$Z$98,0,MATCH(Proforma!G$3,'Argus Cash Flow Drop'!$B$1:$Z$1,0)),'Argus Cash Flow Drop'!$B$1:$B$98,Proforma!$A43) -> 10608833 | H43: =SUMIFS(INDEX('Argus Cash Flow Drop'!$B$1:$Z$98,0,MATCH(Proforma!H$3,'Argus Cash Flow Drop'!$B$1:$Z$1,0)),'Argus Cash Flow Drop'!$B$1:$B$98,Proforma!$A43) -> 10609343 | I43: =SUMIFS(INDEX('Argus Cash Flow Drop'!$B$1:$Z$98,0,MATCH(Proforma!I$3,'Argus Cash Flow Drop'!$B$1:$Z$1,0)),'Argus Cash Flow Drop'!$B$1:$B$98,Proforma!$A43) -> 4976530 | J43: =SUMIFS(INDEX('Argus Cash Flow Drop'!$B$1:$Z$98,0,MATCH(Proforma!J$3,'Argus Cash Flow Drop'!$B$1:$Z$1,0)),'Argus Cash Flow Drop'!$B$1:$B$98,Proforma!$A43) -> 2227061 | K43: =SUMIFS(INDEX('Argus Cash Flow Drop'!$B$1:$Z$98,0,MATCH(Proforma!K$3,'Argus Cash Flow Drop'!$B$1:$Z$1,0)),'Argus Cash Flow Drop'!$B$1:$B$98,Proforma!$A43) -> 27602 | L43: =SUMIFS(INDEX('Argus Cash Flow Drop'!$B$1:$Z$98,0,MATCH(Proforma!L$3,'Argus Cash Flow Drop'!$B$1:$Z$1,0)),'Argus Cash Flow Drop'!$B$1:$B$98,Proforma!$A43) -> 28154 | M43: =SUMIFS(INDEX('Argus Cash Flow Drop'!$B$1:$Z$98,0,MATCH(Proforma!M$3,'Argus Cash Flow Drop'!$B$1:$Z$1,0)),'Argus Cash Flow Drop'!$B$1:$B$98,Proforma!$A43) -> 28717 | ... P43: =SUMIFS(INDEX('Argus Cash Flow Drop'!$B$1:$Z$98,0,MATCH(Proforma!P$3,'Argus Cash Flow Drop'!$B$1:$Z$1,0)),'Argus Cash Flow Drop'!$B$1:$B$98,Proforma!$A43) -> 30475
A44: Total Leasing and Capital | C44: =SUM(C42:C43) -> 1.5531833 | E44: =SUM(E42:E43) -> 0 | F44: =SUM(F42:F43) -> 62954964 | G44: =SUM(G42:G43) -> 45326282 | H44: =SUM(H42:H43) -> 31810558 | I44: =SUM(I42:I43) -> 20178587 | J44: =SUM(J42:J43) -> 15159478 | K44: =SUM(K42:K43) -> 75425539 | L44: =SUM(L42:L43) -> 4759420 | ... P44: =SUM(P42:P43) -> 18375570
A46: Cash Before Debt Service | E46: =-'Building Analysis'!B5 -> -904283329 | F46: =F37-F44 -> 24293580 | G46: =G37-G44 -> 46326241 | H46: =H37-H44 -> 63946064 | I46: =I37-I44 -> 78148212 | J46: =J37-J44 -> 81287072 | K46: =K37-K44 -> -4334726 | L46: =L37-L44 -> 75952234 | M46: =M37-M44 -> 76959344 | ... P46: =P37-P44 -> 67106682
A47: ="Sales Proceeds"&TEXT('Building Analysis'!$D$5," - 0.00%")&" Exit Cap Rate" -> Sales Proceeds - 7.00% Exit Cap Rate | E47: =IF(E3='Building Analysis'!$D$6,'Building Analysis'!$I$11,0) -> 0 | F47: =IF(F3='Building Analysis'!$D$6,'Building Analysis'!$I$11,0) -> 0 | G47: =IF(G3='Building Analysis'!$D$6,'Building Analysis'!$I$11,0) -> 0 | H47: =IF(H3='Building Analysis'!$D$6,'Building Analysis'!$I$11,0) -> 0 | I47: =IF(I3='Building Analysis'!$D$6,'Building Analysis'!$I$11,0) -> 0 | J47: =IF(J3='Building Analysis'!$D$6,'Building Analysis'!$I$11,0) -> 0 | K47: =IF(K3='Building Analysis'!$D$6,'Building Analysis'!$I$11,0) -> 0 | L47: =IF(L3='Building Analysis'!$D$6,'Building Analysis'!$I$11,0) -> 0 | ... P47: =IF(P3='Building Analysis'!$D$6,'Building Analysis'!$I$11,0) -> 0
A49: Unlevered Cash Flow | C49: =F49/$A$2/12 -> 0.72081777 | E49: =SUM(E46:E47)*(E3<='Building Analysis'!$D$6) -> -904283329 | F49: =SUM(F46:F47)*(F3<='Building Analysis'!$D$6) -> 24293580 | G49: =SUM(G46:G47)*(G3<='Building Analysis'!$D$6) -> 46326241 | H49: =SUM(H46:H47)*(H3<='Building Analysis'!$D$6) -> 63946064 | I49: =SUM(I46:I47)*(I3<='Building Analysis'!$D$6) -> 78148212 | J49: =SUM(J46:J47)*(J3<='Building Analysis'!$D$6) -> 81287072 | K49: =SUM(K46:K47)*(K3<='Building Analysis'!$D$6) -> -4334726 | L49: =SUM(L46:L47)*(L3<='Building Analysis'!$D$6) -> 75952234 | ... P49: =SUM(P46:P47)*(P3<='Building Analysis'!$D$6) -> 0
A51: DEBT SERVICE
A52: Loan Proceeds | E52: ='Building Analysis'!D12 -> 0
A53: Interest Payments | C53: =F53/$A$2/12 -> -2.2215464 | E53: =-SUMIF('Loan Amortization'!$K$27:$K$56,E$3,'Loan Amortization'!$M$27:$M$56) -> 0 | F53: =-SUMIF('Loan Amortization'!$K$27:$K$56,F$3,'Loan Amortization'!$M$27:$M$56) -> -74872345 | G53: =-SUMIF('Loan Amortization'!$K$27:$K$56,G$3,'Loan Amortization'!$M$27:$M$56) -> -74872345 | H53: =-SUMIF('Loan Amortization'!$K$27:$K$56,H$3,'Loan Amortization'!$M$27:$M$56) -> -74872345 | I53: =-SUMIF('Loan Amortization'!$K$27:$K$56,I$3,'Loan Amortization'!$M$27:$M$56) -> -74528147 | J53: =-SUMIF('Loan Amortization'!$K$27:$K$56,J$3,'Loan Amortization'!$M$27:$M$56) -> -73742704 | K53: =-SUMIF('Loan Amortization'!$K$27:$K$56,K$3,'Loan Amortization'!$M$27:$M$56) -> -72900482 | L53: =-SUMIF('Loan Amortization'!$K$27:$K$56,L$3,'Loan Amortization'!$M$27:$M$56) -> -71997375 | ... P53: =-SUMIF('Loan Amortization'!$K$27:$K$56,P$3,'Loan Amortization'!$M$27:$M$56) -> 0
A54: Principal Payments | C54: =F54/$A$2/12 -> 0 | E54: =-SUMIF('Loan Amortization'!$K$27:$K$56,E$3,'Loan Amortization'!$N$27:$N$56) -> 0 | F54: =-SUMIF('Loan Amortization'!$K$27:$K$56,F$3,'Loan Amortization'!$N$27:$N$56) -> 0 | G54: =-SUMIF('Loan Amortization'!$K$27:$K$56,G$3,'Loan Amortization'!$N$27:$N$56) -> 0 | H54: =-SUMIF('Loan Amortization'!$K$27:$K$56,H$3,'Loan Amortization'!$N$27:$N$56) -> 0 | I54: =-SUMIF('Loan Amortization'!$K$27:$K$56,I$3,'Loan Amortization'!$N$27:$N$56) -> -10865152 | J54: =-SUMIF('Loan Amortization'!$K$27:$K$56,J$3,'Loan Amortization'!$N$27:$N$56) -> -11650595 | K54: =-SUMIF('Loan Amortization'!$K$27:$K$56,K$3,'Loan Amortization'!$N$27:$N$56) -> -12492817 | L54: =-SUMIF('Loan Amortization'!$K$27:$K$56,L$3,'Loan Amortization'!$N$27:$N$56) -> -13395924 | ... P54: =-SUMIF('Loan Amortization'!$K$27:$K$56,P$3,'Loan Amortization'!$N$27:$N$56) -> 0
A55: Principal Payoff | E55: =-IF(E3='Building Analysis'!$D$6,SUM('Loan Amortization'!$F$27:$F$386),0) -> 0 | F55: =-IF(F3='Building Analysis'!$D$6,SUM('Loan Amortization'!$F$27:$F$386),0) -> 0 | G55: =-IF(G3='Building Analysis'!$D$6,SUM('Loan Amortization'!$F$27:$F$386),0) -> 0 | H55: =-IF(H3='Building Analysis'!$D$6,SUM('Loan Amortization'!$F$27:$F$386),0) -> 0 | I55: =-IF(I3='Building Analysis'!$D$6,SUM('Loan Amortization'!$F$27:$F$386),0) -> 0 | J55: =-IF(J3='Building Analysis'!$D$6,SUM('Loan Amortization'!$F$27:$F$386),0) -> 0 | K55: =-IF(K3='Building Analysis'!$D$6,SUM('Loan Amortization'!$F$27:$F$386),0) -> 0 | L55: =-IF(L3='Building Analysis'!$D$6,SUM('Loan Amortization'!$F$27:$F$386),0) -> 0 | ... P55: =-IF(P3='Building Analysis'!$D$6,SUM('Loan Amortization'!$F$27:$F$386),0) -> 0
A56: TOTAL DEBT SERVICE | E56: =SUM(E52:E55) -> 0 | F56: =SUM(F52:F55) -> -74872345 | G56: =SUM(G52:G55) -> -74872345 | H56: =SUM(H52:H55) -> -74872345 | I56: =SUM(I52:I55) -> -85393299 | J56: =SUM(J52:J55) -> -85393299 | K56: =SUM(K52:K55) -> -85393299 | L56: =SUM(L52:L55) -> -85393299 | ... P56: =SUM(P52:P55) -> 0
A58: Levered Cash Flow | E58: =(E49+E56)*(E3<='Building Analysis'!$D$6) -> -904283329 | F58: =(F49+F56)*(F3<='Building Analysis'!$D$6) -> -50578765 | G58: =(G49+G56)*(G3<='Building Analysis'!$D$6) -> -28546104 | H58: =(H49+H56)*(H3<='Building Analysis'!$D$6) -> -10926281 | I58: =(I49+I56)*(I3<='Building Analysis'!$D$6) -> -7245086.8 | J58: =(J49+J56)*(J3<='Building Analysis'!$D$6) -> -4106226.8 | K58: =(K49+K56)*(K3<='Building Analysis'!$D$6) -> -89728025 | L58: =(L49+L56)*(L3<='Building Analysis'!$D$6) -> -9441064.8 | ... P58: =(P49+P56)*(P3<='Building Analysis'!$D$6) -> 0
A61: RETURN SUMMARY
A62: UL $ Profit | C62: =SUMIF($E$49:$P$49,">0",$E$49:$P$49)+SUMIF($E$49:$P$49,"<0",$E$49:$P$49) -> 7.7653875e+08
A63: UL IRR | C63: =IRR(E49:P49) -> 0.07716462
A64: UL EM | C64: =SUMIF(E49:P49,">"&0,E49:P49)/-SUMIF(E49:P49,"<"&0,E49:P49) -> 1.8546372
A65: UL $ Profit | C65: =SUMIF($E$58:$P$58,">0",$E$58:$P$58)+SUMIF($E$58:$P$58,"<0",$E$58:$P$58) -> -1.0207486e+09
A66: UL IRR | C66: =IRR(E58:P58) -> -0.25439609
A67: UL EM | C67: =SUMIF(E58:P58,">"&0,E58:P58)/-SUMIF(E58:P58,"<"&0,E58:P58) -> 0.088682448
T94: EMPIRE STATE BLDG | Y94: 1099 STEWART
T95: For the Years Ending | Y95: For the Years Ending
S97: =T97=Y97 -> TRUE | T97: Rental Revenue | Y97: Rental Revenue
S98: =T98=Y98 -> TRUE | T98: Potential Base Rent | Y98: Potential Base Rent
S99: =T99=Y99 -> TRUE | T99: Absorption & Turnover Vacancy | Y99: Absorption & Turnover Vacancy
S100: =T100=Y100 -> TRUE | T100: Free Rent | Y100: Free Rent
S101: =T101=Y101 -> TRUE | T101: Scheduled Base Rent | Y101: Scheduled Base Rent
S102: =T102=Y102 -> TRUE | T102: Total Rental Revenue | Y102: Total Rental Revenue
S103: =T103=Y103 -> TRUE
S104: =T104=Y104 -> TRUE | T104: Other Tenant Revenue | Y104: Other Tenant Revenue
S105: =T105=Y105 -> TRUE | T105: Total Expense Recoveries | Y105: Total Expense Recoveries
S106: =T106=Y106 -> TRUE | T106: Total Other Tenant Revenue | Y106: Total Other Tenant Revenue
S107: =T107=Y107 -> TRUE
S108: =T108=Y108 -> TRUE | T108: Total Tenant Revenue | Y108: Total Tenant Revenue
S109: =T109=Y109 -> TRUE
S110: =T110=Y110 -> FALSE | T110: Potential Gross Revenue | Y110: Parking Revenue
S111: =T111=Y111 -> FALSE | Y111: Parking Garage
S112: =T112=Y112 -> FALSE | T112: Vacancy & Credit Loss | Y112: Total Other Revenue
S113: =T113=Y113 -> FALSE | T113: Vacancy Allowance
S114: =T114=Y114 -> FALSE | T114: Credit Loss | Y114: Potential Gross Revenue
S115: =T115=Y115 -> FALSE | T115: Total Vacancy & Credit Loss
S116: =T116=Y116 -> FALSE | Y116: Vacancy & Credit Loss
S117: =T117=Y117 -> FALSE | T117: Effective Gross Revenue | Y117: Vacancy Allowance
S118: =T118=Y118 -> FALSE | Y118: Credit Loss
S119: =T119=Y119 -> FALSE | T119: Operating Expenses | Y119: Total Vacancy & Credit Loss
S120: =T120=Y120 -> FALSE | T120: REAL ESTATE TAXES
S121: =T121=Y121 -> FALSE | T121: INSURANCE | Y121: Effective Gross Revenue
S122: =T122=Y122 -> FALSE | T122: UTILITIES
S123: =T123=Y123 -> FALSE | T123: REPAIRS AND MAINTENANCE | Y123: Operating Expenses
S124: =T124=Y124 -> FALSE | T124: MANAGEMENT FEES | Y124: Real Estate Taxes
S125: =T125=Y125 -> FALSE | T125: PAYROLL AND BENEFITS | Y125: Insurance
S126: =T126=Y126 -> FALSE | T126: ADVERTISING AND MARKETING | Y126: Utilities
S127: =T127=Y127 -> FALSE | T127: SECURITY | Y127: Repairs and Maintenance
S128: =T128=Y128 -> TRUE | T128: JANITORIAL | Y128: Janitorial
S129: =T129=Y129 -> FALSE | T129: Total Operating Expenses | Y129: Management Fees
S130: =T130=Y130 -> FALSE | Y130: Payroll and Benefits
S131: =T131=Y131 -> FALSE | T131: Net Operating Income | Y131: Advertising and Marketing
S132: =T132=Y132 -> FALSE | Y132: Professional Fees
S133: =T133=Y133 -> FALSE | T133: Leasing Costs | Y133: General and Admin
S134: =T134=Y134 -> FALSE | T134: Tenant Improvements | Y134: Total Operating Expenses
S135: =T135=Y135 -> FALSE | T135: Leasing Commissions
S136: =T136=Y136 -> FALSE | T136: Total Leasing Costs | Y136: Net Operating Income
S137: =T137=Y137 -> TRUE
S138: =T138=Y138 -> FALSE | T138: Capital Expenditures | Y138: Leasing Costs
S139: =T139=Y139 -> FALSE | T139: Elevator Modernization | Y139: Tenant Improvements
S140: =T140=Y140 -> FALSE | T140: Corridor Updates | Y140: Leasing Commissions
S141: =T141=Y141 -> FALSE | T141: LED Lighting | Y141: Total Leasing Costs
S142: =T142=Y142 -> FALSE | T142: Furniture
S143: =T143=Y143 -> FALSE | T143: Restroom Updates | Y143: Capital Expenditures
S144: =T144=Y144 -> FALSE | T144: Total Capital Expenditures | Y144: Elevator Replacement
...

Sheet Loan Amortization
B2: Loan Information
B3: Loan Amount | D3: ='Property Summary'!D12 -> 1.0696049e+09
B4: Rate (Annual) | D4: ='Property Summary'!B15 -> 0.07
B5: Term of Loan (Years) | D5: ='Property Summary'!D13 -> 10
B6: Interest Only (Years) | D6: ='Property Summary'!D14 -> 3
B7: Amortization (Years) | D7: ='Property Summary'!D15 -> 30
B8: Monthly Payment (non IO) | D8: =PMT(D4/12,D7*12,-D3,0) -> 7116108.2
B9: Annual Payment (non IO) | D9: =D8*12 -> 85393299
B23: Monthly Amortization Schedule | K23: Annual Amounts
B25: Month | C25: Year | D25: BOP Balance | E25: Total Payment | F25: Loan Payoff | G25: Interest Payment | H25: Principal Payment | I25: EOP Balance | K25: Year | L25: Total Payment | M25: Interest Payment | N25: Principal Payment | O25: EOP Balance
I26: =D3 -> 1.0696049e+09
B27: 1 | C27: 1 | D27: =I26 -> 1.0696049e+09 | E27: =IF(B27>($D$5*12),0,IF(B27<$D$6*12+1,D27*($D$4/12),$D$8)) -> 6239362 | F27: =IF(B27=($D$5*12),D27-H27,0) -> 0 | G27: =$D$4/12*D27 -> 6239362 | H27: =IF(B27<($D$6*12+1),0,E27-G27) -> 0 | I27: =D27-H27-F27 -> 1.0696049e+09 | K27: 1 | L27: =SUMIF($C$27:$C$386,$K27,$E$27:$E$386) -> 74872345 | M27: =SUMIF($C$27:$C$386,$K27,$G$27:$G$386) -> 74872345 | N27: =SUMIF($C$27:$C$386,$K27,$H$27:$H$386) -> 0 | O27: =VLOOKUP(Q27,$B$27:$I$386,7,FALSE) -> 0 | Q27: =K27*12 -> 12
B28: =B27+1 -> 2 | C28: 1 | D28: =I27 -> 1.0696049e+09 | E28: =IF(B28>($D$5*12),0,IF(B28<$D$6*12+1,D28*($D$4/12),$D$8)) -> 6239362 | F28: =IF(B28=($D$5*12),D28-H28,0) -> 0 | G28: =$D$4/12*D28 -> 6239362 | H28: =IF(B28<($D$6*12+1),0,E28-G28) -> 0 | I28: =D28-H28-F28 -> 1.0696049e+09 | K28: =K27+1 -> 2 | L28: =SUMIF($C$27:$C$386,$K28,$E$27:$E$386) -> 74872345 | M28: =SUMIF($C$27:$C$386,$K28,$G$27:$G$386) -> 74872345 | N28: =SUMIF($C$27:$C$386,$K28,$H$27:$H$386) -> 0 | O28: =VLOOKUP(Q28,$B$27:$I$386,7,FALSE) -> 0 | Q28: =K28*12 -> 24
B29: =B28+1 -> 3 | C29: 1 | D29: =I28 -> 1.0696049e+09 | E29: =IF(B29>($D$5*12),0,IF(B29<$D$6*12+1,D29*($D$4/12),$D$8)) -> 6239362 | F29: =IF(B29=($D$5*12),D29-H29,0) -> 0 | G29: =$D$4/12*D29 -> 6239362 | H29: =IF(B29<($D$6*12+1),0,E29-G29) -> 0 | I29: =D29-H29-F29 -> 1.0696049e+09 | K29: =K28+1 -> 3 | L29: =SUMIF($C$27:$C$386,$K29,$E$27:$E$386) -> 74872345 | M29: =SUMIF($C$27:$C$386,$K29,$G$27:$G$386) -> 74872345 | N29: =SUMIF($C$27:$C$386,$K29,$H$27:$H$386) -> 0 | O29: =VLOOKUP(Q29,$B$27:$I$386,7,FALSE) -> 0 | Q29: =K29*12 -> 36
B30: =B29+1 -> 4 | C30: 1 | D30: =I29 -> 1.0696049e+09 | E30: =IF(B30>($D$5*12),0,IF(B30<$D$6*12+1,D30*($D$4/12),$D$8)) -> 6239362 | F30: =IF(B30=($D$5*12),D30-H30,0) -> 0 | G30: =$D$4/12*D30 -> 6239362 | H30: =IF(B30<($D$6*12+1),0,E30-G30) -> 0 | I30: =D30-H30-F30 -> 1.0696049e+09 | K30: =K29+1 -> 4 | L30: =SUMIF($C$27:$C$386,$K30,$E$27:$E$386) -> 85393299 | M30: =SUMIF($C$27:$C$386,$K30,$G$27:$G$386) -> 74528147 | N30: =SUMIF($C$27:$C$386,$K30,$H$27:$H$386) -> 10865152 | O30: =VLOOKUP(Q30,$B$27:$I$386,7,FALSE) -> 934673.98 | Q30: =K30*12 -> 48
B31: =B30+1 -> 5 | C31: 1 | D31: =I30 -> 1.0696049e+09 | E31: =IF(B31>($D$5*12),0,IF(B31<$D$6*12+1,D31*($D$4/12),$D$8)) -> 6239362 | F31: =IF(B31=($D$5*12),D31-H31,0) -> 0 | G31: =$D$4/12*D31 -> 6239362 | H31: =IF(B31<($D$6*12+1),0,E31-G31) -> 0 | I31: =D31-H31-F31 -> 1.0696049e+09 | K31: =K30+1 -> 5 | L31: =SUMIF($C$27:$C$386,$K31,$E$27:$E$386) -> 85393299 | M31: =SUMIF($C$27:$C$386,$K31,$G$27:$G$386) -> 73742704 | N31: =SUMIF($C$27:$C$386,$K31,$H$27:$H$386) -> 11650595 | O31: =VLOOKUP(Q31,$B$27:$I$386,7,FALSE) -> 1002241.6 | Q31: =K31*12 -> 60
B32: =B31+1 -> 6 | C32: 1 | D32: =I31 -> 1.0696049e+09 | E32: =IF(B32>($D$5*12),0,IF(B32<$D$6*12+1,D32*($D$4/12),$D$8)) -> 6239362 | F32: =IF(B32=($D$5*12),D32-H32,0) -> 0 | G32: =$D$4/12*D32 -> 6239362 | H32: =IF(B32<($D$6*12+1),0,E32-G32) -> 0 | I32: =D32-H32-F32 -> 1.0696049e+09 | K32: =K31+1 -> 6 | L32: =SUMIF($C$27:$C$386,$K32,$E$27:$E$386) -> 85393299 | M32: =SUMIF($C$27:$C$386,$K32,$G$27:$G$386) -> 72900482 | N32: =SUMIF($C$27:$C$386,$K32,$H$27:$H$386) -> 12492817 | O32: =VLOOKUP(Q32,$B$27:$I$386,7,FALSE) -> 1074693.8 | Q32: =K32*12 -> 72
B33: =B32+1 -> 7 | C33: 1 | D33: =I32 -> 1.0696049e+09 | E33: =IF(B33>($D$5*12),0,IF(B33<$D$6*12+1,D33*($D$4/12),$D$8)) -> 6239362 | F33: =IF(B33=($D$5*12),D33-H33,0) -> 0 | G33: =$D$4/12*D33 -> 6239362 | H33: =IF(B33<($D$6*12+1),0,E33-G33) -> 0 | I33: =D33-H33-F33 -> 1.0696049e+09 | K33: =K32+1 -> 7 | L33: =SUMIF($C$27:$C$386,$K33,$E$27:$E$386) -> 85393299 | M33: =SUMIF($C$27:$C$386,$K33,$G$27:$G$386) -> 71997375 | N33: =SUMIF($C$27:$C$386,$K33,$H$27:$H$386) -> 13395924 | O33: =VLOOKUP(Q33,$B$27:$I$386,7,FALSE) -> 1152383.5 | Q33: =K33*12 -> 84
B34: =B33+1 -> 8 | C34: 1 | D34: =I33 -> 1.0696049e+09 | E34: =IF(B34>($D$5*12),0,IF(B34<$D$6*12+1,D34*($D$4/12),$D$8)) -> 6239362 | F34: =IF(B34=($D$5*12),D34-H34,0) -> 0 | G34: =$D$4/12*D34 -> 6239362 | H34: =IF(B34<($D$6*12+1),0,E34-G34) -> 0 | I34: =D34-H34-F34 -> 1.0696049e+09 | K34: =K33+1 -> 8 | L34: =SUMIF($C$27:$C$386,$K34,$E$27:$E$386) -> 85393299 | M34: =SUMIF($C$27:$C$386,$K34,$G$27:$G$386) -> 71028983 | N34: =SUMIF($C$27:$C$386,$K34,$H$27:$H$386) -> 14364316 | O34: =VLOOKUP(Q34,$B$27:$I$386,7,FALSE) -> 1235689.4 | Q34: =K34*12 -> 96
B35: =B34+1 -> 9 | C35: 1 | D35: =I34 -> 1.0696049e+09 | E35: =IF(B35>($D$5*12),0,IF(B35<$D$6*12+1,D35*($D$4/12),$D$8)) -> 6239362 | F35: =IF(B35=($D$5*12),D35-H35,0) -> 0 | G35: =$D$4/12*D35 -> 6239362 | H35: =IF(B35<($D$6*12+1),0,E35-G35) -> 0 | I35: =D35-H35-F35 -> 1.0696049e+09 | K35: =K34+1 -> 9 | L35: =SUMIF($C$27:$C$386,$K35,$E$27:$E$386) -> 85393299 | M35: =SUMIF($C$27:$C$386,$K35,$G$27:$G$386) -> 69990585 | N35: =SUMIF($C$27:$C$386,$K35,$H$27:$H$386) -> 15402714 | O35: =VLOOKUP(Q35,$B$27:$I$386,7,FALSE) -> 1325017.4 | Q35: =K35*12 -> 108
B36: =B35+1 -> 10 | C36: 1 | D36: =I35 -> 1.0696049e+09 | E36: =IF(B36>($D$5*12),0,IF(B36<$D$6*12+1,D36*($D$4/12),$D$8)) -> 6239362 | F36: =IF(B36=($D$5*12),D36-H36,0) -> 0 | G36: =$D$4/12*D36 -> 6239362 | H36: =IF(B36<($D$6*12+1),0,E36-G36) -> 0 | I36: =D36-H36-F36 -> 1.0696049e+09 | K36: =K35+1 -> 10 | L36: =SUMIF($C$27:$C$386,$K36,$E$27:$E$386) -> 85393299 | M36: =SUMIF($C$27:$C$386,$K36,$G$27:$G$386) -> 68877122 | N36: =SUMIF($C$27:$C$386,$K36,$H$27:$H$386) -> 16516177 | O36: =VLOOKUP(Q36,$B$27:$I$386,7,FALSE) -> 1420803.1 | Q36: =K36*12 -> 120 | S36: =SUM(F27:F386) -> 9.7491723e+08
B37: =B36+1 -> 11 | C37: 1 | D37: =I36 -> 1.0696049e+09 | E37: =IF(B37>($D$5*12),0,IF(B37<$D$6*12+1,D37*($D$4/12),$D$8)) -> 6239362 | F37: =IF(B37=($D$5*12),D37-H37,0) -> 0 | G37: =$D$4/12*D37 -> 6239362 | H37: =IF(B37<($D$6*12+1),0,E37-G37) -> 0 | I37: =D37-H37-F37 -> 1.0696049e+09 | K37: =K36+1 -> 11 | L37: =SUMIF($C$27:$C$386,$K37,$E$27:$E$386) -> 0 | M37: =SUMIF($C$27:$C$386,$K37,$G$27:$G$386) -> 0 | N37: =SUMIF($C$27:$C$386,$K37,$H$27:$H$386) -> 0 | O37: =VLOOKUP(Q37,$B$27:$I$386,7,FALSE) -> 0 | Q37: =K37*12 -> 132
B38: =B37+1 -> 12 | C38: 1 | D38: =I37 -> 1.0696049e+09 | E38: =IF(B38>($D$5*12),0,IF(B38<$D$6*12+1,D38*($D$4/12),$D$8)) -> 6239362 | F38: =IF(B38=($D$5*12),D38-H38,0) -> 0 | G38: =$D$4/12*D38 -> 6239362 | H38: =IF(B38<($D$6*12+1),0,E38-G38) -> 0 | I38: =D38-H38-F38 -> 1.0696049e+09 | K38: =K37+1 -> 12 | L38: =SUMIF($C$27:$C$386,$K38,$E$27:$E$386) -> 0 | M38: =SUMIF($C$27:$C$386,$K38,$G$27:$G$386) -> 0 | N38: =SUMIF($C$27:$C$386,$K38,$H$27:$H$386) -> 0 | O38: =VLOOKUP(Q38,$B$27:$I$386,7,FALSE) -> 0 | Q38: =K38*12 -> 144
B39: =B38+1 -> 13 | C39: =C27+1 -> 2 | D39: =I38 -> 1.0696049e+09 | E39: =IF(B39>($D$5*12),0,IF(B39<$D$6*12+1,D39*($D$4/12),$D$8)) -> 6239362 | F39: =IF(B39=($D$5*12),D39-H39,0) -> 0 | G39: =$D$4/12*D39 -> 6239362 | H39: =IF(B39<($D$6*12+1),0,E39-G39) -> 0 | I39: =D39-H39-F39 -> 1.0696049e+09 | K39: =K38+1 -> 13 | L39: =SUMIF($C$27:$C$386,$K39,$E$27:$E$386) -> 0 | M39: =SUMIF($C$27:$C$386,$K39,$G$27:$G$386) -> 0 | N39: =SUMIF($C$27:$C$386,$K39,$H$27:$H$386) -> 0 | O39: =VLOOKUP(Q39,$B$27:$I$386,7,FALSE) -> 0 | Q39: =K39*12 -> 156
B40: =B39+1 -> 14 | C40: =C28+1 -> 2 | D40: =I39 -> 1.0696049e+09 | E40: =IF(B40>($D$5*12),0,IF(B40<$D$6*12+1,D40*($D$4/12),$D$8)) -> 6239362 | F40: =IF(B40=($D$5*12),D40-H40,0) -> 0 | G40: =$D$4/12*D40 -> 6239362 | H40: =IF(B40<($D$6*12+1),0,E40-G40) -> 0 | I40: =D40-H40-F40 -> 1.0696049e+09 | K40: =K39+1 -> 14 | L40: =SUMIF($C$27:$C$386,$K40,$E$27:$E$386) -> 0 | M40: =SUMIF($C$27:$C$386,$K40,$G$27:$G$386) -> 0 | N40: =SUMIF($C$27:$C$386,$K40,$H$27:$H$386) -> 0 | O40: =VLOOKUP(Q40,$B$27:$I$386,7,FALSE) -> 0 | Q40: =K40*12 -> 168
B41: =B40+1 -> 15 | C41: =C29+1 -> 2 | D41: =I40 -> 1.0696049e+09 | E41: =IF(B41>($D$5*12),0,IF(B41<$D$6*12+1,D41*($D$4/12),$D$8)) -> 6239362 | F41: =IF(B41=($D$5*12),D41-H41,0) -> 0 | G41: =$D$4/12*D41 -> 6239362 | H41: =IF(B41<($D$6*12+1),0,E41-G41) -> 0 | I41: =D41-H41-F41 -> 1.0696049e+09 | K41: =K40+1 -> 15 | L41: =SUMIF($C$27:$C$386,$K41,$E$27:$E$386) -> 0 | M41: =SUMIF($C$27:$C$386,$K41,$G$27:$G$386) -> 0 | N41: =SUMIF($C$27:$C$386,$K41,$H$27:$H$386) -> 0 | O41: =VLOOKUP(Q41,$B$27:$I$386,7,FALSE) -> 0 | Q41: =K41*12 -> 180
B42: =B41+1 -> 16 | C42: =C30+1 -> 2 | D42: =I41 -> 1.0696049e+09 | E42: =IF(B42>($D$5*12),0,IF(B42<$D$6*12+1,D42*($D$4/12),$D$8)) -> 6239362 | F42: =IF(B42=($D$5*12),D42-H42,0) -> 0 | G42: =$D$4/12*D42 -> 6239362 | H42: =IF(B42<($D$6*12+1),0,E42-G42) -> 0 | I42: =D42-H42-F42 -> 1.0696049e+09 | K42: =K41+1 -> 16 | L42: =SUMIF($C$27:$C$386,$K42,$E$27:$E$386) -> 0 | M42: =SUMIF($C$27:$C$386,$K42,$G$27:$G$386) -> 0 | N42: =SUMIF($C$27:$C$386,$K42,$H$27:$H$386) -> 0 | O42: =VLOOKUP(Q42,$B$27:$I$386,7,FALSE) -> 0 | Q42: =K42*12 -> 192
B43: =B42+1 -> 17 | C43: =C31+1 -> 2 | D43: =I42 -> 1.0696049e+09 | E43: =IF(B43>($D$5*12),0,IF(B43<$D$6*12+1,D43*($D$4/12),$D$8)) -> 6239362 | F43: =IF(B43=($D$5*12),D43-H43,0) -> 0 | G43: =$D$4/12*D43 -> 6239362 | H43: =IF(B43<($D$6*12+1),0,E43-G43) -> 0 | I43: =D43-H43-F43 -> 1.0696049e+09 | K43: =K42+1 -> 17 | L43: =SUMIF($C$27:$C$386,$K43,$E$27:$E$386) -> 0 | M43: =SUMIF($C$27:$C$386,$K43,$G$27:$G$386) -> 0 | N43: =SUMIF($C$27:$C$386,$K43,$H$27:$H$386) -> 0 | O43: =VLOOKUP(Q43,$B$27:$I$386,7,FALSE) -> 0 | Q43: =K43*12 -> 204
B44: =B43+1 -> 18 | C44: =C32+1 -> 2 | D44: =I43 -> 1.0696049e+09 | E44: =IF(B44>($D$5*12),0,IF(B44<$D$6*12+1,D44*($D$4/12),$D$8)) -> 6239362 | F44: =IF(B44=($D$5*12),D44-H44,0) -> 0 | G44: =$D$4/12*D44 -> 6239362 | H44: =IF(B44<($D$6*12+1),0,E44-G44) -> 0 | I44: =D44-H44-F44 -> 1.0696049e+09 | K44: =K43+1 -> 18 | L44: =SUMIF($C$27:$C$386,$K44,$E$27:$E$386) -> 0 | M44: =SUMIF($C$27:$C$386,$K44,$G$27:$G$386) -> 0 | N44: =SUMIF($C$27:$C$386,$K44,$H$27:$H$386) -> 0 | O44: =VLOOKUP(Q44,$B$27:$I$386,7,FALSE) -> 0 | Q44: =K44*12 -> 216
B45: =B44+1 -> 19 | C45: =C33+1 -> 2 | D45: =I44 -> 1.0696049e+09 | E45: =IF(B45>($D$5*12),0,IF(B45<$D$6*12+1,D45*($D$4/12),$D$8)) -> 6239362 | F45: =IF(B45=($D$5*12),D45-H45,0) -> 0 | G45: =$D$4/12*D45 -> 6239362 | H45: =IF(B45<($D$6*12+1),0,E45-G45) -> 0 | I45: =D45-H45-F45 -> 1.0696049e+09 | K45: =K44+1 -> 19 | L45: =SUMIF($C$27:$C$386,$K45,$E$27:$E$386) -> 0 | M45: =SUMIF($C$27:$C$386,$K45,$G$27:$G$386) -> 0 | N45: =SUMIF($C$27:$C$386,$K45,$H$27:$H$386) -> 0 | O45: =VLOOKUP(Q45,$B$27:$I$386,7,FALSE) -> 0 | Q45: =K45*12 -> 228
B46: =B45+1 -> 20 | C46: =C34+1 -> 2 | D46: =I45 -> 1.0696049e+09 | E46: =IF(B46>($D$5*12),0,IF(B46<$D$6*12+1,D46*($D$4/12),$D$8)) -> 6239362 | F46: =IF(B46=($D$5*12),D46-H46,0) -> 0 | G46: =$D$4/12*D46 -> 6239362 | H46: =IF(B46<($D$6*12+1),0,E46-G46) -> 0 | I46: =D46-H46-F46 -> 1.0696049e+09 | K46: =K45+1 -> 20 | L46: =SUMIF($C$27:$C$386,$K46,$E$27:$E$386) -> 0 | M46: =SUMIF($C$27:$C$386,$K46,$G$27:$G$386) -> 0 | N46: =SUMIF($C$27:$C$386,$K46,$H$27:$H$386) -> 0 | O46: =VLOOKUP(Q46,$B$27:$I$386,7,FALSE) -> 0 | Q46: =K46*12 -> 240
B47: =B46+1 -> 21 | C47: =C35+1 -> 2 | D47: =I46 -> 1.0696049e+09 | E47: =IF(B47>($D$5*12),0,IF(B47<$D$6*12+1,D47*($D$4/12),$D$8)) -> 6239362 | F47: =IF(B47=($D$5*12),D47-H47,0) -> 0 | G47: =$D$4/12*D47 -> 6239362 | H47: =IF(B47<($D$6*12+1),0,E47-G47) -> 0 | I47: =D47-H47-F47 -> 1.0696049e+09 | K47: =K46+1 -> 21 | L47: =SUMIF($C$27:$C$386,$K47,$E$27:$E$386) -> 0 | M47: =SUMIF($C$27:$C$386,$K47,$G$27:$G$386) -> 0 | N47: =SUMIF($C$27:$C$386,$K47,$H$27:$H$386) -> 0 | O47: =VLOOKUP(Q47,$B$27:$I$386,7,FALSE) -> 0 | Q47: =K47*12 -> 252
B48: =B47+1 -> 22 | C48: =C36+1 -> 2 | D48: =I47 -> 1.0696049e+09 | E48: =IF(B48>($D$5*12),0,IF(B48<$D$6*12+1,D48*($D$4/12),$D$8)) -> 6239362 | F48: =IF(B48=($D$5*12),D48-H48,0) -> 0 | G48: =$D$4/12*D48 -> 6239362 | H48: =IF(B48<($D$6*12+1),0,E48-G48) -> 0 | I48: =D48-H48-F48 -> 1.0696049e+09 | K48: =K47+1 -> 22 | L48: =SUMIF($C$27:$C$386,$K48,$E$27:$E$386) -> 0 | M48: =SUMIF($C$27:$C$386,$K48,$G$27:$G$386) -> 0 | N48: =SUMIF($C$27:$C$386,$K48,$H$27:$H$386) -> 0 | O48: =VLOOKUP(Q48,$B$27:$I$386,7,FALSE) -> 0 | Q48: =K48*12 -> 264
B49: =B48+1 -> 23 | C49: =C37+1 -> 2 | D49: =I48 -> 1.0696049e+09 | E49: =IF(B49>($D$5*12),0,IF(B49<$D$6*12+1,D49*($D$4/12),$D$8)) -> 6239362 | F49: =IF(B49=($D$5*12),D49-H49,0) -> 0 | G49: =$D$4/12*D49 -> 6239362 | H49: =IF(B49<($D$6*12+1),0,E49-G49) -> 0 | I49: =D49-H49-F49 -> 1.0696049e+09 | K49: =K48+1 -> 23 | L49: =SUMIF($C$27:$C$386,$K49,$E$27:$E$386) -> 0 | M49: =SUMIF($C$27:$C$386,$K49,$G$27:$G$386) -> 0 | N49: =SUMIF($C$27:$C$386,$K49,$H$27:$H$386) -> 0 | O49: =VLOOKUP(Q49,$B$27:$I$386,7,FALSE) -> 0 | Q49: =K49*12 -> 276
B50: =B49+1 -> 24 | C50: =C38+1 -> 2 | D50: =I49 -> 1.0696049e+09 | E50: =IF(B50>($D$5*12),0,IF(B50<$D$6*12+1,D50*($D$4/12),$D$8)) -> 6239362 | F50: =IF(B50=($D$5*12),D50-H50,0) -> 0 | G50: =$D$4/12*D50 -> 6239362 | H50: =IF(B50<($D$6*12+1),0,E50-G50) -> 0 | I50: =D50-H50-F50 -> 1.0696049e+09 | K50: =K49+1 -> 24 | L50: =SUMIF($C$27:$C$386,$K50,$E$27:$E$386) -> 0 | M50: =SUMIF($C$27:$C$386,$K50,$G$27:$G$386) -> 0 | N50: =SUMIF($C$27:$C$386,$K50,$H$27:$H$386) -> 0 | O50: =VLOOKUP(Q50,$B$27:$I$386,7,FALSE) -> 0 | Q50: =K50*12 -> 288
... B56: =B55+1 -> 30 | C56: =C44+1 -> 3 | D56: =I55 -> 1.0696049e+09 | E56: =IF(B56>($D$5*12),0,IF(B56<$D$6*12+1,D56*($D$4/12),$D$8)) -> 6239362 | F56: =IF(B56=($D$5*12),D56-H56,0) -> 0 | G56: =$D$4/12*D56 -> 6239362 | H56: =IF(B56<($D$6*12+1),0,E56-G56) -> 0 | I56: =D56-H56-F56 -> 1.0696049e+09 | K56: =K55+1 -> 30 | L56: =SUMIF($C$27:$C$386,$K56,$E$27:$E$386) -> 0 | M56: =SUMIF($C$27:$C$386,$K56,$G$27:$G$386) -> 0 | N56: =SUMIF($C$27:$C$386,$K56,$H$27:$H$386) -> 0 | O56: =VLOOKUP(Q56,$B$27:$I$386,7,FALSE) -> 0 | Q56: =K56*12 -> 360
B57: =B56+1 -> 31 | C57: =C45+1 -> 3 | D57: =I56 -> 1.0696049e+09 | E57: =IF(B57>($D$5*12),0,IF(B57<$D$6*12+1,D57*($D$4/12),$D$8)) -> 6239362 | F57: =IF(B57=($D$5*12),D57-H57,0) -> 0 | G57: =$D$4/12*D57 -> 6239362 | H57: =IF(B57<($D$6*12+1),0,E57-G57) -> 0 | I57: =D57-H57-F57 -> 1.0696049e+09
B58: =B57+1 -> 32 | C58: =C46+1 -> 3 | D58: =I57 -> 1.0696049e+09 | E58: =IF(B58>($D$5*12),0,IF(B58<$D$6*12+1,D58*($D$4/12),$D$8)) -> 6239362 | F58: =IF(B58=($D$5*12),D58-H58,0) -> 0 | G58: =$D$4/12*D58 -> 6239362 | H58: =IF(B58<($D$6*12+1),0,E58-G58) -> 0 | I58: =D58-H58-F58 -> 1.0696049e+09
B59: =B58+1 -> 33 | C59: =C47+1 -> 3 | D59: =I58 -> 1.0696049e+09 | E59: =IF(B59>($D$5*12),0,IF(B59<$D$6*12+1,D59*($D$4/12),$D$8)) -> 6239362 | F59: =IF(B59=($D$5*12),D59-H59,0) -> 0 | G59: =$D$4/12*D59 -> 6239362 | H59: =IF(B59<($D$6*12+1),0,E59-G59) -> 0 | I59: =D59-H59-F59 -> 1.0696049e+09
B60: =B59+1 -> 34 | C60: =C48+1 -> 3 | D60: =I59 -> 1.0696049e+09 | E60: =IF(B60>($D$5*12),0,IF(B60<$D$6*12+1,D60*($D$4/12),$D$8)) -> 6239362 | F60: =IF(B60=($D$5*12),D60-H60,0) -> 0 | G60: =$D$4/12*D60 -> 6239362 | H60: =IF(B60<($D$6*12+1),0,E60-G60) -> 0 | I60: =D60-H60-F60 -> 1.0696049e+09
B61: =B60+1 -> 35 | C61: =C49+1 -> 3 | D61: =I60 -> 1.0696049e+09 | E61: =IF(B61>($D$5*12),0,IF(B61<$D$6*12+1,D61*($D$4/12),$D$8)) -> 6239362 | F61: =IF(B61=($D$5*12),D61-H61,0) -> 0 | G61: =$D$4/12*D61 -> 6239362 | H61: =IF(B61<($D$6*12+1),0,E61-G61) -> 0 | I61: =D61-H61-F61 -> 1.0696049e+09
B62: =B61+1 -> 36 | C62: =C50+1 -> 3 | D62: =I61 -> 1.0696049e+09 | E62: =IF(B62>($D$5*12),0,IF(B62<$D$6*12+1,D62*($D$4/12),$D$8)) -> 6239362 | F62: =IF(B62=($D$5*12),D62-H62,0) -> 0 | G62: =$D$4/12*D62 -> 6239362 | H62: =IF(B62<($D$6*12+1),0,E62-G62) -> 0 | I62: =D62-H62-F62 -> 1.0696049e+09
B63: =B62+1 -> 37 | C63: =C51+1 -> 4 | D63: =I62 -> 1.0696049e+09 | E63: =IF(B63>($D$5*12),0,IF(B63<$D$6*12+1,D63*($D$4/12),$D$8)) -> 7116108.2 | F63: =IF(B63=($D$5*12),D63-H63,0) -> 0 | G63: =$D$4/12*D63 -> 6239362 | H63: =IF(B63<($D$6*12+1),0,E63-G63) -> 876746.19 | I63: =D63-H63-F63 -> 1.0687282e+09
B64: =B63+1 -> 38 | C64: =C52+1 -> 4 | D64: =I63 -> 1.0687282e+09 | E64: =IF(B64>($D$5*12),0,IF(B64<$D$6*12+1,D64*($D$4/12),$D$8)) -> 7116108.2 | F64: =IF(B64=($D$5*12),D64-H64,0) -> 0 | G64: =$D$4/12*D64 -> 6234247.7 | H64: =IF(B64<($D$6*12+1),0,E64-G64) -> 881860.54 | I64: =D64-H64-F64 -> 1.0678463e+09
B65: =B64+1 -> 39 | C65: =C53+1 -> 4 | D65: =I64 -> 1.0678463e+09 | E65: =IF(B65>($D$5*12),0,IF(B65<$D$6*12+1,D65*($D$4/12),$D$8)) -> 7116108.2 | F65: =IF(B65=($D$5*12),D65-H65,0) -> 0 | G65: =$D$4/12*D65 -> 6229103.5 | H65: =IF(B65<($D$6*12+1),0,E65-G65) -> 887004.73 | I65: =D65-H65-F65 -> 1.0669593e+09
B66: =B65+1 -> 40 | C66: =C54+1 -> 4 | D66: =I65 -> 1.0669593e+09 | E66: =IF(B66>($D$5*12),0,IF(B66<$D$6*12+1,D66*($D$4/12),$D$8)) -> 7116108.2 | F66: =IF(B66=($D$5*12),D66-H66,0) -> 0 | G66: =$D$4/12*D66 -> 6223929.3 | H66: =IF(B66<($D$6*12+1),0,E66-G66) -> 892178.92 | I66: =D66-H66-F66 -> 1.0660671e+09
B67: =B66+1 -> 41 | C67: =C55+1 -> 4 | D67: =I66 -> 1.0660671e+09 | E67: =IF(B67>($D$5*12),0,IF(B67<$D$6*12+1,D67*($D$4/12),$D$8)) -> 7116108.2 | F67: =IF(B67=($D$5*12),D67-H67,0) -> 0 | G67: =$D$4/12*D67 -> 6218724.9 | H67: =IF(B67<($D$6*12+1),0,E67-G67) -> 897383.3 | I67: =D67-H67-F67 -> 1.0651697e+09
B68: =B67+1 -> 42 | C68: =C56+1 -> 4 | D68: =I67 -> 1.0651697e+09 | E68: =IF(B68>($D$5*12),0,IF(B68<$D$6*12+1,D68*($D$4/12),$D$8)) -> 7116108.2 | F68: =IF(B68=($D$5*12),D68-H68,0) -> 0 | G68: =$D$4/12*D68 -> 6213490.2 | H68: =IF(B68<($D$6*12+1),0,E68-G68) -> 902618.04 | I68: =D68-H68-F68 -> 1.0642671e+09
... B386: =B385+1 -> 360 | C386: =C374+1 -> 30 | D386: =I385 -> 0 | E386: =IF(B386>($D$5*12),0,IF(B386<$D$6*12+1,D386*($D$4/12),$D$8)) -> 0 | F386: =IF(B386=($D$5*12),D386-H386,0) -> 0 | G386: =$D$4/12*D386 -> 0 | H386: =IF(B386<($D$6*12+1),0,E386-G386) -> 0 | I386: =D386-H386-F386 -> 0

Sheet Waterfall Model
F2: INPUTS | L2: RETURNS
E3: Investor | F3: Sponsor co-invest | G3: Preferred Return | H3: Promote up to Hurdle | I3: Hurdle Rate | J3: Promote over Hurdle | L3: Sponsor IRR | M3: Sponsor Multiple | N3: Sponsor Profit | O3: Sponsor Share of Profit | P3: Investor IRR | Q3: Investor Multiple | R3: Investor Profit | S3: Investor Share of Profit
E4: ='Property Summary'!A59 -> Sponsor | F4: ='Property Summary'!B59 -> 0.05 | G4: ='Property Summary'!D59 -> 0.1 | H4: ='Property Summary'!E59 -> 0.325 | I4: ='Property Summary'!F59 -> 0.15 | J4: ='Property Summary'!G59 -> 0.46 | L4: =XIRR(G49:ET49,G8:ET8) -> 0.095341793 | M4: =-SUMIF($G$49:$ET$49,">0",$G$49:$ET$49)/SUMIF($G$49:$ET$49,"<0",$G$49:$ET$49) -> 2.1268146 | N4: =SUM($G$49:$ET$49) -> 60262320 | O4: =N4/(N4+R4) -> 0.05 | P4: =XIRR(G48:ET48,G8:ET8) -> 0.095341793 | Q4: =-SUMIF($G$48:$ET$48,">0",$G$48:$ET$48)/SUMIF($G$48:$ET$48,"<0",$G$48:$ET$48) -> 2.1268146 | R4: =SUM($G$48:$ET$48) -> 1.1449841e+09 | S4: =R4/(N4+R4) -> 0.95
E5: ='Property Summary'!A60 -> Capital Partner | F5: ='Property Summary'!B60 -> 0.95 | G5: ='Property Summary'!D60 -> 0.1 | H5: ='Property Summary'!E60 -> 0.675 | I5: ='Property Summary'!F60 -> 0.1 | J5: ='Property Summary'!G60 -> 0.54
G8: =Proforma!E4 -> 45292 | H8: =Proforma!F4 -> 45657 | I8: =Proforma!G4 -> 46022 | J8: =Proforma!H4 -> 46387 | K8: =Proforma!I4 -> 46752 | L8: =Proforma!J4 -> 47118 | M8: =Proforma!K4 -> 47483 | N8: =Proforma!L4 -> 47848 | ... ET8: =Proforma!ER4 -> 0
E11: Project Leveraged Cash Flow | G11: ='Property Summary'!B41 -> -1.0696049e+09 | H11: ='Property Summary'!C41 -> 41812835 | I11: ='Property Summary'!D41 -> 65693328 | J11: ='Property Summary'!E41 -> 85197940 | K11: ='Property Summary'!F41 -> 90801618 | L11: ='Property Summary'!G41 -> 95901412 | M11: ='Property Summary'!H41 -> 12279767 | N11: ='Property Summary'!I41 -> 94606883 | ... ET11: ='Property Summary'!EO41 -> 0 | EV11: x
EV12: x
E13: Project Levered IRR | G13: =XIRR($G$11:$R$11,$G$8:$R$8) -> 0.095341793 | EV13: x
EV14: x
E16: Standard Partner Contributions | EV16: x
E17: =$E$5 -> Capital Partner | G17: =G18/$F$4*$F$5 -> -1.0161247e+09 | H17: =H18/$F$4*$F$5 -> 0 | I17: =I18/$F$4*$F$5 -> 0 | J17: =J18/$F$4*$F$5 -> 0 | K17: =K18/$F$4*$F$5 -> 0 | L17: =L18/$F$4*$F$5 -> 0 | M17: =M18/$F$4*$F$5 -> 0 | N17: =N18/$F$4*$F$5 -> 0 | ... ET17: =ET18/$F$4*$F$5 -> 0 | EV17: x
E18: =$E$4 -> Sponsor | G18: =IF(G11<0,G11*$F$4,0) -> -53480246 | H18: =IF(H11<0,H11*$F$4,0) -> 0 | I18: =IF(I11<0,I11*$F$4,0) -> 0 | J18: =IF(J11<0,J11*$F$4,0) -> 0 | K18: =IF(K11<0,K11*$F$4,0) -> 0 | L18: =IF(L11<0,L11*$F$4,0) -> 0 | M18: =IF(M11<0,M11*$F$4,0) -> 0 | N18: =IF(N11<0,N11*$F$4,0) -> 0 | ... ET18: =IF(ET11<0,ET11*$F$4,0) -> 0 | EV18: x
E19: Fund Total | G19: =SUM(G17:G18) -> -1.0696049e+09 | H19: =SUM(H17:H18) -> 0 | I19: =SUM(I17:I18) -> 0 | J19: =SUM(J17:J18) -> 0 | K19: =SUM(K17:K18) -> 0 | L19: =SUM(L17:L18) -> 0 | M19: =SUM(M17:M18) -> 0 | N19: =SUM(N17:N18) -> 0 | ... ET19: =SUM(ET17:ET18) -> 0 | EV19: x
EV20: x
EV21: x
E22: Level 1 | EV22: x
E23: =$E$5 -> Capital Partner | G23: =+G61 -> 0 | H23: =+H61 -> 39722194 | I23: =+I61 -> 62408662 | J23: =+J61 -> 80938043 | K23: =+K61 -> 86261537 | L23: =+L61 -> 91106342 | M23: =+M61 -> 11665779 | N23: =+N61 -> 89876539 | ... ET23: =+ET61 -> 0 | EV23: x
E24: =$E$4 -> Sponsor | G24: =G23/$F5*$F$4 -> 0 | H24: =H23/$F5*$F$4 -> 2090641.8 | I24: =I23/$F5*$F$4 -> 3284666.4 | J24: =J23/$F5*$F$4 -> 4259897 | K24: =K23/$F5*$F$4 -> 4540080.9 | L24: =L23/$F5*$F$4 -> 4795070.6 | M24: =M23/$F5*$F$4 -> 613988.36 | N24: =N23/$F5*$F$4 -> 4730344.1 | ... ET24: =ET23/$F5*$F$4 -> 0 | EV24: x
E25: Fund Total | G25: =SUM(G23:G24) -> 0 | H25: =SUM(H23:H24) -> 41812835 | I25: =SUM(I23:I24) -> 65693328 | J25: =SUM(J23:J24) -> 85197940 | K25: =SUM(K23:K24) -> 90801618 | L25: =SUM(L23:L24) -> 95901412 | M25: =SUM(M23:M24) -> 12279767 | N25: =SUM(N23:N24) -> 94606883 | ... ET25: =SUM(ET23:ET24) -> 0 | EV25: x
EV26: x
E27: Remaining Cash Flow | G27: =ROUND(IF(G$11>0,G11-G25,0),2) -> 0 | H27: =ROUND(IF(H$11>0,H11-H25,0),2) -> 0 | I27: =ROUND(IF(I$11>0,I11-I25,0),2) -> 0 | J27: =ROUND(IF(J$11>0,J11-J25,0),2) -> 0 | K27: =ROUND(IF(K$11>0,K11-K25,0),2) -> 0 | L27: =ROUND(IF(L$11>0,L11-L25,0),2) -> 0 | M27: =ROUND(IF(M$11>0,M11-M25,0),2) -> 0 | N27: =ROUND(IF(N$11>0,N11-N25,0),2) -> 0 | ... ET27: =ROUND(IF(ET$11>0,ET11-ET25,0),2) -> 0 | EV27: x
EV28: x
E29: Remaining Cash Flow After Superpref | G29: =IF(G27=0,0,G27) -> 0 | H29: =IF(H27=0,0,H27) -> 0 | I29: =IF(I27=0,0,I27) -> 0 | J29: =IF(J27=0,0,J27) -> 0 | K29: =IF(K27=0,0,K27) -> 0 | L29: =IF(L27=0,0,L27) -> 0 | M29: =IF(M27=0,0,M27) -> 0 | N29: =IF(N27=0,0,N27) -> 0 | ... ET29: =IF(ET27=0,0,ET27) -> 0 | EV29: x
EV30: x
E31: Level 2 | EV31: x
E32: =$E$5 -> Capital Partner | G32: =+G73 -> 0 | H32: =+H73 -> 0 | I32: =+I73 -> 0 | J32: =+J73 -> 0 | K32: =+K73 -> 0 | L32: =+L73 -> 0 | M32: =+M73 -> 0 | N32: =+N73 -> 0 | ... ET32: =+ET73 -> 0 | EV32: x
E33: =$E$4 -> Sponsor | G33: =G32/$H5*$H$4 -> 0 | H33: =H32/$H5*$H$4 -> 0 | I33: =I32/$H5*$H$4 -> 0 | J33: =J32/$H5*$H$4 -> 0 | K33: =K32/$H5*$H$4 -> 0 | L33: =L32/$H5*$H$4 -> 0 | M33: =M32/$H5*$H$4 -> 0 | N33: =N32/$H5*$H$4 -> 0 | ... ET33: =ET32/$H5*$H$4 -> 0 | EV33: x
E34: Fund Total | G34: =SUM(G32:G33) -> 0 | H34: =SUM(H32:H33) -> 0 | I34: =SUM(I32:I33) -> 0 | J34: =SUM(J32:J33) -> 0 | K34: =SUM(K32:K33) -> 0 | L34: =SUM(L32:L33) -> 0 | M34: =SUM(M32:M33) -> 0 | N34: =SUM(N32:N33) -> 0 | ... ET34: =SUM(ET32:ET33) -> 0 | EV34: x
EV35: x
E36: Remaining Cash Flow | G36: =G29-G34 -> 0 | H36: =H29-H34 -> 0 | I36: =I29-I34 -> 0 | J36: =J29-J34 -> 0 | K36: =K29-K34 -> 0 | L36: =L29-L34 -> 0 | M36: =M29-M34 -> 0 | N36: =N29-N34 -> 0 | ... ET36: =ET29-ET34 -> 0 | EV36: x
EV37: x
EV38: x
E39: Level 3 | EV39: x
E40: =$E$5 -> Capital Partner | G40: =G73 -> 0 | H40: =H36*$J$5 -> 0 | I40: =I36*$J$5 -> 0 | J40: =J36*$J$5 -> 0 | K40: =K36*$J$5 -> 0 | L40: =L36*$J$5 -> 0 | M40: =M36*$J$5 -> 0 | N40: =N36*$J$5 -> 0 | O40: =O36*$J$5 -> 0 | ... ET40: =ET36*$J$5 -> 0 | EV40: x
E41: =$E$4 -> Sponsor | G41: =G40/$J5*$J$4 -> 0 | H41: =H40/$J5*$J$4 -> 0 | I41: =I40/$J5*$J$4 -> 0 | J41: =J40/$J5*$J$4 -> 0 | K41: =K40/$J5*$J$4 -> 0 | L41: =L40/$J5*$J$4 -> 0 | M41: =M40/$J5*$J$4 -> 0 | N41: =N40/$J5*$J$4 -> 0 | ... ET41: =ET40/$J5*$J$4 -> 0 | EV41: x
E42: Fund Total | G42: =SUM(G40:G41) -> 0 | H42: =SUM(H40:H41) -> 0 | I42: =SUM(I40:I41) -> 0 | J42: =SUM(J40:J41) -> 0 | K42: =SUM(K40:K41) -> 0 | L42: =SUM(L40:L41) -> 0 | M42: =SUM(M40:M41) -> 0 | N42: =SUM(N40:N41) -> 0 | ... ET42: =SUM(ET40:ET41) -> 0 | EV42: x
EV43: x
E44: Remaining Cash Flow | G44: =G36-G42 -> 0 | H44: =H36-H42 -> 0 | I44: =I36-I42 -> 0 | J44: =J36-J42 -> 0 | K44: =K36-K42 -> 0 | L44: =L36-L42 -> 0 | M44: =M36-M42 -> 0 | N44: =N36-N42 -> 0 | ... ET44: =ET36-ET42 -> 0 | EV44: x
EV45: x
EV46: x
E47: Partnership Cash Flows | EV47: x
E48: =$E$5 -> Capital Partner | G48: =+G23+G32+G40+G17+(G27-G29) -> -1.0161247e+09 | H48: =+H23+H32+H40+H17+(H27-H29) -> 39722194 | I48: =+I23+I32+I40+I17+(I27-I29) -> 62408662 | J48: =+J23+J32+J40+J17+(J27-J29) -> 80938043 | K48: =+K23+K32+K40+K17+(K27-K29) -> 86261537 | L48: =+L23+L32+L40+L17+(L27-L29) -> 91106342 | M48: =+M23+M32+M40+M17+(M27-M29) -> 11665779 | N48: =+N23+N32+N40+N17+(N27-N29) -> 89876539 | ... ET48: =+ET23+ET32+ET40+ET17+(ET27-ET29) -> 0 | EV48: x
E49: =$E$4 -> Sponsor | G49: =+G24+G33+G41+G18 -> -53480246 | H49: =+H24+H33+H41+H18 -> 2090641.8 | I49: =+I24+I33+I41+I18 -> 3284666.4 | J49: =+J24+J33+J41+J18 -> 4259897 | K49: =+K24+K33+K41+K18 -> 4540080.9 | L49: =+L24+L33+L41+L18 -> 4795070.6 | M49: =+M24+M33+M41+M18 -> 613988.36 | N49: =+N24+N33+N41+N18 -> 4730344.1 | ... ET49: =+ET24+ET33+ET41+ET18 -> 0 | EV49: x
E50: Partnership Total | G50: =SUM(G48:G49) -> -1.0696049e+09 | H50: =SUM(H48:H49) -> 41812835 | I50: =SUM(I48:I49) -> 65693328 | J50: =SUM(J48:J49) -> 85197940 | K50: =SUM(K48:K49) -> 90801618 | L50: =SUM(L48:L49) -> 95901412 | M50: =SUM(M48:M49) -> 12279767 | N50: =SUM(N48:N49) -> 94606883 | ... ET50: =SUM(ET48:ET49) -> 0 | EV50: x
G51: =+ROUND(G50,2)=ROUND(G11,2) -> TRUE | H51: =+ROUND(H50,2)=ROUND(H11,2) -> TRUE | I51: =+ROUND(I50,2)=ROUND(I11,2) -> TRUE | J51: =+ROUND(J50,2)=ROUND(J11,2) -> TRUE | K51: =+ROUND(K50,2)=ROUND(K11,2) -> TRUE | L51: =+ROUND(L50,2)=ROUND(L11,2) -> TRUE | M51: =+ROUND(M50,2)=ROUND(M11,2) -> TRUE | N51: =+ROUND(N50,2)=ROUND(N11,2) -> TRUE | ... ET51: =+ROUND(ET50,2)=ROUND(ET11,2) -> TRUE | EV51: x
EV52: x
EV53: x
EV54: x
E55: Level 1 | F55: =G4 -> 0.1 | EV55: x
F56: =(1+F55)^(1/365) -> 1.0002612 | G56: =+G$8 -> 45292 | H56: =+H$8 -> 45657 | I56: =+I$8 -> 46022 | J56: =+J$8 -> 46387 | K56: =+K$8 -> 46752 | L56: =+L$8 -> 47118 | M56: =+M$8 -> 47483 | N56: =+N$8 -> 47848 | ... ET56: =+ET$8 -> 0 | EV56: x
E57: Beginning Balance | G57: 0 | H57: =+G62 -> -1.0161247e+09 | I57: =+H62 -> -1.0780149e+09 | J57: =+I62 -> -1.1234078e+09 | K57: =+J62 -> -1.1548105e+09 | L57: =+K62 -> -1.18403e+09 | M57: =+L62 -> -1.2116668e+09 | N57: =+M62 -> -1.3211677e+09 | O57: =+N62 -> -1.363408e+09 | ... ET57: =+ES62 -> -244.59898 | EV57: x
E58: Contributions | G58: =SUM(G$17) -> -1.0161247e+09 | H58: =SUM(H$17) -> 0 | I58: =SUM(I$17) -> 0 | J58: =SUM(J$17) -> 0 | K58: =SUM(K$17) -> 0 | L58: =SUM(L$17) -> 0 | M58: =SUM(M$17) -> 0 | N58: =SUM(N$17) -> 0 | ... ET58: =SUM(ET$17) -> 0 | EV58: x
E59: Accrued Return | G59: 0 | H59: =H57*$F$56^(H56-G56)-H57 -> -1.0161247e+08 | I59: =I57*$F$56^(I56-H56)-I57 -> -1.0780149e+08 | J59: =J57*$F$56^(J56-I56)-J57 -> -1.1234078e+08 | K59: =K57*$F$56^(K56-J56)-K57 -> -1.1548105e+08 | L59: =L57*$F$56^(L56-K56)-L57 -> -1.1874314e+08 | M59: =M57*$F$56^(M56-L56)-M57 -> -1.2116668e+08 | N59: =N57*$F$56^(N56-M56)-N57 -> -1.3211677e+08 | O59: =O57*$F$56^(O56-N56)-O57 -> -1.363408e+08 | ... ET59: =ET57*$F$56^(ET56-ES56)-ET57 -> 0 | EV59: x
E60: Subtotal | G60: =SUM(G57:G59) -> -1.0161247e+09 | H60: =SUM(H57:H59) -> -1.1177371e+09 | I60: =SUM(I57:I59) -> -1.1858164e+09 | J60: =SUM(J57:J59) -> -1.2357486e+09 | K60: =SUM(K57:K59) -> -1.2702916e+09 | L60: =SUM(L57:L59) -> -1.3027732e+09 | M60: =SUM(M57:M59) -> -1.3328335e+09 | N60: =SUM(N57:N59) -> -1.4532845e+09 | ... ET60: =SUM(ET57:ET59) -> -244.59898 | EV60: x
E61: Level 1 Distribution | G61: 0 | H61: =IF(MIN(-H60,H11*$F$5)<0,0,MIN(-H60,H11*$F$5)) -> 39722194 | I61: =IF(MIN(-I60,I11*$F$5)<0,0,MIN(-I60,I11*$F$5)) -> 62408662 | J61: =IF(MIN(-J60,J11*$F$5)<0,0,MIN(-J60,J11*$F$5)) -> 80938043 | K61: =IF(MIN(-K60,K11*$F$5)<0,0,MIN(-K60,K11*$F$5)) -> 86261537 | L61: =IF(MIN(-L60,L11*$F$5)<0,0,MIN(-L60,L11*$F$5)) -> 91106342 | M61: =IF(MIN(-M60,M11*$F$5)<0,0,MIN(-M60,M11*$F$5)) -> 11665779 | N61: =IF(MIN(-N60,N11*$F$5)<0,0,MIN(-N60,N11*$F$5)) -> 89876539 | O61: =IF(MIN(-O60,O11*$F$5)<0,0,MIN(-O60,O11*$F$5)) -> 92810204 | ... ET61: =IF(MIN(-ET60,ET11*$F$5)<0,0,MIN(-ET60,ET11*$F$5)) -> 0 | EV61: x
E62: Ending Balance | G62: =+SUM(G60:G61) -> -1.0161247e+09 | H62: =+SUM(H60:H61) -> -1.0780149e+09 | I62: =+SUM(I60:I61) -> -1.1234078e+09 | J62: =+SUM(J60:J61) -> -1.1548105e+09 | K62: =+SUM(K60:K61) -> -1.18403e+09 | L62: =+SUM(L60:L61) -> -1.2116668e+09 | M62: =+SUM(M60:M61) -> -1.3211677e+09 | N62: =+SUM(N60:N61) -> -1.363408e+09 | ... ET62: =+SUM(ET60:ET61) -> -244.59898 | EV62: x
E63: IRR Check | F63: =XIRR(G63:ET63,G56:ET56) -> 0.095341793 | G63: =+G61+G58 -> -1.0161247e+09 | H63: =+H61+H58 -> 39722194 | I63: =+I61+I58 -> 62408662 | J63: =+J61+J58 -> 80938043 | K63: =+K61+K58 -> 86261537 | L63: =+L61+L58 -> 91106342 | M63: =+M61+M58 -> 11665779 | N63: =+N61+N58 -> 89876539 | ... ET63: =+ET61+ET58 -> 0 | EV63: x
EV64: x
EV65: x
E66: Level 2 | F66: =I4 -> 0.15 | EV66: x
F67: =(1+F66)^(1/365) -> 1.000383 | G67: =+G$8 -> 45292 | H67: =+H$8 -> 45657 | I67: =+I$8 -> 46022 | J67: =+J$8 -> 46387 | K67: =+K$8 -> 46752 | L67: =+L$8 -> 47118 | M67: =+M$8 -> 47483 | N67: =+N$8 -> 47848 | ... ET67: =+ET$8 -> 0 | EV67: x
E68: Beginning Balance | G68: 0 | H68: =+G74 -> -1.0161247e+09 | I68: =+H74 -> -1.1288212e+09 | J68: =+I74 -> -1.2357357e+09 | K68: =+J74 -> -1.340158e+09 | L68: =+K74 -> -1.4549202e+09 | M68: =+L74 -> -1.5826927e+09 | N68: =+M74 -> -1.8084308e+09 | O68: =+N74 -> -1.9898188e+09 | ... ET68: =+ES74 -> -9.3186409 | EV68: x
E69: Contributions | G69: =SUM(G$17) -> -1.0161247e+09 | H69: =SUM(H$17) -> 0 | I69: =SUM(I$17) -> 0 | J69: =SUM(J$17) -> 0 | K69: =SUM(K$17) -> 0 | L69: =SUM(L$17) -> 0 | M69: =SUM(M$17) -> 0 | N69: =SUM(N$17) -> 0 | ... ET69: =SUM(ET$17) -> 0 | EV69: x
E70: Accrued Return | G70: 0 | H70: =H68*$F$67^(H67-G67)-H68 -> -1.524187e+08 | I70: =I68*$F$67^(I67-H67)-I68 -> -1.6932318e+08 | J70: =J68*$F$67^(J67-I67)-J68 -> -1.8536035e+08 | K70: =K68*$F$67^(K67-J67)-K68 -> -2.010237e+08 | L70: =L68*$F$67^(L67-K67)-L68 -> -2.1887882e+08 | M70: =M68*$F$67^(M67-L67)-M68 -> -2.374039e+08 | N70: =N68*$F$67^(N67-M67)-N68 -> -2.7126462e+08 | O70: =O68*$F$67^(O67-N67)-O68 -> -2.9847283e+08 | ... ET70: =ET68*$F$67^(ET67-ES67)-ET68 -> 0 | EV70: x
E71: Level 1 Distribution | G71: =+G68*$F$55 -> 0 | H71: =+H61 -> 39722194 | I71: =+I61 -> 62408662 | J71: =+J61 -> 80938043 | K71: =+K61 -> 86261537 | L71: =+L61 -> 91106342 | M71: =+M61 -> 11665779 | N71: =+N61 -> 89876539 | O71: =+O61 -> 92810204 | ... ET71: =+ET61 -> 0 | EV71: x
E72: Subtotal | G72: =SUM(G68:G71) -> -1.0161247e+09 | H72: =SUM(H68:H71) -> -1.1288212e+09 | I72: =SUM(I68:I71) -> -1.2357357e+09 | J72: =SUM(J68:J71) -> -1.340158e+09 | K72: =SUM(K68:K71) -> -1.4549202e+09 | L72: =SUM(L68:L71) -> -1.5826927e+09 | M72: =SUM(M68:M71) -> -1.8084308e+09 | N72: =SUM(N68:N71) -> -1.9898188e+09 | ... ET72: =SUM(ET68:ET71) -> -9.3186409 | EV72: x
E73: Level 2 Distribution | G73: 0 | H73: =IF(MIN(-H72,H29*$H$5)<0,0,MIN(-H72,H29*$H$5)) -> 0 | I73: =IF(MIN(-I72,I29*$H$5)<0,0,MIN(-I72,I29*$H$5)) -> 0 | J73: =IF(MIN(-J72,J29*$H$5)<0,0,MIN(-J72,J29*$H$5)) -> 0 | K73: =IF(MIN(-K72,K29*$H$5)<0,0,MIN(-K72,K29*$H$5)) -> 0 | L73: =IF(MIN(-L72,L29*$H$5)<0,0,MIN(-L72,L29*$H$5)) -> 0 | M73: =IF(MIN(-M72,M29*$H$5)<0,0,MIN(-M72,M29*$H$5)) -> 0 | N73: =IF(MIN(-N72,N29*$H$5)<0,0,MIN(-N72,N29*$H$5)) -> 0 | O73: =IF(MIN(-O72,O29*$H$5)<0,0,MIN(-O72,O29*$H$5)) -> 0 | ... ET73: =IF(MIN(-ET72,ET29*$H$5)<0,0,MIN(-ET72,ET29*$H$5)) -> 0 | EV73: x
E74: Ending Balance | G74: =+SUM(G72:G73) -> -1.0161247e+09 | H74: =+SUM(H72:H73) -> -1.1288212e+09 | I74: =+SUM(I72:I73) -> -1.2357357e+09 | J74: =+SUM(J72:J73) -> -1.340158e+09 | K74: =+SUM(K72:K73) -> -1.4549202e+09 | L74: =+SUM(L72:L73) -> -1.5826927e+09 | M74: =+SUM(M72:M73) -> -1.8084308e+09 | N74: =+SUM(N72:N73) -> -1.9898188e+09 | ... ET74: =+SUM(ET72:ET73) -> -9.3186409 | EV74: x
E75: IRR Check | F75: =XIRR(G75:ET75,G67:ET67) -> 0.095341793 | G75: =+G73+G71+G69 -> -1.0161247e+09 | H75: =+H73+H71+H69 -> 39722194 | I75: =+I73+I71+I69 -> 62408662 | J75: =+J73+J71+J69 -> 80938043 | K75: =+K73+K71+K69 -> 86261537 | L75: =+L73+L71+L69 -> 91106342 | M75: =+M73+M71+M69 -> 11665779 | N75: =+N73+N71+N69 -> 89876539 | ... ET75: =+ET73+ET71+ET69 -> 0 | EV75: x

Sheet PASTE ARGUS EXPORTS>>>

Sheet Argus Cash Flow Drop
B1: PASTE IN CELL B2 | C1: 1 | D1: 2 | E1: 3 | F1: 4 | G1: 5 | H1: 6 | I1: 7 | J1: 8 | K1: 9 | L1: 10 | M1: 11
A2: PASTE IN CELL B2 >> | B2: Cash Flow
B3: The Empire State Building (Final Valuation) (Amounts in USD)
B4: Jan, 2024 through Dec, 2034
B5: 1/23/2026 10:52:08 AM
C7: Forecast | D7: Forecast | E7: Forecast | F7: Forecast | G7: Forecast | H7: Forecast | I7: Forecast | J7: Forecast | K7: Forecast | L7: Forecast | M7: Forecast | N7: Forecast
C9: Year 1 | D9: Year 2 | E9: Year 3 | F9: Year 4 | G9: Year 5 | H9: Year 6 | I9: Year 7 | J9: Year 8 | K9: Year 9 | L9: Year 10 | M9: Year 11
B10: For the Years Ending | C10: Dec-2024 | D10: Dec-2025 | E10: Dec-2026 | F10: Dec-2027 | G10: Dec-2028 | H10: Dec-2029 | I10: Dec-2030 | J10: Dec-2031 | K10: Dec-2032 | L10: Dec-2033 | M10: Dec-2034 | N10: Total
A12: NORMALIZE OPERATING EXPENSES USING BY CATEGORIZING THEM TO PROPER EXPENSE ACCOUNT | B12: Rental Revenue
B13: Potential Base Rent | C13: 192730265 | D13: 196665836 | E13: 201172086 | F13: 203672189 | G13: 201866506 | H13: 189739704 | I13: 188872887 | J13: 191192600 | K13: 191761766 | L13: 194585931 | M13: 197724472 | N13: 2149984241
B14: Absorption & Turnover Vacancy | C14: -19906573 | D14: -14667121 | E14: -5159640 | F14: -4447950 | G14: -7092471 | H14: -17970691 | I14: -1492850 | J14: -1401642 | K14: -1555210 | L14: -636553 | M14: -7352362 | N14: -81683064
B15: Free Rent | C15: -6047431 | D15: -5519907 | E15: -4347120 | F15: -2773989 | G15: -2060532 | H15: -9599230 | I15: -859887 | J15: -928928 | K15: -897880 | L15: -588828 | M15: -2382661 | N15: -36006392
B16: Scheduled Base Rent | C16: 166776261 | D16: 176478808 | E16: 191665326 | F16: 196450250 | G16: 192713503 | H16: 162169782 | I16: 186520150 | J16: 188862030 | K16: 189308676 | L16: 193360550 | M16: 187989449 | N16: 2032294785
B17: Total Rental Revenue | C17: 166776261 | D17: 176478808 | E17: 191665326 | F17: 196450250 | G17: 192713503 | H17: 162169782 | I17: 186520150 | J17: 188862030 | K17: 189308676 | L17: 193360550 | M17: 187989449 | N17: 2032294785
B19: Other Tenant Revenue
B20: Total Expense Recoveries | C20: 10664704 | D20: 12357653 | E20: 13921960 | F20: 14912340 | G20: 15685452 | H20: 11651807 | I20: 13941425 | J20: 15633018 | K20: 18116768 | L20: 20183830 | M20: 20489924 | N20: 167558881
B21: Total Other Tenant Revenue | C21: 10664704 | D21: 12357653 | E21: 13921960 | F21: 14912340 | G21: 15685452 | H21: 11651807 | I21: 13941425 | J21: 15633018 | K21: 18116768 | L21: 20183830 | M21: 20489924 | N21: 167558881
B23: Total Tenant Revenue | C23: 177440965 | D23: 188836461 | E23: 205587287 | F23: 211362590 | G23: 208398955 | H23: 173821589 | I23: 200461575 | J23: 204495048 | K23: 207425443 | L23: 213544380 | M23: 208479373 | N23: 2199853666
B25: Potential Gross Revenue | C25: 177440965 | D25: 188836461 | E25: 205587287 | F25: 211362590 | G25: 208398955 | H25: 173821589 | I25: 200461575 | J25: 204495048 | K25: 207425443 | L25: 213544380 | M25: 208479373 | N25: 2199853666
B27: Vacancy & Credit Loss
B28: Vacancy Allowance | C28: -1439303 | D28: -6042782 | E28: -15915053 | F28: -17133104 | G28: -14523799 | H28: -5377765 | I28: -18702592 | J28: -19188027 | K28: -19342855 | L28: -20781540 | M28: -14230812 | N28: -152677631
B29: Credit Loss | C29: -1774410 | D29: -1888365 | E29: -2055873 | F29: -2113626 | G29: -2083990 | H29: -1738216 | I29: -2004616 | J29: -2044950 | K29: -2074254 | L29: -2135444 | M29: -2084794 | N29: -21998537
B30: Total Vacancy & Credit Loss | C30: -3213712 | D30: -7931146 | E30: -17970926 | F30: -19246730 | G30: -16607789 | H30: -7115980 | I30: -20707208 | J30: -21232978 | K30: -21417109 | L30: -22916984 | M30: -16315605 | N30: -174676168
B32: Effective Gross Revenue | C32: 174227253 | D32: 180905315 | E32: 187616361 | F32: 192115860 | G32: 191791166 | H32: 166705609 | I32: 179754367 | J32: 183262070 | K32: 186008334 | L32: 190627396 | M32: 192163767 | N32: 2025177498
B34: Operating Expenses
A35: REAL ESTATE TAXES | B35: REAL ESTATE TAXES | C35: 43020000 | D35: 43880400 | E35: 44758008 | F35: 45653168 | G35: 46566232 | H35: 47497556 | I35: 48447507 | J35: 49416457 | K35: 50404787 | L35: 51412882 | M35: 52441140 | N35: 523498137
A36: INSURANCE | B36: INSURANCE | C36: 3398366 | D36: 3466333 | E36: 3535660 | F36: 3606373 | G36: 3678501 | H36: 3752071 | I36: 3827112 | J36: 3903654 | K36: 3981727 | L36: 4061362 | M36: 4142589 | N36: 41353750
A37: UTILITES | B37: UTILITIES | C37: 5488270 | D37: 5806542 | E37: 6269198 | F37: 6427715 | G37: 6463487 | H37: 6227235 | I37: 6933606 | J37: 7079388 | K37: 7217229 | L37: 7388904 | M37: 7289734 | N37: 72591307
A38: CAM | B38: REPAIRS AND MAINTENANCE | C38: 9335099 | D38: 9706005 | E38: 10206262 | F38: 10439659 | G38: 10566484 | H38: 10454894 | I38: 11178005 | J38: 11407846 | K38: 11632693 | L38: 11889492 | M38: 11909117 | N38: 118725556
A39: MGMT FEE | B39: MANAGEMENT FEES | C39: 5226818 | D39: 5427159 | E39: 5628491 | F39: 5763476 | G39: 5753735 | H39: 5001168 | I39: 5392631 | J39: 5497862 | K39: 5580250 | L39: 5718822 | M39: 5764913 | N39: 60755325
A40: CAM | B40: PAYROLL AND BENEFITS | C40: 7723559 | D40: 7878030 | E40: 8035591 | F40: 8196303 | G40: 8360229 | H40: 8527434 | I40: 8697982 | J40: 8871942 | K40: 9049381 | L40: 9230368 | M40: 9414976 | N40: 93985795
A41: CAM | B41: ADVERTISING AND MARKETING | C41: 1430000 | D41: 1458600 | E41: 1487772 | F41: 1517527 | G41: 1547878 | H41: 1578836 | I41: 1610412 | J41: 1642621 | K41: 1675473 | L41: 1708982 | M41: 1743162 | N41: 17401263
A42: CAM | B42: SECURITY | C42: 5318177 | D42: 5470535 | E42: 5656385 | F42: 5776821 | G42: 5871891 | H42: 5908699 | I42: 6155217 | J42: 6279890 | K42: 6404661 | L42: 6538783 | M42: 6615085 | N42: 65996143
A43: CAM | B43: JANITORIAL | C43: 6038419 | D43: 6159187 | E43: 6282371 | F43: 6408019 | G43: 6536179 | H43: 6666903 | I43: 6800241 | J43: 6936245 | K43: 7074970 | L43: 7216470 | M43: 7360799 | N43: 73479803
B44: Total Operating Expenses | C44: 86978707 | D44: 89252793 | E44: 91859738 | F44: 93789062 | G44: 95344614 | H44: 95614795 | I44: 99042713 | J44: 101035906 | K44: 103021171 | L44: 105166066 | M44: 106681515 | N44: 1067787079
B46: Net Operating Income | C46: 87248546 | D46: 91652523 | E46: 95756623 | F46: 98326798 | G46: 96446552 | H46: 71090813 | I46: 80711654 | J46: 82226165 | K46: 82987163 | L46: 85461330 | M46: 85482253 | N46: 957390419
B48: Leasing Costs
B49: Tenant Improvements | C49: 34949871 | D49: 22950092 | E49: 13696597 | F49: 10184088 | G49: 8652727 | H49: 53012645 | I49: 3063045 | J49: 3405628 | K49: 2850373 | L49: 1905593 | M49: 11960829 | N49: 166631488
B50: Leasing Commissions | C50: 17396760 | D50: 11767357 | E50: 7504618 | F50: 5017969 | G50: 4279690 | H50: 22385292 | I50: 1668221 | J50: 1832477 | K50: 1505407 | L50: 960270 | M50: 6384266 | N50: 80702329
B51: Total Leasing Costs | C51: 52346631 | D51: 34717449 | E51: 21201215 | F51: 15202058 | G51: 12932417 | H51: 75397937 | I51: 4731266 | J51: 5238105 | K51: 4355780 | L51: 2865863 | M51: 18345096 | N51: 247333817
B53: Capital Expenditures
B54: Elevator Modernization | C54: 5633333 | D54: 5633333 | E54: 5633333 | F54: 0 | G54: 0 | H54: 0 | I54: 0 | J54: 0 | K54: 0 | L54: 0 | M54: 0 | N54: 16899999
B55: Corridor Updates | C55: 750000 | D55: 750000 | E55: 750000 | F55: 750000 | G55: 0 | H55: 0 | I55: 0 | J55: 0 | K55: 0 | L55: 0 | M55: 0 | N55: 3000000
B56: Restroom Updates | C56: 2000000 | D56: 2000000 | E56: 2000000 | F56: 2000000 | G56: 0 | H56: 0 | I56: 0 | J56: 0 | K56: 0 | L56: 0 | M56: 0 | N56: 8000000
B57: Furniturer Replacement | C57: 25000 | D57: 25500 | E57: 26010 | F57: 26530 | G57: 27061 | H57: 27602 | I57: 28154 | J57: 28717 | K57: 29291 | L57: 29877 | M57: 30475 | N57: 304218
B58: LED Lighting | C58: 2200000 | D58: 2200000 | E58: 2200000 | F58: 2200000 | G58: 2200000 | H58: 0 | I58: 0 | J58: 0 | K58: 0 | L58: 0 | M58: 0 | N58: 11000000
B59: Total Capital Expenditures | C59: 10608333 | D59: 10608833 | E59: 10609343 | F59: 4976530 | G59: 2227061 | H59: 27602 | I59: 28154 | J59: 28717 | K59: 29291 | L59: 29877 | M59: 30475 | N59: 39204217
B61: Total Leasing & Capital Costs | C61: 62954964 | D61: 45326282 | E61: 31810558 | F61: 20178588 | G61: 15159478 | H61: 75425539 | I61: 4759420 | J61: 5266822 | K61: 4385071 | L61: 2895740 | M61: 18375570 | N61: 286538033
B63: Cash Flow Before Debt Service | C63: 24293582 | D63: 46326240 | E63: 63946065 | F63: 78148210 | G63: 81287074 | H63: -4334726 | I63: 75952234 | J63: 76959342 | K63: 78602092 | L63: 82565590 | M63: 67106682 | N63: 670852386
B65: Cash Flow Available for Distribution | C65: 24293582 | D65: 46326240 | E65: 63946065 | F65: 78148210 | G65: 81287074 | H65: -4334726 | I65: 75952234 | J65: 76959342 | K65: 78602092 | L65: 82565590 | M65: 67106682 | N65: 670852386
B68: Tenant Occupancy Summary
B69: Occupied Area | C69: 2483380 | D69: 2575877 | E69: 2726587 | F69: 2740715 | G69: 2701929 | H69: 2552126 | I69: 2785902 | J69: 2788703 | K69: 2787256 | L69: 2797604 | M69: 2705937
B70: Vacant Area | C70: 325187 | D70: 232690 | E70: 81980 | F70: 67852 | G70: 106638 | H70: 256441 | I70: 22665 | J70: 19864 | K70: 21311 | L70: 10963 | M70: 102630
B71: Leased Area | C71: 2483380 | D71: 2575877 | E71: 2726587 | F71: 2740715 | G71: 2701929 | H71: 2552126 | I71: 2785902 | J71: 2788703 | K71: 2787256 | L71: 2797604 | M71: 2705937
B72: Building Area | C72: 2808567 | D72: 2808567 | E72: 2808567 | F72: 2808567 | G72: 2808567 | H72: 2808567 | I72: 2808567 | J72: 2808567 | K72: 2808567 | L72: 2808567 | M72: 2808567
A73: OCCUPANCY | B73: Average Occupancy Percentage | C73: 0.88421604 | D73: 0.91714992 | E73: 0.97081074 | F73: 0.97584097 | G73: 0.96203111 | H73: 0.90869332 | I73: 0.99193005 | J73: 0.99292729 | K73: 0.99241206 | L73: 0.9960965 | M73: 0.96345829

Sheet Rent Roll Drop
A1: PASTE IN COLUMN B>> | B1: Tenant Rent Roll
A2: =IF(E2="Contract",1,0) -> 0 | B2: The Empire State Building (Final Valuation) (Amounts in USD)
A3: =IF(E3="Contract",1,0) -> 0 | B3: Jan, 2024 through Dec, 2024
A4: =IF(E4="Contract",1,0) -> 0 | B4: Grouped By - None
A5: =IF(E5="Contract",1,0) -> 0 | B5: 1/23/2026 10:53:12 AM
A6: =IF(E6="Contract",1,0) -> 0
A7: =IF(E7="Contract",1,0) -> 0 | I7: Lease | J7: Lease | K7: Potential | L7: Absorption & | M7: Free | N7: Scheduled | O7: Miscellaneous | P7: CPI | Q7: Percentage | R7: Expense | S7: Potential | T7: Tenant | U7: Leasing | V7: Tenant | W7: Net
A8: =IF(E8="Contract",1,0) -> 0 | B8: Tenant Name | C8: Suite | D8: Lease Type | E8: Lease Status | F8: Credit Tenants | G8: Tenant Status | H8: Area | I8: Start Date | J8: End Date | K8: Base Rent | L8: Turnover Rent | M8: Rent | N8: Base Rent | O8: Rent | P8: Increases | Q8: Rent | R8: Recoveries | S8: Gross Revenue | T8: Improvements | U8: Commissions | V8: Incentives | W8: Cash Flow
A9: =IF(E9="Contract",1,0) -> 0
A10: =IF(E10="Contract",1,0) -> 1 | B10: ABC Global Systems | C10: GRND | D10: Office | E10: Contract | H10: 1350 | I10: 2/1/2021 | J10: 12/31/2036 | K10: 70878 | L10: 0 | M10: 0 | N10: 70878 | O10: 0 | P10: 0 | Q10: 0 | R10: 5358 | S10: 76236 | T10: 0 | U10: 0 | V10: 0 | W10: 76236
A11: =IF(E11="Contract",1,0) -> 1 | B11: Acronym | C11: 65th | D11: Office | E11: Contract | H11: 1463 | I11: 2/1/2012 | J11: 9/30/2027 | K11: 65887 | L11: 0 | M11: 0 | N11: 65887 | O11: 0 | P11: 0 | Q11: 0 | R11: 5807 | S11: 71694 | T11: 0 | U11: 0 | V11: 0 | W11: 71694
A12: =IF(E12="Contract",1,0) -> 1 | B12: Adler Brothers | C12: 26th | D12: Office | E12: Contract | H12: 10076 | I12: 1/1/2024 | J12: 6/30/2052 | K12: 241824 | L12: 0 | M12: 40304 | N12: 201520 | O12: 0 | P12: 0 | Q12: 0 | R12: 0 | S12: 201520 | T12: 856460 | U12: 473343 | V12: 0 | W12: -1128283
A13: =IF(E13="Contract",1,0) -> 1 | B13: Agoda | C13: 47th | D13: Office | E13: Contract | H13: 3851 | I13: 8/1/2017 | J13: 1/31/2027 | K13: 172408 | L13: 0 | M13: 0 | N13: 172408 | O13: 0 | P13: 0 | Q13: 0 | R13: 34540 | S13: 206948 | T13: 0 | U13: 0 | V13: 0 | W13: 206948
A14: =IF(E14="Contract",1,0) -> 1 | B14: Air China International Corp | C14: 69th | D14: Office | E14: Contract | H14: 4588 | I14: 10/1/2021 | J14: 10/31/2028 | K14: 192369 | L14: 0 | M14: 0 | N14: 192369 | O14: 0 | P14: 0 | Q14: 0 | R14: 41150 | S14: 233519 | T14: 0 | U14: 0 | V14: 0 | W14: 233519
A15: =IF(E15="Contract",1,0) -> 1 | B15: AIR Communities | C15: 65th | D15: Office | E15: Contract | H15: 1794 | I15: 6/1/2017 | J15: 7/31/2028 | K15: 80450 | L15: 0 | M15: 0 | N15: 80450 | O15: 0 | P15: 0 | Q15: 0 | R15: 10709 | S15: 91159 | T15: 0 | U15: 0 | V15: 0 | W15: 91159
A16: =IF(E16="Contract",1,0) -> 1 | B16: ALAC | C16: 30th | D16: Office | E16: Contract | H16: 2839 | I16: 2/1/2017 | J16: 5/31/2032 | K16: 130775 | L16: 0 | M16: 0 | N16: 130775 | O16: 0 | P16: 0 | Q16: 0 | R16: 14107 | S16: 144882 | T16: 0 | U16: 0 | V16: 0 | W16: 144882
A17: =IF(E17="Contract",1,0) -> 1 | B17: Alberleen Group Llc | C17: 53rd | D17: Office | E17: Contract | H17: 2374 | I17: 3/1/2011 | J17: 10/31/2031 | K17: 115987 | L17: 0 | M17: 0 | N17: 115987 | O17: 0 | P17: 0 | Q17: 0 | R17: 0 | S17: 115987 | T17: 0 | U17: 0 | V17: 0 | W17: 115987
A18: =IF(E18="Contract",1,0) -> 1 | B18: Aldad & Associates, P.C. | C18: 43rd | D18: Office | E18: Contract | H18: 949 | I18: 4/1/2003 | J18: 12/31/2024 | K18: 48999 | L18: 0 | M18: 0 | N18: 48999 | O18: 0 | P18: 0 | Q18: 0 | R18: 2818 | S18: 51817 | T18: 0 | U18: 0 | V18: 0 | W18: 51817
A19: =IF(E19="Contract",1,0) -> 1 | B19: Algonquin Legal Associates | C19: 10th | D19: Office | E19: Contract | H19: 11134 | I19: 1/1/2024 | J19: 6/30/2037 | K19: 256082 | L19: 0 | M19: 42680 | N19: 213402 | O19: 0 | P19: 0 | Q19: 0 | R19: 0 | S19: 213402 | T19: 612370 | U19: 218362 | V19: 0 | W19: -617330
A20: =IF(E20="Contract",1,0) -> 1 | B20: alliantgroup | C20: 52nd | D20: Office | E20: Contract | H20: 1371 | I20: 8/1/2011 | J20: 3/31/2026 | K20: 68258 | L20: 0 | M20: 0 | N20: 68258 | O20: 0 | P20: 0 | Q20: 0 | R20: 0 | S20: 68258 | T20: 0 | U20: 0 | V20: 0 | W20: 68258
A21: =IF(E21="Contract",1,0) -> 1 | B21: American Equity Partners Inc | C21: GRND | D21: Office | E21: Contract | H21: 500 | I21: 6/1/2022 | J21: 11/30/2027 | K21: 23873 | L21: 0 | M21: 0 | N21: 23873 | O21: 0 | P21: 0 | Q21: 0 | R21: 4485 | S21: 28358 | T21: 0 | U21: 0 | V21: 0 | W21: 28358
... A198: =IF(E198="Contract",1,0) -> 0 | B198: Big Blocks (2 of 6) | C198: Auto Lease-Up | D198: Office | E198: Speculative | H198: 46330 | I198: 7/1/2024 | J198: 6/30/2034 | K198: 2779800 | L198: 1389900 | M198: 926600 | N198: 463300 | O198: 0 | P198: 0 | Q198: 0 | R198: 0 | S198: 463300 | T198: 2779800 | U198: 1689376 | V198: 0 | W198: -4005876
A199: =IF(E199="Contract",1,0) -> 0 | B199: Big Blocks (3 of 6) | C199: Auto Lease-Up | D199: Office | E199: Speculative | I199: 1/1/2025 | J199: 12/31/2034
A200: =IF(E200="Contract",1,0) -> 0 | B200: Big Blocks (4 of 6) | C200: Auto Lease-Up | D200: Office | E200: Speculative | I200: 7/1/2025 | J200: 6/30/2035
A201: =IF(E201="Contract",1,0) -> 0 | B201: Big Blocks (5 of 6) | C201: Auto Lease-Up | D201: Office | E201: Speculative | I201: 1/1/2026 | J201: 12/31/2035
A202: =IF(E202="Contract",1,0) -> 0 | B202: Big Blocks (6 of 6) | C202: Auto Lease-Up | D202: Office | E202: Speculative | I202: 7/1/2026 | J202: 6/30/2036
A203: =IF(E203="Contract",1,0) -> 0 | B203: Spec Suites (1 of 4) | C203: Auto Lease-Up | D203: Office | E203: Speculative | H203: 13132 | I203: 1/1/2024 | J203: 12/31/2033 | K203: 919240 | L203: 0 | M203: 153207 | N203: 766033 | O203: 0 | P203: 0 | Q203: 0 | R203: 0 | S203: 766033 | T203: 1313200 | U203: 567845 | V203: 0 | W203: -1115011
A204: =IF(E204="Contract",1,0) -> 0 | B204: Spec Suites (2 of 4) | C204: Auto Lease-Up | D204: Office | E204: Speculative | H204: 13132 | I204: 4/1/2024 | J204: 3/31/2034 | K204: 919240 | L204: 229810 | M204: 153207 | N204: 536223 | O204: 0 | P204: 0 | Q204: 0 | R204: 0 | S204: 536223 | T204: 1313200 | U204: 567845 | V204: 0 | W204: -1344821
A205: =IF(E205="Contract",1,0) -> 0 | B205: Spec Suites (3 of 4) | C205: Auto Lease-Up | D205: Office | E205: Speculative | H205: 13132 | I205: 7/1/2024 | J205: 6/30/2034 | K205: 919240 | L205: 459620 | M205: 153207 | N205: 306413 | O205: 0 | P205: 0 | Q205: 0 | R205: 0 | S205: 306413 | T205: 1313200 | U205: 567845 | V205: 0 | W205: -1574631
A206: =IF(E206="Contract",1,0) -> 0 | B206: Spec Suites (4 of 4) | C206: Auto Lease-Up | D206: Office | E206: Speculative | H206: 13132 | I206: 10/1/2024 | J206: 9/30/2034 | K206: 919240 | L206: 689430 | M206: 153207 | N206: 76603 | O206: 0 | P206: 0 | Q206: 0 | R206: 0 | S206: 76603 | T206: 1313200 | U206: 567845 | V206: 0 | W206: -1804441
A207: =IF(E207="Contract",1,0) -> 0 | B207: Full Floors (1 of 4) | C207: Auto Lease-Up | D207: Office | E207: Speculative | H207: 25294 | I207: 1/1/2024 | J207: 12/31/2033 | K207: 1517640 | L207: 0 | M207: 505880 | N207: 1011760 | O207: 0 | P207: 0 | Q207: 0 | R207: 0 | S207: 1011760 | T207: 1517640 | U207: 922320 | V207: 0 | W207: -1428200
A208: =IF(E208="Contract",1,0) -> 0 | B208: Full Floors (2 of 4) | C208: Auto Lease-Up | D208: Office | E208: Speculative | H208: 25294 | I208: 7/1/2024 | J208: 6/30/2034 | K208: 1517640 | L208: 758820 | M208: 505880 | N208: 252940 | O208: 0 | P208: 0 | Q208: 0 | R208: 0 | S208: 252940 | T208: 1517640 | U208: 922320 | V208: 0 | W208: -2187020
A209: =IF(E209="Contract",1,0) -> 0 | B209: Full Floors (3 of 4) | C209: Auto Lease-Up | D209: Office | E209: Speculative | I209: 1/1/2025 | J209: 12/31/2034
A210: =IF(E210="Contract",1,0) -> 0 | B210: Full Floors (4 of 4) | C210: Auto Lease-Up | D210: Office | E210: Speculative | I210: 7/1/2025 | J210: 6/30/2035
A211: =IF(E211="Contract",1,0) -> 0 | B211: Retail (1 of 3) | C211: Auto Lease-Up | D211: Office | E211: Speculative | H211: 7903 | I211: 1/1/2024 | J211: 12/31/2030 | K211: 553210 | L211: 0 | M211: 92202 | N211: 461008 | O211: 0 | P211: 0 | Q211: 0 | R211: 244749 | S211: 705757 | T211: 355635 | U211: 233904 | V211: 0 | W211: 116218
A212: =IF(E212="Contract",1,0) -> 0 | B212: Retail (2 of 3) | C212: Auto Lease-Up | D212: Office | E212: Speculative | H212: 7903 | I212: 4/1/2024 | J212: 3/31/2031 | K212: 553210 | L212: 138303 | M212: 92202 | N212: 322706 | O212: 0 | P212: 0 | Q212: 0 | R212: 183561 | S212: 506267 | T212: 355635 | U212: 233904 | V212: 0 | W212: -83272
A213: =IF(E213="Contract",1,0) -> 0 | B213: Retail (3 of 3) | C213: Auto Lease-Up | D213: Office | E213: Speculative | H213: 7902 | I213: 7/1/2024 | J213: 6/30/2031 | K213: 553140 | L213: 276570 | M213: 92190 | N213: 184380 | O213: 0 | P213: 0 | Q213: 0 | R213: 122359 | S213: 306739 | T213: 355590 | U213: 233874 | V213: 0 | W213: -282725
A214: =IF(E214="Contract",1,0) -> 0
A215: =IF(E215="Contract",1,0) -> 0 | B215: Total | H215: 2572667 | K215: 178576265 | L215: 5752573 | M215: 6047431 | N215: 166776261 | O215: 0 | P215: 0 | Q215: 0 | R215: 10664704 | S215: 177440965 | T215: 34949871 | U215: 17396760 | V215: 0 | W215: 125094334
A216: =IF(E216="Contract",1,0) -> 0
A217: =IF(E217="Contract",1,0) -> 0
A218: =IF(E218="Contract",1,0) -> 0
A219: =IF(E219="Contract",1,0) -> 0
A220: =IF(E220="Contract",1,0) -> 0
A221: =IF(E221="Contract",1,0) -> 0
A222: =IF(E222="Contract",1,0) -> 0
A223: =IF(E223="Contract",1,0) -> 0
A224: =IF(E224="Contract",1,0) -> 0
A225: =IF(E225="Contract",1,0) -> 0
A226: =IF(E226="Contract",1,0) -> 0
A227: =IF(E227="Contract",1,0) -> 0
... A381: =IF(E381="Contract",1,0) -> 0
A382: =IF(B382=" Total",B382,"")
A383: =IF(B383=" Total",B383,"")
A384: =IF(B384=" Total",B384,"")
A385: =IF(B385=" Total",B385,"")
A386: =IF(B386=" Total",B386,"")
A387: =IF(B387=" Total",B387,"")
A388: =IF(B388=" Total",B388,"")
A389: =IF(B389=" Total",B389,"")
A390: =IF(B390=" Total",B390,"")
A391: =IF(B391=" Total",B391,"")
A392: =IF(B392=" Total",B392,"")
A393: =IF(B393=" Total",B393,"")
... A929: =IF(B929=" Total",B929,"")

Sheet CONFIG
A4: PROFORMA ROLLUP DATA VALIDATION
A5: REAL ESTATE TAXES
A6: INSURANCE
A7: UTILITES
A8: CAM
A9: MGMT FEE
A10: OCCUPANCY
A11: OTHER INCOME
